Workbook

Sheet readme
A2: url | B2: 該則 Facebook 貼文的原始連結（URL）
A3: user_name | B3: 貼文發文者或粉絲專頁的名稱
A4: title | B4: 貼文的標題（部分分享連結或網誌型貼文才會有，一般純文字貼文，若無標題則空着
A5: text | B5: 貼文的內文完整文字內容
A6: time | B6: 貼文發布的時間
A7: video_url_one | B7: 貼文中所包含的影片連結，若無影片則空着
A8: photo_url_one | B8: 貼文中所包含的圖片連結（第一張），若無圖片則空着
A9: emotion_basic | B9: 貼文 的基本情緒傾向，例如：中性、正面、負面
A10: emotion_detailed | B10: 貼文 更細緻的情緒或語氣分類，例如：開心 / 滿意 / 期待 / 陳述 / 疑問 / 生氣 / 失望 / 驚
A11: theme | B11: 貼文討論的核心主題，例如：收費/價錢 、資訊分享、服務/投訴
A12: info_value | B12: 貼文的目的或價值分類，例如：有行動意向 / 純分享 / 求助 / 廣告
A13: ev_relevance | B13: 貼文與電動車（EV）的相關程度，例如：直接相關、間接相關、完全無關
... A20: sharesCount | B20: 該則貼文被分享的次數

Sheet 香港電動車充電資訊交流 1
A1: url | B1: user_name | C1: time | D1: title | E1: text | F1: video_url_one | G1: photo_url_one | H1: emotion_basic | I1: emotion_detailed | J1: theme | K1: info_value | L1: ev_relevance | M1: Location_Mentioned | N1: EV_Model_Mentioned | O1: Competitor_Brand | P1: Charging_Type | Q1: likesCount | R1: commentsCount | S1: sharesCount
A2: https://www.facebook.com/groups/366950274676457/permalink/1746279596743511/ | B2: RubyOtter8812 | C2: 46159 | E2: 荃灣京匯中心雙雄，經常拍充電位阻住人充電，人哋入嚟充電要比停車費㗎 | G2: https://scontent-sjc6-1.xx.fbcdn.net/v/t39.30808-6/700285578_4361105797501786_7241732557230475897_n.jpg?stp=cp6_dst-jpg_s720x720_tt6&_nc_cat=107&ccb=1-7&_nc_sid=aa7b47&_nc_ohc=1JNTXRdYvB8Q7kNvwFBKp_C&_nc_oc=Ado-o2GDHK2zKnuk4fZYQPQ7H3WqGlq7LZZMZgdN6fRSD0_L5DmXAOTfrdnUF3Pr5-s&_nc_zt=23&_nc_ht=scontent-sjc6-1.xx&_nc_gid=Il4HE2c_YBEaCjFZchdSuA&_nc_ss=72289&oh=00_Af5XMnXTEeg5cdfzHSCtjNLxQC-8s-xyxVJ7tKmDag9VCw&oe=6A10B6E7 | H2: 負面 | I2: 生氣 | J2: 排隊/打尖/霸位 | K2: 純分享 | L2: 直接相關 | M2: 荃灣京匯中心 | N2: null | O2: null | P2: null | Q2: 45 | R2: 28 | S2: 1
A3: https://www.facebook.com/groups/366950274676457/permalink/1746284526743018/ | B3: RubyOtter8812 | C3: 46159 | E3: 入荃灣京匯充電要諗清楚會唔會比油車霸住兩個位，管理處話呢兩部車經常霸住 | G3: https://scontent-sjc3-1.xx.fbcdn.net/v/t39.30808-6/702064419_4361111370834562_7186191070475268686_n.jpg?stp=cp6_dst-jpg_s720x720_tt6&_nc_cat=106&ccb=1-7&_nc_sid=aa7b47&_nc_ohc=zEPnfmkeyuIQ7kNvwGe4dOp&_nc_oc=AdrHaAG36nnXpccvu3QUMbFGqnjcQkoRl7UjPLkLQEeP6VrFIsar9z-VgudAqcIXCIk&_nc_zt=23&_nc_ht=scontent-sjc3-1.xx&_nc_gid=Il4HE2c_YBEaCjFZchdSuA&_nc_ss=72289&oh=00_Af450jqLkHgXj3U1Ub4vAnTIZheZlletniRBeFZq_FYGaA&oe=6A10976D | H3: 負面 | I3: 生氣 | J3: 排隊/打尖/霸位 | K3: 純分享 | L3: 直接相關 | M3: 荃灣京匯中心 | N3: null | O3: null | P3: null | Q3: 0 | R3: 1 | S3: 0
A4: https://www.facebook.com/groups/366950274676457/permalink/1746133363424801/ | B4: Gary Tsui 港車薈轉插 | C4: 46159 | E4: 港車薈PRO X轉插 X 阿維塔07 港車北上充電實況分享 無懼雨天 ，會員直接到珠海港車薈現場測試教學，液冷超充速度滿意！充電速度達到268KW，30%電量半小時充滿！ 越級顏值 悅目亦悅心 港車薈PRO X 讓你充電無憂！ 港車北上全方位服務 - 港車薈 #港車北上 #快充轉插 | H4: 正面 | I4: 滿意 | J4: 廣告/促銷 | K4: 廣告 | L4: 直接相關 | M4: null | N4: 阿維塔07 | O4: null | P4: 液冷超充,268kW | Q4: 0 | R4: 0 | S4: 0
A5: https://www.facebook.com/groups/366950274676457/permalink/1741215493916588/ | B5: Rex Lam | C5: 46153 | E5: 多點方便系統優越 | G5: https://scontent-atl3-2.xx.fbcdn.net/v/t39.30808-6/695032015_10242884265788812_5596688430513272657_n.jpg?stp=dst-jpg_s720x720_tt6&_nc_cat=104&ccb=1-7&_nc_sid=aa7b47&_nc_ohc=4Y_RXxuM76cQ7kNvwEY-eJ5&_nc_oc=AdpsQLr3zlzbLMjL8zLYGH0cn1q7zSn7wBm6alEcst5Z6yEGeG1-NRJaJ79NuUw_9Gs&_nc_zt=23&_nc_ht=scontent-atl3-2.xx&_nc_gid=edX6JYlN3__cukAu7Y3kBw&_nc_ss=7c289&oh=00_Af7TTRMpPMmNuIZn1zFJf5wFhe37VJCH8tfHgBrPwPqaZQ&oe=6A10C255 | H5: 正面 | I5: 滿意 | J5: 廣告/促銷 | K5: 廣告 | L5: 直接相關 | M5: null | N5: null | O5: null | P5: null | Q5: 2 | R5: 0 | S5: 0
A6: https://www.facebook.com/groups/366950274676457/permalink/1740287304009407/ | B6: 翡翠家 | C6: 46152 | E6: 承接 派傳單 貼海報 貼街招 掛橫額 掛banner 工商廈派傳單 印傳單 印街招 想宣傳又想慳荷包 平價宣傳 增加生意額 增加公司知名度 全港 貼海報 海報宣傳 印傳單 印海報 印街招 派傳單 街上派傳單 派發傳單 工商廈派傳單 商廈派傳單 工廈派傳單 屋苑入傳單 屋苑派傳單 屋苑入信箱 私樓派傳單 私樓入傳單 私樓入信箱 街頭派傳單 工商廈入傳單 工廈入傳單 商廈入傳單 派贈品 派sample 放易拉架 貼海報 貼街招 公屋派傳單 派通函 入通函 掛banner 放banner 合適行業 餐廳 補習社 茶飲 工程公司 太陽能公司 二餸飯 零售 美容儀器 裝修工程 防水工程 鋁窗工程 地產代理 保險代理 產品宣傳 品牌宣傳 電腦維修 食堂宣傳 宣傳易派傳單公司 WhatsApp: 94518014 https://api.whatsapp.com/send?phone=85294518014 承接全港各區派傳單.貼海報街招服務 我們的網站 https://myeasypromotion.com/ 我們的客戶 https://myeasypromotion.com/%e6%88%91%e5%80%91%e7%9a%84%e5%ae%a2%e6%88%b6/ 印傳單 https://myeasypromotion.com/%E5%8D%B0%E5%88%B7%E6%9C%8D%E5%8B%99/ Facebook 專頁 https://www.facebook.com/share/19Vz17DbxX/ 旋轉拍賣商店 https://carousell.app.link/me5wd2PN5Vb 海報宣傳 •••••••••••••••• 街上貼街招/貼海報 海報宣傳 全港各區, 每區300張起接, 提供影相為證服務. ⭕A4每區 300張起（每張$1.8） ⭕A5每區300張起(每張$1.2） ⭕A6每區300張起（每張$ 1) ⭕每張:A3/5 $ ; A2 /5.5 $ ; A1/ 6.5$ 每區 300張 貼村屋範圍街招海報 海報會全部拍攝相片 街招拍攝35張相片 . •••••••••••••••••• 洗樓入公屋 (上樓派傳單) 每張 0.65 1000張起 會拍攝150張相片 工商廈洗樓 舊式工商廈 會拍攝 35張相片證明 150元3座 130元 5座 120元 10座 110元20座 95元 30座 ⭕入村屋地下信箱 ：$270起接單 每區最少300戶起x9毫子 ⭕入唐樓地下信箱：$180 起接單 每區最少300戶起.x6毫子 汽車派傳單 派名片 的士或call 車平台公司或汽車美容公司 優惠 1.5 1張 放置 banner 掛banner 街頭放bannet 已申請地政署獲批放置 包取貨 10條以下 120元條 20條起 100元1條 要有放資詳細資料 code 會影相證明 偏遠地或 加 30元 1條 街上(舉牌)派傳單服務： 派傳單 2小時起 85元1小時 派傳單 3小時 80元 1小時 派傳單 4小時起 80元1小時 舉牌放傳單 加 10元1小時 加易拉架 加25元1小時 著制服 加 20元1小時 半山學校 加80元 1小時 派贈品 派飲品 派試用裝 派香水 派樣本 派sample 派公屋信箱 已申請入信箱 200戶 70元 每座 元 500戶 125元 750戶 188元 1000戶 250元. 最小 5 座起 已成功申請入公屋通函 誠意合作：WhatsApp: 94518014 派傳單，貼海報，貼街招 洗樓派傳單. 工廈商廈洗樓和私人屋苑,村屋，唐樓等入信箱服務. 印傳單 光粉紙 115克 210*285mm 2000張 需帶稿件 包本地送貨 460元 A4 尺寸 2000張 430元 A4 尺寸 4000張 660元 其後每 1000張 100元 A5 2000張 330元 A5 4000張 530元 其後每 1000張 100元 A6 2000張 300元 其後 每1000張80元 包送貨 印刷 A3. 海報 300張起 2.4元張 印刷 A2 海報 600張起 3元張 印刷 A1 海報 128克紙 600張起 3.4元 張 印刷 A1 海報 115克紙 700張 3元 #派傳單 #傳單員 #派傳單公司 #傳單印刷 #推廣員 #Promoter #印傳單 #派報公司 #投遞信箱 #發傳單 #發名片 #唐樓派傳單 #公屋派傳單 #貼海報 #貼街招 #貼貼紙 #全港專業洗樓派傳單 #派樓及印刷服務 #派傳單服務 #洗樓 #市場推廣 #宣傳 #派傳單服務 #海報宣傳 #派傳單 #推廣 #宣傳 #廣告 #Promotion #村屋派傳單 #車輛派傳單 #汽車派傳單 #村屋派信箱 #唐樓派信箱 #舊樓派傳單 #舊樓派信箱 # 工商廈派傳單 | F6: https://video-atl3-1.xx.fbcdn.net/o1/v/t2/f2/m366/AQMJ0hai10LJrYAmXaNgZxhI-uGdO9ELUW3-8FSzlNZPDym3IiEOsjMnb5XCbONCOdGjpquDRGSNGhniVrmdx1x7XxGQZJNP0zNB_rn1qBvrrw.mp4?_nc_cat=103&_nc_sid=5e9851&_nc_ht=video-atl3-1.xx.fbcdn.net&_nc_ohc=mQoetQy1Aw8Q7kNvwGgzQSs&efg=eyJ2ZW5jb2RlX3RhZyI6Inhwdl9wcm9ncmVzc2l2ZS5GQUNFQk9PSy4uQzMuMTA4OC5kYXNoX2gyNjQtYmFzaWMtZ2VuMl83MjBwIiwieHB2X2Fzc2V0X2lkIjo5Njk0ODQ0OTkwMDUyNzMsImFzc2V0X2FnZV9kYXlzIjo4LCJ2aV91c2VjYXNlX2lkIjoxMDEyMSwiZHVyYXRpb25fcyI6MTY0LCJ1cmxnZW5fc291cmNlIjoid3d3In0%3D&ccb=17-1&vs=7c17d4b9da931767&_nc_vs=HBksFQIYRWZiX2VwaGVtZXJhbC9GODQ0RUE2QjE4NkJBMzk4N0U5QjIyREUxMzk3RTBBMF9tdF8xX3ZpZGVvX2Rhc2hpbml0Lm1wNBUAAsgBEgAVAhhAZmJfcGVybWFuZW50L0Y5NEEwNUQ2RjZENzc1ODdGMjQxQzEwMkU5Qzc5REExX2F1ZGlvX2Rhc2hpbml0Lm1wNBUCAsgBEgAoABgAGwKIB3VzZV9vaWwBMRJwcm9ncmVzc2l2ZV9yZWNpcGUBMRUAACayve2ytu-4AxUCKAJDMywXQGSQo9cKPXEYGWRhc2hfaDI2NC1iYXNpYy1nZW4yXzcyMHARAHUCZZKeAQA&_nc_gid=edX6JYlN3__cukAu7Y3kBw&_nc_ss=7c289&_nc_zt=28&oh=00_Af5LnEZVP7vNRknLenbr_HgNli82ynpZASYKQJEFlZ0Dog&oe=6A109999&bitrate=184413&tag=dash_h264-basic-gen2_720p | H6: 中性 | I6: 陳述 | J6: 廣告/促銷 | K6: 廣告 | L6: 無關 | M6: null | N6: null | O6: null | P6: null | Q6: 0 | R6: 0 | S6: 0
A7: https://www.facebook.com/groups/366950274676457/permalink/1738832300821574/ | B7: 翡翠家 | C7: 46150 | E7: 承接 派傳單 貼海報 貼街招 掛橫額 掛banner 工商廈派傳單 印傳單 印街招 想宣傳又想慳荷包 平價宣傳 增加生意額 增加公司知名度 全港 貼海報 海報宣傳 印傳單 印海報 印街招 派傳單 街上派傳單 派發傳單 工商廈派傳單 商廈派傳單 工廈派傳單 屋苑入傳單 屋苑派傳單 屋苑入信箱 私樓派傳單 私樓入傳單 私樓入信箱 街頭派傳單 工商廈入傳單 工廈入傳單 商廈入傳單 派贈品 派sample 放易拉架 貼海報 貼街招 公屋派傳單 派通函 入通函 掛banner 放banner 合適行業 餐廳 補習社 茶飲 工程公司 太陽能公司 二餸飯 零售 美容儀器 裝修工程 防水工程 鋁窗工程 地產代理 保險代理 產品宣傳 品牌宣傳 電腦維修 食堂宣傳 宣傳易派傳單公司 WhatsApp: 94518014 https://api.whatsapp.com/send?phone=85294518014 承接全港各區派傳單.貼海報街招服務 我們的網站 https://myeasypromotion.com/ 我們的客戶 https://myeasypromotion.com/%e6%88%91%e5%80%91%e7%9a%84%e5%ae%a2%e6%88%b6/ 印傳單 https://myeasypromotion.com/%E5%8D%B0%E5%88%B7%E6%9C%8D%E5%8B%99/ Facebook 專頁 https://www.facebook.com/share/19Vz17DbxX/ 旋轉拍賣商店 https://carousell.app.link/me5wd2PN5Vb 海報宣傳 •••••••••••••••• 街上貼街招/貼海報 海報宣傳 全港各區, 每區300張起接, 提供影相為證服務. ⭕A4每區 300張起（每張$1.8） ⭕A5每區300張起(每張$1.2） ⭕A6每區300張起（每張$ 1) ⭕每張:A3/5 $ ; A2 /5.5 $ ; A1/ 6.5$ 每區 300張 貼村屋範圍街招海報 海報會全部拍攝相片 街招拍攝35張相片 . •••••••••••••••••• 洗樓入公屋 (上樓派傳單) 每張 0.65 1000張起 會拍攝150張相片 工商廈洗樓 舊式工商廈 會拍攝 35張相片證明 150元3座 130元 5座 120元 10座 110元20座 95元 30座 ⭕入村屋地下信箱 ：$270起接單 每區最少300戶起x9毫子 ⭕入唐樓地下信箱：$180 起接單 每區最少300戶起.x6毫子 汽車派傳單 派名片 的士或call 車平台公司或汽車美容公司 優惠 1.5 1張 放置 banner 掛banner 街頭放bannet 已申請地政署獲批放置 包取貨 10條以下 120元條 20條起 100元1條 要有放資詳細資料 code 會影相證明 偏遠地或 加 30元 1條 街上(舉牌)派傳單服務： 派傳單 2小時起 85元1小時 派傳單 3小時 80元 1小時 派傳單 4小時起 80元1小時 舉牌放傳單 加 10元1小時 加易拉架 加25元1小時 著制服 加 20元1小時 半山學校 加80元 1小時 派贈品 派飲品 派試用裝 派香水 派樣本 派sample 派公屋信箱 已申請入信箱 200戶 70元 每座 元 500戶 125元 750戶 188元 1000戶 250元. 最小 5 座起 已成功申請入公屋通函 誠意合作：WhatsApp: 94518014 派傳單，貼海報，貼街招 洗樓派傳單. 工廈商廈洗樓和私人屋苑,村屋，唐樓等入信箱服務. 印傳單 光粉紙 115克 210*285mm 2000張 需帶稿件 包本地送貨 460元 A4 尺寸 2000張 430元 A4 尺寸 4000張 660元 其後每 1000張 100元 A5 2000張 330元 A5 4000張 530元 其後每 1000張 100元 A6 2000張 300元 其後 每1000張80元 包送貨 印刷 A3. 海報 300張起 2.4元張 印刷 A2 海報 600張起 3元張 印刷 A1 海報 128克紙 600張起 3.4元 張 印刷 A1 海報 115克紙 700張 3元 #派傳單 #傳單員 #派傳單公司 #傳單印刷 #推廣員 #Promoter #印傳單 #派報公司 #投遞信箱 #發傳單 #發名片 #唐樓派傳單 #公屋派傳單 #貼海報 #貼街招 #貼貼紙 #全港專業洗樓派傳單 #派樓及印刷服務 #派傳單服務 #洗樓 #市場推廣 #宣傳 #派傳單服務 #海報宣傳 #派傳單 #推廣 #宣傳 #廣告 #Promotion #村屋派傳單 #車輛派傳單 #汽車派傳單 #村屋派信箱 #唐樓派信箱 #舊樓派傳單 #舊樓派信箱 # 工商廈派傳單 | F7: https://video-lga3-3.xx.fbcdn.net/o1/v/t2/f2/m366/AQOBSy4LumdSIuzk7S77hKz7jMfZ-PWOCmW81Iix0BhJYS0if6AGBCXlilSbXuuKmvX8tQqHsOfuZsoilCot9xxdcGCOGhrPFCfkeya8YmLnCg.mp4?_nc_cat=106&_nc_sid=5e9851&_nc_ht=video-lga3-3.xx.fbcdn.net&_nc_ohc=e__eJPlzw60Q7kNvwEC2fGp&efg=eyJ2ZW5jb2RlX3RhZyI6Inhwdl9wcm9ncmVzc2l2ZS5GQUNFQk9PSy4uQzMuMTA4OC5kYXNoX2gyNjQtYmFzaWMtZ2VuMl83MjBwIiwieHB2X2Fzc2V0X2lkIjo4MTIyOTg4OTQ5NjQzMDMsImFzc2V0X2FnZV9kYXlzIjo5LCJ2aV91c2VjYXNlX2lkIjoxMDEyMSwiZHVyYXRpb25fcyI6MTY0LCJ1cmxnZW5fc291cmNlIjoid3d3In0%3D&ccb=17-1&vs=157a8875f6384c0d&_nc_vs=HBksFQIYRWZiX2VwaGVtZXJhbC9GRDRBQzU4MjY1RDZFNDczRUJFNDdDOEEyRDU4ODNCMl9tdF8xX3ZpZGVvX2Rhc2hpbml0Lm1wNBUAAsgBEgAVAhhAZmJfcGVybWFuZW50LzEwNEMwMDkxQzQ2RjFCMENFRTNCNUYwMDc2MEYyRkFFX2F1ZGlvX2Rhc2hpbml0Lm1wNBUCAsgBEgAoABgAGwKIB3VzZV9vaWwBMRJwcm9ncmVzc2l2ZV9yZWNpcGUBMRUAACae2a-xgrLxAhUCKAJDMywXQGSQo9cKPXEYGWRhc2hfaDI2NC1iYXNpYy1nZW4yXzcyMHARAHUCZZKeAQA&_nc_gid=WCZZ1cfkRQjguD8a8YMU5Q&_nc_ss=72289&_nc_zt=28&oh=00_Af5j9SCzuY7jam_E-uc8MgnBOJnLPSVPUvMP6Z3b89O0OA&oe=6A10B532&bitrate=184413&tag=dash_h264-basic-gen2_720p | H7: 中性 | I7: 陳述 | J7: 其他 | K7: 廣告 | L7: 無關 | M7: null | N7: null | O7: null | P7: null | Q7: 0 | R7: 0 | S7: 0
A8: https://www.facebook.com/groups/366950274676457/permalink/1738538877517583/ | B8: Gary Tsui 港車薈轉插 | C8: 46150 | E8: 港車薈PRO X 轉插 X 現代IONIQ 5 珠海山姆#八達通液冷超充站 實況分享。 越級顏值 悅目亦悅心 港車薈PRO X 讓你充電無憂！ 選擇最優品牌，質量，售後，服務都是NO.1 #港車薈 #DC快充轉插 #CCS2 #GBT #電車北上 | H8: 正面 | I8: 滿意 | J8: 廣告/促銷 | K8: 廣告 | L8: 直接相關 | M8: 珠海山姆 | N8: 現代IONIQ 5 | O8: 港車薈 | P8: DC快充、超充、CCS2、GBT | Q8: 0 | R8: 0 | S8: 0
A9: https://www.facebook.com/groups/366950274676457/permalink/1738448004193337/ | B9: Simon Lee | C9: 46150 | E9: 大角咀 One Bedford Place 停車場， 終於有TESLA免費EV充電 | H9: 正面 | I9: 開心 | J9: 充電站設施/位置 | K9: 純分享 | L9: 直接相關 | M9: 大角咀 One Bedford Place | N9: null | O9: Tesla | P9: null | Q9: 2 | R9: 0 | S9: 0
A10: https://www.facebook.com/groups/366950274676457/permalink/1738332220871582/ | B10: Jack Chan | C10: 46149 | E10: 月租停車場終於減價 幫補吓保養、牌費都好 佐敦高臨停車場做月租優惠！(電動車) | H10: 正面 | I10: 滿意 | J10: 收費/價錢 | K10: 純分享 | L10: 間接相關 | M10: 佐敦高臨停車場 | N10: null | O10: null | P10: null | Q10: 16 | R10: 1 | S10: 0
A11: https://www.facebook.com/groups/366950274676457/permalink/1737987944239343/ | B11: 翡翠家 | C11: 46149 | E11: 承接 派傳單 貼海報 貼街招 掛橫額 掛banner 工商廈派傳單 印傳單 印街招 想宣傳又想慳荷包 平價宣傳 增加生意額 增加公司知名度 全港 貼海報 海報宣傳 印傳單 印海報 印街招 派傳單 街上派傳單 派發傳單 工商廈派傳單 商廈派傳單 工廈派傳單 屋苑入傳單 屋苑派傳單 屋苑入信箱 私樓派傳單 私樓入傳單 私樓入信箱 街頭派傳單 工商廈入傳單 工廈入傳單 商廈入傳單 派贈品 派sample 放易拉架 貼海報 貼街招 公屋派傳單 派通函 入通函 掛banner 放banner 合適行業 餐廳 補習社 茶飲 工程公司 太陽能公司 二餸飯 零售 美容儀器 裝修工程 防水工程 鋁窗工程 地產代理 保險代理 產品宣傳 品牌宣傳 電腦維修 食堂宣傳 宣傳易派傳單公司 WhatsApp: 94518014 https://api.whatsapp.com/send?phone=85294518014 承接全港各區派傳單.貼海報街招服務 我們的網站 https://myeasypromotion.com/ 我們的客戶 https://myeasypromotion.com/%e6%88%91%e5%80%91%e7%9a%84%e5%ae%a2%e6%88%b6/ 印傳單 https://myeasypromotion.com/%E5%8D%B0%E5%88%B7%E6%9C%8D%E5%8B%99/ Facebook 專頁 https://www.facebook.com/share/19Vz17DbxX/ 旋轉拍賣商店 https://carousell.app.link/me5wd2PN5Vb 海報宣傳 •••••••••••••••• 街上貼街招/貼海報 海報宣傳 全港各區, 每區300張起接, 提供影相為證服務. ⭕A4每區 300張起（每張$1.8） ⭕A5每區300張起(每張$1.2） ⭕A6每區300張起（每張$ 1) ⭕每張:A3/5 $ ; A2 /5.5 $ ; A1/ 6.5$ 每區 300張 貼村屋範圍街招海報 海報會全部拍攝相片 街招拍攝35張相片 . •••••••••••••••••• 洗樓入公屋 (上樓派傳單) 每張 0.65 1000張起 會拍攝150張相片 工商廈洗樓 舊式工商廈 會拍攝 35張相片證明 150元3座 130元 5座 120元 10座 110元20座 95元 30座 ⭕入村屋地下信箱 ：$270起接單 每區最少300戶起x9毫子 ⭕入唐樓地下信箱：$180 起接單 每區最少300戶起.x6毫子 汽車派傳單 派名片 的士或call 車平台公司或汽車美容公司 優惠 1.5 1張 放置 banner 掛banner 街頭放bannet 已申請地政署獲批放置 包取貨 10條以下 120元條 20條起 100元1條 要有放資詳細資料 code 會影相證明 偏遠地或 加 30元 1條 街上(舉牌)派傳單服務： 派傳單 2小時起 85元1小時 派傳單 3小時 80元 1小時 派傳單 4小時起 80元1小時 舉牌放傳單 加 10元1小時 加易拉架 加25元1小時 著制服 加 20元1小時 半山學校 加80元 1小時 派贈品 派飲品 派試用裝 派香水 派樣本 派sample 派公屋信箱 已申請入信箱 200戶 70元 每座 元 500戶 125元 750戶 188元 1000戶 250元. 最小 5 座起 已成功申請入公屋通函 誠意合作：WhatsApp: 94518014 派傳單，貼海報，貼街招 洗樓派傳單. 工廈商廈洗樓和私人屋苑,村屋，唐樓等入信箱服務. 印傳單 光粉紙 115克 210*285mm 2000張 需帶稿件 包本地送貨 460元 A4 尺寸 2000張 430元 A4 尺寸 4000張 660元 其後每 1000張 100元 A5 2000張 330元 A5 4000張 530元 其後每 1000張 100元 A6 2000張 300元 其後 每1000張80元 包送貨 印刷 A3. 海報 300張起 2.4元張 印刷 A2 海報 600張起 3元張 印刷 A1 海報 128克紙 600張起 3.4元 張 印刷 A1 海報 115克紙 700張 3元 #派傳單 #傳單員 #派傳單公司 #傳單印刷 #推廣員 #Promoter #印傳單 #派報公司 #投遞信箱 #發傳單 #發名片 #唐樓派傳單 #公屋派傳單 #貼海報 #貼街招 #貼貼紙 #全港專業洗樓派傳單 #派樓及印刷服務 #派傳單服務 #洗樓 #市場推廣 #宣傳 #派傳單服務 #海報宣傳 #派傳單 #推廣 #宣傳 #廣告 #Promotion #村屋派傳單 #車輛派傳單 #汽車派傳單 #村屋派信箱 #唐樓派信箱 #舊樓派傳單 #舊樓派信箱 # 工商廈派傳單 | F11: https://video-ord5-2.xx.fbcdn.net/o1/v/t2/f2/m366/AQO68B5K_trnqYX5MX0ve6hinrM5mfw3ijgJ0VZAIeurJFaHKgVmLVtCk__sP4JIUC1XrrAAKEFCRFSMQrKzl57AhCm5lfcgt46z2IBBC03yfw.mp4?_nc_cat=103&_nc_sid=5e9851&_nc_ht=video-ord5-2.xx.fbcdn.net&_nc_ohc=el9pftu8RG8Q7kNvwHTDBNS&efg=eyJ2ZW5jb2RlX3RhZyI6Inhwdl9wcm9ncmVzc2l2ZS5GQUNFQk9PSy4uQzMuMTA4OC5kYXNoX2gyNjQtYmFzaWMtZ2VuMl83MjBwIiwieHB2X2Fzc2V0X2lkIjoxNTQwODYwODUxMDA2NzIxLCJhc3NldF9hZ2VfZGF5cyI6MTAsInZpX3VzZWNhc2VfaWQiOjEwMTIxLCJkdXJhdGlvbl9zIjoxNjQsInVybGdlbl9zb3VyY2UiOiJ3d3cifQ%3D%3D&ccb=17-1&vs=456289e30dd5702d&_nc_vs=HBksFQIYRWZiX2VwaGVtZXJhbC8xMTQyN0NEQ0UxQUU0QTAzQUUwOTE2MUMyRURCMzlBRl9tdF8xX3ZpZGVvX2Rhc2hpbml0Lm1wNBUAAsgBEgAVAhhAZmJfcGVybWFuZW50LzVGNEUyMjU1OEE2OTdGOTFDQTQxMEFFOUNERjVBMkEwX2F1ZGlvX2Rhc2hpbml0Lm1wNBUCAsgBEgAoABgAGwKIB3VzZV9vaWwBMRJwcm9ncmVzc2l2ZV9yZWNpcGUBMRUAACaCtOH689m8BRUCKAJDMywXQGSQo9cKPXEYGWRhc2hfaDI2NC1iYXNpYy1nZW4yXzcyMHARAHUCZZKeAQA&_nc_gid=ytKkpwsqmUAL7DgRjBRMIw&_nc_ss=72289&_nc_zt=28&oh=00_Af6hQtEjN5mkfdllPGOs-0yihp-RNzjl27iT8hcr7vckyg&oe=6A109A1D&bitrate=184413&tag=dash_h264-basic-gen2_720p | H11: 中性 | I11: 陳述 | J11: 廣告/促銷 | K11: 廣告 | L11: 無關 | M11: null | N11: null | O11: null | P11: null | Q11: 0 | R11: 0 | S11: 0
A12: https://www.facebook.com/groups/366950274676457/permalink/1737587170946087/ | B12: Amuro Lee | C12: 46148 | E12: 1. 本田（Honda）於 2026 年 4 月 16 日正式在日本開啟全新純電車仔 Super-ONE （歐美稱為 Super-N）的預購活動，並預定於 5 月下旬正式上市。儘管官方尚未揭曉最終建議售價，但這款強調「純粹駕馭樂趣」的車款已在當地掀起搶購熱潮。根據日本經銷商的最新消息，Super-ONE 的預接訂單量遠超預期，目前的交車等候期已拉長至 5 到 6 個月，足見這款結合復古與運動性能車仔魅力驚人。#拍車新聞網 2. Super-ONE 的設計靈感源自 2024 年 Goodwood 速度嘉年華亮相的 Super EV Concept，並以此為基礎進行量產化。為了強化運動氣息，Super-ONE 採用了顯著外擴的輪拱與寬體設計，車寬來到 1,595mm，車長則延伸至 3,595mm，這意味著它已超越了日本傳統 K-Car（輕自動車）的尺碼限制，正式跨入乘用車（小型車）類別。外觀細節上，重新塑形的前泵把加入了直立式導流口，搭配專屬的紫色車身塗裝（可選黑色車頂）、15 吋啞光黑多輻式空力輪圈與車尾擾流尾翼，營造出宛如 80 年代 City Turbo II 再世的鋼砲神韻。 3. 動力表現更是 Super-ONE 的精髓所在，其研發目標是打破電動車枯燥乏味的既定印象。雖然採單馬達前驅配置，但在一般模式下具備 64 匹馬力，一旦按下方向盤上的「BOOST」模式按鈕，最大輸出將瞬間提升至 95 匹（70kW） 之譜。配合僅 1,090 公斤 的輕量化車身，Super-ONE 具備極為靈活且強勁的加速反應。為了提升感官沉浸感，本田更為其配置了主動式聲浪控制系統與模擬換檔功能，透過標配的 BOSE 高級音響系統 傳遞合成的引擎轟鳴聲，甚至在換檔點提供細微的震動回饋。 4. 座艙空間同樣展現「以駕駛為中心」的初衷，換裝了專屬運動化座椅，以類麂皮材質包覆提供極佳防滑效果。內裝配置包含 7 吋數位儀表與 9 吋中控螢幕，在 BOOST 模式下儀表會切換為專屬圖型顯示。而在實用性方面，受惠於薄型低重心電池布局，車輛具備 274 公里（WLTC 模式） 的續航里程，並支援 50kW 快充與 AC1500W 外部供電功能（V2L），兼顧了日常通勤便利與週末跑山樂趣。 | G12: https://scontent.fhkg10-2.fna.fbcdn.net/v/t39.30808-6/690650422_1413969480745884_1036797877813894995_n.jpg?stp=dst-jpg_p526x296_tt6&_nc_cat=108&ccb=1-7&_nc_sid=127cfc&_nc_ohc=Ijfwew97gxcQ7kNvwHTHbVQ&_nc_oc=AdozeuuiiipM4cUnBd3Wg80IXi2fU7Et-MbxL5L14lOKHLTGcrlE2EyGFBDT1OFa41g&_nc_zt=23&_nc_ht=scontent.fhkg10-2.fna&_nc_gid=hhm3hxkX8mxEimLjr45G8A&_nc_ss=7b2a8&oh=00_Af4wky3M62s95jwfhyvfQTxOKEepNNdsHHd7kzFUMVY88A&oe=6A12DDE7 | H12: 中性 | I12: 陳述 | J12: 安裝/硬件/技術 | K12: 純分享 | L12: 直接相關 | M12: 日本 | N12: Honda Super-ONE | O12: null | P12: 50kW 快充 | Q12: 1 | R12: 0 | S12: 0
A13: https://www.facebook.com/groups/366950274676457/permalink/1737096300995174/ | B13: 翡翠家 | C13: 46148 | E13: 承接 派傳單 貼海報 貼街招 掛橫額 掛banner 工商廈派傳單 印傳單 印街招 想宣傳又想慳荷包 平價宣傳 增加生意額 增加公司知名度 全港 貼海報 海報宣傳 印傳單 印海報 印街招 派傳單 街上派傳單 派發傳單 工商廈派傳單 商廈派傳單 工廈派傳單 屋苑入傳單 屋苑派傳單 屋苑入信箱 私樓派傳單 私樓入傳單 私樓入信箱 街頭派傳單 工商廈入傳單 工廈入傳單 商廈入傳單 派贈品 派sample 放易拉架 貼海報 貼街招 公屋派傳單 派通函 入通函 掛banner 放banner 合適行業 餐廳 補習社 茶飲 工程公司 太陽能公司 二餸飯 零售 美容儀器 裝修工程 防水工程 鋁窗工程 地產代理 保險代理 產品宣傳 品牌宣傳 電腦維修 食堂宣傳 宣傳易派傳單公司 WhatsApp: 94518014 https://api.whatsapp.com/send?phone=85294518014 承接全港各區派傳單.貼海報街招服務 我們的網站 https://myeasypromotion.com/ 我們的客戶 https://myeasypromotion.com/%e6%88%91%e5%80%91%e7%9a%84%e5%ae%a2%e6%88%b6/ 印傳單 https://myeasypromotion.com/%E5%8D%B0%E5%88%B7%E6%9C%8D%E5%8B%99/ Facebook 專頁 https://www.facebook.com/share/19Vz17DbxX/ 旋轉拍賣商店 https://carousell.app.link/me5wd2PN5Vb 海報宣傳 •••••••••••••••• 街上貼街招/貼海報 海報宣傳 全港各區, 每區300張起接, 提供影相為證服務. ⭕A4每區 300張起（每張$1.8） ⭕A5每區300張起(每張$1.2） ⭕A6每區300張起（每張$ 1) ⭕每張:A3/5 $ ; A2 /5.5 $ ; A1/ 6.5$ 每區 300張 貼村屋範圍街招海報 海報會全部拍攝相片 街招拍攝35張相片 . •••••••••••••••••• 洗樓入公屋 (上樓派傳單) 每張 0.65 1000張起 會拍攝150張相片 工商廈洗樓 舊式工商廈 會拍攝 35張相片證明 150元3座 130元 5座 120元 10座 110元20座 95元 30座 ⭕入村屋地下信箱 ：$270起接單 每區最少300戶起x9毫子 ⭕入唐樓地下信箱：$180 起接單 每區最少300戶起.x6毫子 汽車派傳單 派名片 的士或call 車平台公司或汽車美容公司 優惠 1.5 1張 放置 banner 掛banner 街頭放bannet 已申請地政署獲批放置 包取貨 10條以下 120元條 20條起 100元1條 要有放資詳細資料 code 會影相證明 偏遠地或 加 30元 1條 街上(舉牌)派傳單服務： 派傳單 2小時起 85元1小時 派傳單 3小時 80元 1小時 派傳單 4小時起 80元1小時 舉牌放傳單 加 10元1小時 加易拉架 加25元1小時 著制服 加 20元1小時 半山學校 加80元 1小時 派贈品 派飲品 派試用裝 派香水 派樣本 派sample 派公屋信箱 已申請入信箱 200戶 70元 每座 元 500戶 125元 750戶 188元 1000戶 250元. 最小 5 座起 已成功申請入公屋通函 誠意合作：WhatsApp: 94518014 派傳單，貼海報，貼街招 洗樓派傳單. 工廈商廈洗樓和私人屋苑,村屋，唐樓等入信箱服務. 印傳單 光粉紙 115克 210*285mm 2000張 需帶稿件 包本地送貨 460元 A4 尺寸 2000張 430元 A4 尺寸 4000張 660元 其後每 1000張 100元 A5 2000張 330元 A5 4000張 530元 其後每 1000張 100元 A6 2000張 300元 其後 每1000張80元 包送貨 印刷 A3. 海報 300張起 2.4元張 印刷 A2 海報 600張起 3元張 印刷 A1 海報 128克紙 600張起 3.4元 張 印刷 A1 海報 115克紙 700張 3元 #派傳單 #傳單員 #派傳單公司 #傳單印刷 #推廣員 #Promoter #印傳單 #派報公司 #投遞信箱 #發傳單 #發名片 #唐樓派傳單 #公屋派傳單 #貼海報 #貼街招 #貼貼紙 #全港專業洗樓派傳單 #派樓及印刷服務 #派傳單服務 #洗樓 #市場推廣 #宣傳 #派傳單服務 #海報宣傳 #派傳單 #推廣 #宣傳 #廣告 #Promotion #村屋派傳單 #車輛派傳單 #汽車派傳單 #村屋派信箱 #唐樓派信箱 #舊樓派傳單 #舊樓派信箱 # 工商廈派傳單 | F13: https://video.fagc3-2.fna.fbcdn.net/o1/v/t2/f2/m366/AQMr6smpiZg7OyGnCCy053TgiBlHOxtWY_lOS7uTJoofepUtkAqc75bUBFIulQTHRAzAk9kO6Yq5voWVXtrjJtmsQ6R5KnQXhxs_U0O6RhaNAw.mp4?_nc_cat=105&_nc_oc=AdrDpK6xnqPeyzfYGSF9W1s8qHLZw6zjRUomj11T3zeo_28RwGDl86i6BjrXB9ZGhQE&_nc_sid=5e9851&_nc_ht=video.fagc3-2.fna.fbcdn.net&_nc_ohc=JkbZJQRs-kMQ7kNvwHcTDzj&efg=eyJ2ZW5jb2RlX3RhZyI6Inhwdl9wcm9ncmVzc2l2ZS5GQUNFQk9PSy4uQzMuMTA4OC5kYXNoX2gyNjQtYmFzaWMtZ2VuMl83MjBwIiwieHB2X2Fzc2V0X2lkIjo5OTE3NzI2ODA0NTU4NzEsImFzc2V0X2FnZV9kYXlzIjoxMiwidmlfdXNlY2FzZV9pZCI6MTAxMjEsImR1cmF0aW9uX3MiOjE2NCwidXJsZ2VuX3NvdXJjZSI6Ind3dyJ9&ccb=17-1&vs=29abefa3b26a59a2&_nc_vs=HBksFQIYRWZiX2VwaGVtZXJhbC85NzQ0REVCMEMxOEJDNjM4OEU3MzM1MDQ5MTk4OEY5MV9tdF8xX3ZpZGVvX2Rhc2hpbml0Lm1wNBUAAsgBEgAVAhhAZmJfcGVybWFuZW50LzhDNDU1QjNBNjNBRUU0N0VBOEYzRTY0ODI0RDA4NjlEX2F1ZGlvX2Rhc2hpbml0Lm1wNBUCAsgBEgAoABgAGwKIB3VzZV9vaWwBMRJwcm9ncmVzc2l2ZV9yZWNpcGUBMRUAACb-moil4oDDAxUCKAJDMywXQGSQo9cKPXEYGWRhc2hfaDI2NC1iYXNpYy1nZW4yXzcyMHARAHUCZZKeAQA&_nc_gid=lalNyvLnisdorAjl4SJoBA&_nc_ss=72289&_nc_zt=28&oh=00_Af4PbcL39FSu-pQtQi43QV9LRD9K68K_2nwf8HtfZH_kWA&oe=6A10B97B&bitrate=184413&tag=dash_h264-basic-gen2_720p | H13: 中性 | I13: 陳述 | J13: 廣告/促銷 | K13: 廣告 | L13: 無關 | M13: null | N13: null | O13: null | P13: null | Q13: 0 | R13: 0 | S13: 0
A14: https://www.facebook.com/groups/366950274676457/permalink/1734463431258461/ | B14: 翡翠家 | C14: 46145 | E14: 承接 派傳單 貼海報 貼街招 掛橫額 掛banner 工商廈派傳單 印傳單 印街招 想宣傳又想慳荷包 平價宣傳 增加生意額 增加公司知名度 全港 貼海報 海報宣傳 印傳單 印海報 印街招 派傳單 街上派傳單 派發傳單 工商廈派傳單 商廈派傳單 工廈派傳單 屋苑入傳單 屋苑派傳單 屋苑入信箱 私樓派傳單 私樓入傳單 私樓入信箱 街頭派傳單 工商廈入傳單 工廈入傳單 商廈入傳單 派贈品 派sample 放易拉架 貼海報 貼街招 公屋派傳單 派通函 入通函 掛banner 放banner 合適行業 餐廳 補習社 茶飲 工程公司 太陽能公司 二餸飯 零售 美容儀器 裝修工程 防水工程 鋁窗工程 地產代理 保險代理 產品宣傳 品牌宣傳 電腦維修 食堂宣傳 宣傳易派傳單公司 WhatsApp: 94518014 https://api.whatsapp.com/send?phone=85294518014 承接全港各區派傳單.貼海報街招服務 我們的網站 https://myeasypromotion.com/ 我們的客戶 https://myeasypromotion.com/%e6%88%91%e5%80%91%e7%9a%84%e5%ae%a2%e6%88%b6/ 印傳單 https://myeasypromotion.com/%E5%8D%B0%E5%88%B7%E6%9C%8D%E5%8B%99/ Facebook 專頁 https://www.facebook.com/share/19Vz17DbxX/ 旋轉拍賣商店 https://carousell.app.link/me5wd2PN5Vb 海報宣傳 •••••••••••••••• 街上貼街招/貼海報 海報宣傳 全港各區, 每區300張起接, 提供影相為證服務. ⭕A4每區 300張起（每張$1.8） ⭕A5每區300張起(每張$1.2） ⭕A6每區300張起（每張$ 1) ⭕每張:A3/5 $ ; A2 /5.5 $ ; A1/ 6.5$ 每區 300張 貼村屋範圍街招海報 海報會全部拍攝相片 街招拍攝35張相片 . •••••••••••••••••• 洗樓入公屋 (上樓派傳單) 每張 0.65 1000張起 會拍攝150張相片 工商廈洗樓 舊式工商廈 會拍攝 35張相片證明 150元3座 130元 5座 120元 10座 110元20座 95元 30座 ⭕入村屋地下信箱 ：$270起接單 每區最少300戶起x9毫子 ⭕入唐樓地下信箱：$180 起接單 每區最少300戶起.x6毫子 汽車派傳單 派名片 的士或call 車平台公司或汽車美容公司 優惠 1.5 1張 放置 banner 掛banner 街頭放bannet 已申請地政署獲批放置 包取貨 10條以下 120元條 20條起 100元1條 要有放資詳細資料 code 會影相證明 偏遠地或 加 30元 1條 街上(舉牌)派傳單服務： 派傳單 2小時起 85元1小時 派傳單 3小時 80元 1小時 派傳單 4小時起 80元1小時 舉牌放傳單 加 10元1小時 加易拉架 加25元1小時 著制服 加 20元1小時 半山學校 加80元 1小時 派贈品 派飲品 派試用裝 派香水 派樣本 派sample 派公屋信箱 已申請入信箱 200戶 70元 每座 元 500戶 125元 750戶 188元 1000戶 250元. 最小 5 座起 已成功申請入公屋通函 誠意合作：WhatsApp: 94518014 派傳單，貼海報，貼街招 洗樓派傳單. 工廈商廈洗樓和私人屋苑,村屋，唐樓等入信箱服務. 印傳單 光粉紙 115克 210*285mm 2000張 需帶稿件 包本地送貨 460元 A4 尺寸 2000張 430元 A4 尺寸 4000張 660元 其後每 1000張 100元 A5 2000張 330元 A5 4000張 530元 其後每 1000張 100元 A6 2000張 300元 其後 每1000張80元 包送貨 印刷 A3. 海報 300張起 2.4元張 印刷 A2 海報 600張起 3元張 印刷 A1 海報 128克紙 600張起 3.4元 張 印刷 A1 海報 115克紙 700張 3元 #派傳單 #傳單員 #派傳單公司 #傳單印刷 #推廣員 #Promoter #印傳單 #派報公司 #投遞信箱 #發傳單 #發名片 #唐樓派傳單 #公屋派傳單 #貼海報 #貼街招 #貼貼紙 #全港專業洗樓派傳單 #派樓及印刷服務 #派傳單服務 #洗樓 #市場推廣 #宣傳 #派傳單服務 #海報宣傳 #派傳單 #推廣 #宣傳 #廣告 #Promotion #村屋派傳單 #車輛派傳單 #汽車派傳單 #村屋派信箱 #唐樓派信箱 #舊樓派傳單 #舊樓派信箱 # 工商廈派傳單 | F14: https://video.fagc3-2.fna.fbcdn.net/o1/v/t2/f2/m366/AQOXPceUZS7beoL2CRcri6BKiSy1-YEQP1iGyMVjsWNP6Js0W13-NztNF3R0hQ6CmaSsI3JMCpeNlFC-i6a4PHTi2mJkMyEaEsOUcf1gMEohNw.mp4?_nc_cat=104&_nc_oc=AdrsOGqlFs8nsj8ti85SUN2_q0UDXkv5Bo4aV_53ErhDq217S7E-kZ5l9zyeB1QZIU8&_nc_sid=5e9851&_nc_ht=video.fagc3-2.fna.fbcdn.net&_nc_ohc=ZyKi1xxHFMUQ7kNvwEEdztP&efg=eyJ2ZW5jb2RlX3RhZyI6Inhwdl9wcm9ncmVzc2l2ZS5GQUNFQk9PSy4uQzMuMTA4OC5kYXNoX2gyNjQtYmFzaWMtZ2VuMl83MjBwIiwieHB2X2Fzc2V0X2lkIjo4ODk3OTczNjQxMjAwODMsImFzc2V0X2FnZV9kYXlzIjoxNSwidmlfdXNlY2FzZV9pZCI6MTAxMjEsImR1cmF0aW9uX3MiOjE2NCwidXJsZ2VuX3NvdXJjZSI6Ind3dyJ9&ccb=17-1&vs=6e714a85334d8a82&_nc_vs=HBksFQIYRWZiX2VwaGVtZXJhbC81MzQ4NTAxQzI3NTBBRUFDQ0I4MTRENTI3NkYzQzhBNl9tdF8xX3ZpZGVvX2Rhc2hpbml0Lm1wNBUAAsgBEgAVAhhAZmJfcGVybWFuZW50L0MyNDQwRjM1NjQyMTZBN0YwQzlDMzcyMjMzMUNEMEEyX2F1ZGlvX2Rhc2hpbml0Lm1wNBUCAsgBEgAoABgAGwKIB3VzZV9vaWwBMRJwcm9ncmVzc2l2ZV9yZWNpcGUBMRUAACam6Pv8gtGUAxUCKAJDMywXQGSQo9cKPXEYGWRhc2hfaDI2NC1iYXNpYy1nZW4yXzcyMHARAHUCZZKeAQA&_nc_gid=lalNyvLnisdorAjl4SJoBA&_nc_ss=72289&_nc_zt=28&oh=00_Af7UYD546eT1ZTbg-3Kxu8UzIRvLQLHtZpvDfvz7kEnXKA&oe=6A10AAB0&bitrate=184413&tag=dash_h264-basic-gen2_720p | H14: 中性 | I14: 陳述 | J14: 廣告/促銷 | K14: 廣告 | L14: 無關 | M14: null | N14: null | O14: null | P14: null | Q14: 0 | R14: 0 | S14: 0
A15: https://www.facebook.com/groups/366950274676457/permalink/1731783888193082/ | B15: 翡翠家 | C15: 46141 | E15: 承接 派傳單 貼海報 貼街招 掛橫額 掛banner 工商廈派傳單 印傳單 印街招 想宣傳又想慳荷包 平價宣傳 增加生意額 增加公司知名度 全港 貼海報 海報宣傳 印傳單 印海報 印街招 派傳單 街上派傳單 派發傳單 工商廈派傳單 商廈派傳單 工廈派傳單 屋苑入傳單 屋苑派傳單 屋苑入信箱 私樓派傳單 私樓入傳單 私樓入信箱 街頭派傳單 工商廈入傳單 工廈入傳單 商廈入傳單 派贈品 派sample 放易拉架 貼海報 貼街招 公屋派傳單 派通函 入通函 掛banner 放banner 合適行業 餐廳 補習社 茶飲 工程公司 太陽能公司 二餸飯 零售 美容儀器 裝修工程 防水工程 鋁窗工程 地產代理 保險代理 產品宣傳 品牌宣傳 電腦維修 食堂宣傳 宣傳易派傳單公司 WhatsApp: 94518014 https://api.whatsapp.com/send?phone=85294518014 承接全港各區派傳單.貼海報街招服務 我們的網站 https://myeasypromotion.com/ 我們的客戶 https://myeasypromotion.com/%e6%88%91%e5%80%91%e7%9a%84%e5%ae%a2%e6%88%b6/ 印傳單 https://myeasypromotion.com/%E5%8D%B0%E5%88%B7%E6%9C%8D%E5%8B%99/ Facebook 專頁 https://www.facebook.com/share/19Vz17DbxX/ 旋轉拍賣商店 https://carousell.app.link/me5wd2PN5Vb 海報宣傳 •••••••••••••••• 街上貼街招/貼海報 海報宣傳 全港各區, 每區300張起接, 提供影相為證服務. ⭕A4每區 300張起（每張$1.8） ⭕A5每區300張起(每張$1.2） ⭕A6每區300張起（每張$ 1) ⭕每張:A3/5 $ ; A2 /5.5 $ ; A1/ 6.5$ 每區 300張 貼村屋範圍街招海報 海報會全部拍攝相片 街招拍攝35張相片 . •••••••••••••••••• 洗樓入公屋 (上樓派傳單) 每張 0.65 1000張起 會拍攝150張相片 工商廈洗樓 舊式工商廈 會拍攝 35張相片證明 150元3座 130元 5座 120元 10座 110元20座 95元 30座 ⭕入村屋地下信箱 ：$270起接單 每區最少300戶起x9毫子 ⭕入唐樓地下信箱：$180 起接單 每區最少300戶起.x6毫子 汽車派傳單 派名片 的士或call 車平台公司或汽車美容公司 優惠 1.5 1張 放置 banner 掛banner 街頭放bannet 已申請地政署獲批放置 包取貨 10條以下 120元條 20條起 100元1條 要有放資詳細資料 code 會影相證明 偏遠地或 加 30元 1條 街上(舉牌)派傳單服務： 派傳單 2小時起 85元1小時 派傳單 3小時 80元 1小時 派傳單 4小時起 80元1小時 舉牌放傳單 加 10元1小時 加易拉架 加25元1小時 著制服 加 20元1小時 半山學校 加80元 1小時 派贈品 派飲品 派試用裝 派香水 派樣本 派sample 派公屋信箱 已申請入信箱 200戶 70元 每座 元 500戶 125元 750戶 188元 1000戶 250元. 最小 5 座起 已成功申請入公屋通函 誠意合作：WhatsApp: 94518014 派傳單，貼海報，貼街招 洗樓派傳單. 工廈商廈洗樓和私人屋苑,村屋，唐樓等入信箱服務. 印傳單 光粉紙 115克 210*285mm 2000張 需帶稿件 包本地送貨 460元 A4 尺寸 2000張 430元 A4 尺寸 4000張 660元 其後每 1000張 100元 A5 2000張 330元 A5 4000張 530元 其後每 1000張 100元 A6 2000張 300元 其後 每1000張80元 包送貨 印刷 A3. 海報 300張起 2.4元張 印刷 A2 海報 600張起 3元張 印刷 A1 海報 128克紙 600張起 3.4元 張 印刷 A1 海報 115克紙 700張 3元 #派傳單 #傳單員 #派傳單公司 #傳單印刷 #推廣員 #Promoter #印傳單 #派報公司 #投遞信箱 #發傳單 #發名片 #唐樓派傳單 #公屋派傳單 #貼海報 #貼街招 #貼貼紙 #全港專業洗樓派傳單 #派樓及印刷服務 #派傳單服務 #洗樓 #市場推廣 #宣傳 #派傳單服務 #海報宣傳 #派傳單 #推廣 #宣傳 #廣告 #Promotion #村屋派傳單 #車輛派傳單 #汽車派傳單 #村屋派信箱 #唐樓派信箱 #舊樓派傳單 #舊樓派信箱 # 工商廈派傳單 | F15: https://video.fagc3-1.fna.fbcdn.net/o1/v/t2/f2/m366/AQO8Bhr0LcpKkLechE2_dTjwenirJJYa0z1YZ_ymyGIKEuWcDMcYVtsylnjSRFuG4c1bLCpQ0YF4Aisy2P8qd-v1yXhdcdFUx3GOX10WEQTW7g.mp4?_nc_cat=102&_nc_oc=Adr56FMCZSGluLiDK6_RmBi4_rjPGK_PeQ63lYg3CF-BrDrTSD_Yh91BDTiqcYXi6mE&_nc_sid=5e9851&_nc_ht=video.fagc3-1.fna.fbcdn.net&_nc_ohc=FMtvX5OGnUcQ7kNvwFJKGi0&efg=eyJ2ZW5jb2RlX3RhZyI6Inhwdl9wcm9ncmVzc2l2ZS5GQUNFQk9PSy4uQzMuMTA4OC5kYXNoX2gyNjQtYmFzaWMtZ2VuMl83MjBwIiwieHB2X2Fzc2V0X2lkIjoxNDgzNzE4NjY2NzI3Mjc5LCJhc3NldF9hZ2VfZGF5cyI6MTgsInZpX3VzZWNhc2VfaWQiOjEwMTIxLCJkdXJhdGlvbl9zIjoxNjQsInVybGdlbl9zb3VyY2UiOiJ3d3cifQ%3D%3D&ccb=17-1&vs=7198388bdb5b1488&_nc_vs=HBksFQIYRWZiX2VwaGVtZXJhbC8wNTQ2QUE1MkE0NzI4NkI5MDNCQjc5OUQyMzk3NEJBNl9tdF8xX3ZpZGVvX2Rhc2hpbml0Lm1wNBUAAsgBEgAVAhhAZmJfcGVybWFuZW50LzQyNEUzRUI3MjdCOTU0MEE1RjIwMTg2NjhFNkU3RDkwX2F1ZGlvX2Rhc2hpbml0Lm1wNBUCAsgBEgAoABgAGwKIB3VzZV9vaWwBMRJwcm9ncmVzc2l2ZV9yZWNpcGUBMRUAACbevZ3B5duiBRUCKAJDMywXQGSQo9cKPXEYGWRhc2hfaDI2NC1iYXNpYy1nZW4yXzcyMHARAHUCZZKeAQA&_nc_gid=lalNyvLnisdorAjl4SJoBA&_nc_ss=72289&_nc_zt=28&oh=00_Af5M8i-oL1HNrEfr3Be3xO6cfZBHa_oP4MySIyEjulwjWA&oe=6A10A746&bitrate=184413&tag=dash_h264-basic-gen2_720p | H15: 中性 | I15: 陳述 | J15: 廣告/促銷 | K15: 廣告 | L15: 無關 | M15: null | N15: null | O15: null | P15: null | Q15: 0 | R15: 0 | S15: 0
A16: https://www.facebook.com/groups/366950274676457/permalink/1730649444973193/ | B16: 翡翠家 | C16: 46140 | E16: 承接 派傳單 貼海報 貼街招 掛橫額 掛banner 工商廈派傳單 印傳單 印街招 想宣傳又想慳荷包 平價宣傳 增加生意額 增加公司知名度 全港 貼海報 海報宣傳 印傳單 印海報 印街招 派傳單 街上派傳單 派發傳單 工商廈派傳單 商廈派傳單 工廈派傳單 屋苑入傳單 屋苑派傳單 屋苑入信箱 私樓派傳單 私樓入傳單 私樓入信箱 街頭派傳單 工商廈入傳單 工廈入傳單 商廈入傳單 派贈品 派sample 放易拉架 貼海報 貼街招 公屋派傳單 派通函 入通函 掛banner 放banner 合適行業 餐廳 補習社 茶飲 工程公司 太陽能公司 二餸飯 零售 美容儀器 裝修工程 防水工程 鋁窗工程 地產代理 保險代理 產品宣傳 品牌宣傳 電腦維修 食堂宣傳 宣傳易派傳單公司 WhatsApp: 94518014 https://api.whatsapp.com/send?phone=85294518014 承接全港各區派傳單.貼海報街招服務 我們的網站 https://myeasypromotion.com/ 我們的客戶 https://myeasypromotion.com/%e6%88%91%e5%80%91%e7%9a%84%e5%ae%a2%e6%88%b6/ 印傳單 https://myeasypromotion.com/%E5%8D%B0%E5%88%B7%E6%9C%8D%E5%8B%99/ Facebook 專頁 https://www.facebook.com/share/19Vz17DbxX/ 旋轉拍賣商店 https://carousell.app.link/me5wd2PN5Vb 海報宣傳 •••••••••••••••• 街上貼街招/貼海報 海報宣傳 全港各區, 每區300張起接, 提供影相為證服務. ⭕A4每區 300張起（每張$1.8） ⭕A5每區300張起(每張$1.2） ⭕A6每區300張起（每張$ 1) ⭕每張:A3/5 $ ; A2 /5.5 $ ; A1/ 6.5$ 每區 300張 貼村屋範圍街招海報 海報會全部拍攝相片 街招拍攝35張相片 . •••••••••••••••••• 洗樓入公屋 (上樓派傳單) 每張 0.65 1000張起 會拍攝150張相片 工商廈洗樓 舊式工商廈 會拍攝 35張相片證明 150元3座 130元 5座 120元 10座 110元20座 95元 30座 ⭕入村屋地下信箱 ：$270起接單 每區最少300戶起x9毫子 ⭕入唐樓地下信箱：$180 起接單 每區最少300戶起.x6毫子 汽車派傳單 派名片 的士或call 車平台公司或汽車美容公司 優惠 1.5 1張 放置 banner 掛banner 街頭放bannet 已申請地政署獲批放置 包取貨 10條以下 120元條 20條起 100元1條 要有放資詳細資料 code 會影相證明 偏遠地或 加 30元 1條 街上(舉牌)派傳單服務： 派傳單 2小時起 85元1小時 派傳單 3小時 80元 1小時 派傳單 4小時起 80元1小時 舉牌放傳單 加 10元1小時 加易拉架 加25元1小時 著制服 加 20元1小時 半山學校 加80元 1小時 派贈品 派飲品 派試用裝 派香水 派樣本 派sample 派公屋信箱 已申請入信箱 200戶 70元 每座 元 500戶 125元 750戶 188元 1000戶 250元. 最小 5 座起 已成功申請入公屋通函 誠意合作：WhatsApp: 94518014 派傳單，貼海報，貼街招 洗樓派傳單. 工廈商廈洗樓和私人屋苑,村屋，唐樓等入信箱服務. 印傳單 光粉紙 115克 210*285mm 2000張 需帶稿件 包本地送貨 460元 A4 尺寸 2000張 430元 A4 尺寸 4000張 660元 其後每 1000張 100元 A5 2000張 330元 A5 4000張 530元 其後每 1000張 100元 A6 2000張 300元 其後 每1000張80元 包送貨 印刷 A3. 海報 300張起 2.4元張 印刷 A2 海報 600張起 3元張 印刷 A1 海報 128克紙 600張起 3.4元 張 印刷 A1 海報 115克紙 700張 3元 #派傳單 #傳單員 #派傳單公司 #傳單印刷 #推廣員 #Promoter #印傳單 #派報公司 #投遞信箱 #發傳單 #發名片 #唐樓派傳單 #公屋派傳單 #貼海報 #貼街招 #貼貼紙 #全港專業洗樓派傳單 #派樓及印刷服務 #派傳單服務 #洗樓 #市場推廣 #宣傳 #派傳單服務 #海報宣傳 #派傳單 #推廣 #宣傳 #廣告 #Promotion #村屋派傳單 #車輛派傳單 #汽車派傳單 #村屋派信箱 #唐樓派信箱 #舊樓派傳單 #舊樓派信箱 # 工商廈派傳單 | F16: https://video-ord5-1.xx.fbcdn.net/o1/v/t2/f2/m366/AQN5dkhpO3bCulSKfZNTCZamUAgW0qwTq4qp7SQGp65J08EeGwAJ6IUePRcgdE-Ug1k6C5MeyGhJFZCzMdSgZHEhYfXO-x1Z0zeRfA31qB25gQ.mp4?_nc_cat=101&_nc_sid=5e9851&_nc_ht=video-ord5-1.xx.fbcdn.net&_nc_ohc=PFNSPELsRgAQ7kNvwFOoEFJ&efg=eyJ2ZW5jb2RlX3RhZyI6Inhwdl9wcm9ncmVzc2l2ZS5GQUNFQk9PSy4uQzMuMTA4OC5kYXNoX2gyNjQtYmFzaWMtZ2VuMl83MjBwIiwieHB2X2Fzc2V0X2lkIjo5NDgzMzEzMzc4MDAwODcsImFzc2V0X2FnZV9kYXlzIjoxOSwidmlfdXNlY2FzZV9pZCI6MTAxMjEsImR1cmF0aW9uX3MiOjE2NCwidXJsZ2VuX3NvdXJjZSI6Ind3dyJ9&ccb=17-1&vs=1889844cdedbeb47&_nc_vs=HBksFQIYRWZiX2VwaGVtZXJhbC9DMzQ2MUU1MEQzRkMyNzJDQkZDMjRBMjYzRUU1RTFBRl9tdF8xX3ZpZGVvX2Rhc2hpbml0Lm1wNBUAAsgBEgAVAhhAZmJfcGVybWFuZW50L0ZBNEJDREY1OTZCNUM3NTY3RTVCOUM3QzgzNTJEM0I5X2F1ZGlvX2Rhc2hpbml0Lm1wNBUCAsgBEgAoABgAGwKIB3VzZV9vaWwBMRJwcm9ncmVzc2l2ZV9yZWNpcGUBMRUAACau5qaIk6CvAxUCKAJDMywXQGSQo9cKPXEYGWRhc2hfaDI2NC1iYXNpYy1nZW4yXzcyMHARAHUCZZKeAQA&_nc_gid=zptLeguYWVWdO1tJhQkW3Q&_nc_ss=72289&_nc_zt=28&oh=00_Af5l8V9H097AYQNvyOkjMqffBp7hXaXutdGSXi7ZE8h_Rw&oe=6A10A13B&bitrate=184413&tag=dash_h264-basic-gen2_720p | H16: 中性 | I16: 陳述 | J16: 其他 | K16: 廣告 | L16: 無關 | M16: null | N16: null | O16: null | P16: null | Q16: 0 | R16: 0 | S16: 0
A17: https://www.facebook.com/groups/366950274676457/permalink/1729719748399496/ | B17: 李美薇 | C17: 46139 | E17: ＃格林Greentrac 感謝支持 格林輪呔 --- - - - 銷售地點 港島區： 鴻記電池輪呔 香港田灣漁歌街3號地下 ☎️90455553 中國膠輪電池 幹諾道西160號 ☎️25480222 筲箕灣汽車唧油 香港筲箕灣新成街2號G H I舖 ☎️96089819 金威膠輪有限公司 柴灣豐業街12號 ☎️28978520 九龍區： 通明膠輪公司 觀塘通明街64號地下 ☎️2343 5516 金鋒汽車服務 九龍樂富靜安街36號地下 ☎️9523 1657 灝天輪呔 九龍深水埗海壇街166號地下 ☎️69708432 棠記膠輪 九龍深水埗福華街77號地下 ☎️9234 1185 新界區： 金威膠輪有限公司 沙田火炭坳背灣街53-55 號美高工業大廈地下A舖 ☎️26620588 新昌膠輪公司 上水嘉富坊貿易廣場B座地下5號 ☎️9837 9847 新金成膠輪電池公司 粉嶺安居街8號地下 ☎️2674 6144 大眾輪胎行 元朗媽橫路47號 ☎️2477 2356 萬昌行 屯門建泰街6號恒威工業中心地下155號 ☎️91333830 歐洲品牌格林輪胎 熱賣好評！德國技術，品質保證！ 多謝大家的支持‍♂️‍♂️！ 本公司繼續極力推薦使用 歐洲品牌 格林輪胎 進化科技 定義未來 高強度胎體設計,完美匹配，表現出精湛抓地力與轉向性能。 胎邊結構:雙層聚酯纖維 雙層胎邊結構設計,提供絕佳過彎支撐性能,給於胎面在彎道中保有最大摩擦面積,賦予極佳的安全性與操控性能 A級濕滑✅胎面特殊配方，直線紋路設計有效降低阻滾動噪音，提高濕地性能。 強力轉向✅胎圈特殊材料補強設計提升輪胎支撐性，同時為轉向性能提供強力保障。 ＃歐洲品牌 ＃格林輪胎 ＃Greentrac ＃舒適低噪音 ＃最大排水量 ＃高穩定性擋塊 ＃降低道路噪音 ＃超低滾動阻力 ＃燃油節省 ＃超高性能輪胎 Greentrac Quest-X UHP 超高性能輪胎 採用德國技術3D主動靜音設計！ 熱賣中 性價比高 一致讚好 持續發威 另備有多款專為私家車型號(格林輪呔) 滿足有要求的客人 歡迎各位查詢預約 ＃港澳總代理 ＃智盈實業 https://wa.me/85297840529 | H17: 正面 | I17: 滿意 | J17: 廣告/促銷 | K17: 廣告 | L17: 無關 | M17: 田灣,筲箕灣,柴灣,觀塘,樂富,深水埗,沙田火炭,上水,粉嶺,元朗,屯門 | N17: null | O17: null | P17: null | Q17: 0 | R17: 0 | S17: 0
A18: https://www.facebook.com/groups/366950274676457/permalink/1728247225213415/ | B18: Luk Kwok Ho | C18: 46137 | E18: 市場極小 4K + 4K sony 12吋全畫面（右眼）前後 4K sony鏡頭 $1480 包 64g卡 18個月保養 5g wifi 送gps定位 ( 送完即止 ) ~~~~~~~~~~~~~~~~ 真係要買啲 幾千蚊嘅cam 平貨都有質素嘅 #產品資料 https://www.facebook.com/share/1BvFA6A82o/ 前鏡頭4k 後鏡頭1080p 隱蔽式$380 倒後鏡$430 包32G卡 (一年保養) #最高清產品 前4k後2k $580 包32G卡 (一年保養) #商務車輛必備 三鏡頭 $530 4K+1080P+1080P 包32G卡 (一年保養） #10寸 全畫面 倒後鏡 三鏡頭 前3K中後1080P $580 包32g記憶卡 (一年保養) #高要求首選 最高清 市場極小 前4k後4k sony 鏡頭 $1280 包64g (18個月保養) #12寸全畫面前後錄影 前後外掛sony鏡頭 前2k後2k $980 包64g 18個月保養 #12寸 全畫面 (右眼) 前後 双4K sony鏡頭 $1480 包 64g 18個月保養 ( 前鏡頭跟主機 ) #4G遠程 你這剎那在何方 都可以即時觀看車輛環境 2K + 1080P #須自備sim卡 $680包64g卡 一年保養 #跟兩款電源線 煙插 or 24小時 fuse #wifi手機連接下載 #如果需要安裝人工 $500 - $600 安裝地址 #大角咀洋松街 GPS https://maps.app.goo.gl/7VKGEnVbLzEZ8mTm7?g_st=awb Whatsapp https://api.whatsapp.com/send?phone=85290494941 #屯門良田村 GPS https://maps.app.goo.gl/PLUcXzdT43qFdzR66?g_st=awb Whatsapp https://api.whatsapp.com/send?phone=85269988527 #天水圍田廈路 GPS https://maps.app.goo.gl/UFs1rsR2VBqSLB2A8?g_st=awb whatsapp https://api.whatsapp.com/send?phone=85266883466 #大埔車迷 GPS https://maps.app.goo.gl/dDJxdU79aWy3CELG7?g_st=awb Whatsapp https://api.whatsapp.com/send?phone=85226383365 #旺角黑布街 gps https://maps.app.goo.gl/HNBaAr6YvVJtsxJg8?g_st=awb whatsapp https://api.whatsapp.com/send?phone=85297770066 #和宜合道255號 Gps https://maps.app.goo.gl/6DQMvNVX1LX6LGu48?g_st=awb Whatsapp https://api.whatsapp.com/send?phone=85292209738 #九龍黃大仙竹園翠鳳街19號地下 LAAM LOK car service Gps https://maps.app.goo.gl/TKNjQ2wRPNcRSf9u7?g_st=awb Whatsapp https://api.whatsapp.com/send?phone=85254992828 #新界九龍上門安裝 700蚊費用 中午12 至 夜晚10 whatsapp https://api.whatsapp.com/send?phone=85226383365 #不需要安裝新界九龍面交 中午12 至 夜晚12 有意請whatsapp了解 按下去就是我的whatsapp https://api.whatsapp.com/send?phone=85260326500 #車cam #4K #1080p #前後cam #toyota #honda #nissan #mitsubishi #audi #vw #benz #kia #bmw #byd #Tesla | H18: 中性 | I18: 陳述 | J18: 廣告/促銷 | K18: 廣告 | L18: 無關 | M18: 大角咀洋松街, 屯門良田村, 天水圍田廈路, 大埔, 旺角黑布街, 和宜合道255號, 九龍黃大仙竹園翠鳳街19號 | N18: null | O18: null | P18: null | Q18: 0 | R18: 0 | S18: 0
A19: https://www.facebook.com/groups/366950274676457/permalink/1727408728630598/ | B19: Jack Chan | C19: 46136 | E19: 又有優惠啦！！！ 佐敦高臨停車場，電動車月租優惠！$3800 | G19: https://scontent-bos5-1.xx.fbcdn.net/v/t39.30808-6/677761721_122202717134581123_1503788171277941040_n.jpg?stp=cp6_dst-jpg_s960x960_tt6&_nc_cat=102&ccb=1-7&_nc_sid=aa7b47&_nc_ohc=qOw2sZj-IcAQ7kNvwFKoh2I&_nc_oc=Ado6Qbk18dLhY5bv57mSZRGLkNZvKZfNF9VKL6q_VCo2yfzphdn0DW6dk5oEOL8xA8gh0HUguJj7B1kh8v4G7F4h&_nc_zt=23&_nc_ht=scontent-bos5-1.xx&_nc_gid=YkxMDG4iCmDQ2HuJb-vyzQ&_nc_ss=72289&oh=00_Af55O--TkEycQOPQL_8R9DUAV2-f6BoHyfNF6duCYq5_3g&oe=6A109B03 | H19: 正面 | I19: 開心 | J19: 收費/價錢 | K19: 廣告 | L19: 直接相關 | M19: 佐敦高臨停車場 | N19: null | O19: null | P19: null | Q19: 3 | R19: 0 | S19: 1
A20: https://www.facebook.com/groups/366950274676457/permalink/1723420689029402/ | B20: BlueLobster8261 | C20: 46131 | E20: 我不入地獄誰入地獄 https://share.google/k0d5A5WSK45Qnz1a0 | G20: https://scontent-bos5-1.xx.fbcdn.net/v/t39.30808-6/672710893_2055785651671802_6852572690524723594_n.jpg?stp=dst-jpg_p526x296_tt6&_nc_cat=103&ccb=1-7&_nc_sid=aa7b47&_nc_ohc=T9A5Q9r_3pYQ7kNvwG-_zTx&_nc_oc=AdqhuTe8DpElWsIftbpZE7g0vX88y-2gE6jULyz5AHofTI7_L7oSKjjQ1N-AJo5qPdVqKrO8Y89ziyE2f9w0dONx&_nc_zt=23&_nc_ht=scontent-bos5-1.xx&_nc_gid=YkxMDG4iCmDQ2HuJb-vyzQ&_nc_ss=72289&oh=00_Af6kRAUH_vytmVmbzUH7nVbxoNrKfwp6-i57sff1VDOaLw&oe=6A10A07A | H20: 中性 | I20: 陳述 | J20: 其他 | K20: 純分享 | L20: 無關 | M20: null | N20: null | O20: null | P20: null | Q20: 0 | R20: 0 | S20: 0
A21: https://www.facebook.com/groups/366950274676457/permalink/1721648979206573/ | B21: Ann Lee | C21: 46129 | E21: ＃格林Greentrac 感謝支持 格林輪呔 --- - - - 銷售地點 港島區： 鴻記電池輪呔 香港田灣漁歌街3號地下 ☎️90455553 中國膠輪電池 幹諾道西160號 ☎️25480222 筲箕灣汽車唧油 香港筲箕灣新成街2號G H I舖 ☎️96089819 金威膠輪有限公司 柴灣豐業街12號 ☎️28978520 九龍區： 通明膠輪公司 觀塘通明街64號地下 ☎️2343 5516 金鋒汽車服務 九龍樂富靜安街36號地下 ☎️9523 1657 灝天輪呔 九龍深水埗海壇街166號地下 ☎️69708432 棠記膠輪 九龍深水埗福華街77號地下 ☎️9234 1185 新界區： 金威膠輪有限公司 沙田火炭坳背灣街53-55 號美高工業大廈地下A舖 ☎️26620588 新昌膠輪公司 上水嘉富坊貿易廣場B座地下5號 ☎️9837 9847 新金成膠輪電池公司 粉嶺安居街8號地下 ☎️2674 6144 大眾輪胎行 元朗媽橫路47號 ☎️2477 2356 萬昌行 屯門建泰街6號恒威工業中心地下155號 ☎️91333830 歐洲品牌格林輪胎 熱賣好評！德國技術，品質保證！ 多謝大家的支持‍♂️‍♂️！ 本公司繼續極力推薦使用 歐洲品牌 格林輪胎 進化科技 定義未來 高強度胎體設計,完美匹配，表現出精湛抓地力與轉向性能。 胎邊結構:雙層聚酯纖維 雙層胎邊結構設計,提供絕佳過彎支撐性能,給於胎面在彎道中保有最大摩擦面積,賦予極佳的安全性與操控性能 A級濕滑✅胎面特殊配方，直線紋路設計有效降低阻滾動噪音，提高濕地性能。 強力轉向✅胎圈特殊材料補強設計提升輪胎支撐性，同時為轉向性能提供強力保障。 ＃歐洲品牌 ＃格林輪胎 ＃Greentrac ＃舒適低噪音 ＃最大排水量 ＃高穩定性擋塊 ＃降低道路噪音 ＃超低滾動阻力 ＃燃油節省 ＃超高性能輪胎 Greentrac Quest-X UHP 超高性能輪胎 採用德國技術3D主動靜音設計！ 熱賣中 性價比高 一致讚好 持續發威 另備有多款專為私家車型號(格林輪呔) 滿足有要求的客人 歡迎各位查詢預約 ＃港澳總代理 ＃智盈實業 https://wa.me/85297840529 | H21: 正面 | I21: 期待 | J21: 廣告/促銷 | K21: 廣告 | L21: 無關 | M21: 田灣,筲箕灣,柴灣,觀塘,樂富,深水埗,沙田火炭,上水,粉嶺,元朗,屯門 | N21: null | O21: null | P21: null | Q21: 0 | R21: 0 | S21: 0
A22: https://www.facebook.com/groups/366950274676457/permalink/1720152196022918/ | B22: 李漢民 | C22: 46127 | E22: 【車友警示】小心 Shell Recharge 變相加價！快充 60kW 變 30kW 的收費把戲！ 各位車友，入去 Shell 充電站前請三思！今日喺機場貨運大樓 Shell Recharge 遇到極之離譜嘅收費同技術問題，大家一定要小心以下「三招」： 1️⃣ 「文字遊戲」：標榜 60kW，實質 30kW App 入面大大字寫住最高速度 60kW，但原來只要隔離有車一齊充，佢就會自動減速。我實測部車顯示只入到 30kW！客服起初仲想推卸責任話係部車「唔吸電」，最後被我踢爆先肯承認係因為兩支槍分流導致輸出減半。 2️⃣ 「低消陷阱」：速度減慢，最低消費照收 最無良嘅係，佢速度減半令你充多一倍時間，但依然設有 HKD 80 的最低消費。當你發現充得慢想中途停手，佢一樣收足你 $80。計返埋單，每度電嘅平均單價貴到離譜，完全係變相加價！ 3️⃣ 「計算混亂」：客服口風轉完又轉 我充咗 12.3 kWh，按原價 $3.9/kWh 應該只係 $48 左右，但因為嗰個「最低消費」加上佢哋補償計算不清，搞到收費極度唔透明。雖然最後嘈到佢哋話退返 $30.8 同加 $20 心意金，但呢種「你要嘈先肯退」嘅態度真係令人好失望。 ⚠️ 溫馨提示： 如果大家趕時間，或者唔想被扣冤枉錢，見到隔離有車充電就千祈唔好入去 Shell 呢啲「共享功率」嘅充電位。佢哋嘅銷售標語極具誤導性，明明係慢充速度，卻收快充嘅價錢！ #ShellRecharge #香港電車 #EVHK #充電陷阱 #機場充電 #快充變慢充 #消費者權益 | H22: 負面 | I22: 生氣 | J22: 收費/價錢 | K22: 純分享 | L22: 直接相關 | M22: 機場 | N22: null | O22: Shell Recharge | P22: 60kW, 30kW, 快充, 慢充 | Q22: 151 | R22: 101 | S22: 2
A23: https://www.facebook.com/groups/366950274676457/permalink/1720179539353517/ | B23: Anonymous participant | C23: 46127 | E23: 各位師兄 細佬我想問一問 屯門邊到有叉電平靚正？ | H23: 中性 | I23: 疑問 | J23: 疑問/求助 | K23: 求助 | L23: 直接相關 | M23: 屯門 | N23: null | O23: null | P23: null | Q23: 0 | R23: 6 | S23: 0
A24: https://www.facebook.com/groups/366950274676457/permalink/1718688556169282/ | B24: Roy Ng | C24: 46125 | E24: 八鄉汽車美容 公司位置： 錦田八鄉橫台山 （順利行格離） 如有興趣或其他汽車美容 詳情或預約 可聯絡☎️51992395 賢 ☎️ https://m.facebook.com/八鄉汽車美容-洗車-打蠟-蒸籠-140889456736875 日本9H 白金塗層復合鍍膜 1-2年期 深層研磨去漬拋光 除花痕去蜘蛛紋 鍍晶水腊人手泡抹洗車 推泥膠 去污 凡惠昌顧9H塗層鍍鏌加送 納米空氣觸媒消毒蒸籠 冷氣殺菌消毒服務 ⛔️半年保養⛔️ 現優惠價2️⃣5️⃣0️⃣0️⃣ （全車深層清潔消毒套餐 ） 鍍晶水腊 人手泡抹洗車 推泥膠 去污 ➕吸塵 洗鈴 清潔玻璃 ➕ 霧化藥水消毒 除甲醛 除味 防霉 ➕ 藥水泡泡深層清潔內籠 ➕納米空氣觸媒殺菌消毒除味 ➕冷氣殺菌消毒服務 現優惠價 9️⃣5️⃣0️⃣ （ 跣水3M三重水晶蠟消毒蒸籠套餐 ） 鍍晶水腊 人手泡抹洗車 推泥膠 去污 ➕ 吸塵 口清潔玻璃 洗鈴 ➕ 冷氣霧化消毒 除甲醛 除味 防霉 ➕火三層3M水晶蠟（深度去漬去花拋光） ➕藥水泡泡深層清潔內籠 ➕納米空氣觸媒殺菌消毒除味 ➕冷氣殺菌消毒服務 現優惠價 1️⃣8️⃣8️⃣8️⃣ 以下個別項目因應車輛大小 有所調整 以下是各式單項服務及價錢 A :鍍晶水腊 人手洗車 泥膠 內籠吸塵清潔 洗鈴 1️⃣4️⃣8️⃣起 B：納米空氣觸媒霧化消毒 內籠連冷氣 除菌 除味防霉 4️⃣2️⃣0️⃣起 C：藥水泡泡深層清潔蒸籠 包吸塵 （座位 座位底 尾箱 冷氣口 地毯） 4️⃣8️⃣0️⃣起 D: 一層3M打蠟（拋光 輕度去花去漬） 洗車 吸塵 推泥膠 洗鈴及清潔玻璃 5️⃣0️⃣0️⃣ E: 跣水3M三重水晶蠟 （深度去花去漬拋光水晶臘） 洗車 吸塵 推泥膠 洗鈴及清潔玻璃 9️⃣8️⃣8️⃣ 起 F: 玻璃鍍晶 線水 去油面 污漬 5️⃣0️⃣0️⃣起 G: 清洗引擎箱 3️⃣0️⃣0️⃣ H: 頭燈翻新（一對） 6️⃣0️⃣0️⃣ #洗車 #打臘 #汽車美容 #蒸籠 #除味消毒 #八鄉汽車美容 #去漬 #9H鍍鏌 #內籠清潔 #打腊 #霧化消毒 #拋光 #去花痕 #元朗 #保護層 #撥水 | H24: 中性 | I24: 陳述 | J24: 廣告/促銷 | K24: 廣告 | L24: 無關 | M24: 八鄉 | N24: null | O24: null | P24: null | Q24: 0 | R24: 0 | S24: 0
A25: https://www.facebook.com/groups/366950274676457/permalink/1717680312936773/ | B25: 陳傲輝 | C25: 46124 | E25: 有見到你架電車做的士未？ 大熱byd 竟然少過mifa7 | H25: 中性 | I25: 疑問 | J25: 資訊分享 | K25: 純分享 | L25: 直接相關 | M25: null | N25: BYD, MIFA7 | O25: null | P25: null | Q25: 0 | R25: 0 | S25: 0
A26: https://www.facebook.com/groups/366950274676457/permalink/1716559856382152/ | B26: LoyalElephant5591 | C26: 46122 | E26: 成日無電 元朗呢個新潭路三號電站，唔知點解朝早成日都會停電，係咪被人差曬啲電？無電賣？ | G26: https://scontent-dfw5-2.xx.fbcdn.net/v/t39.30808-6/668712945_993325249925828_1842925722426541292_n.jpg?stp=cp6_dst-jpg_p180x540_tt6&_nc_cat=100&ccb=1-7&_nc_sid=aa7b47&_nc_ohc=nuZghVGqVQAQ7kNvwF71fZn&_nc_oc=AdrGbf2rP9nuu0J6Q_Cix1XdakmNtsETJ-qX-ZpY-RzsY1pS70g31KIjZKZDJ1ySiVs&_nc_zt=23&_nc_ht=scontent-dfw5-2.xx&_nc_gid=TC7hPaUniuFmHQh6Vk2hiQ&_nc_ss=72289&oh=00_Af5fzOAJtNI5aeBgZJPnDE-1DbAr0vUbcSzuvJk0Kj6-yw&oe=6A10B5CF | H26: 負面 | I26: 失望 | J26: 充電站設施/位置 | K26: 純分享 | L26: 直接相關 | M26: 元朗新潭路 | N26: null | O26: null | P26: null | Q26: 32 | R26: 25 | S26: 0
A27: https://www.facebook.com/groups/366950274676457/permalink/1715215686516569/ | B27: Tommy Lo | C27: 46121 | E27: 偉業街洗車加充電一站過可以淨充電 日頭都係2.5一度 洗車都係，全部都係次次清俾八達通 唔需要套票或者充值一百值得推薦 | H27: 正面 | I27: 滿意 | J27: 收費/價錢 | K27: 純分享 | L27: 直接相關 | M27: 偉業街 | N27: null | O27: null | P27: null | Q27: 73 | R27: 35 | S27: 1
A28: https://www.facebook.com/groups/366950274676457/permalink/1709728790398592/ | B28: Ka Ka Chan | C28: 46114 | E28: Cornerstone 6折充電私放 有意請PM | H28: 中性 | I28: 陳述 | J28: 收費/價錢 | K28: 廣告 | L28: 直接相關 | M28: null | N28: null | O28: Cornerstone | P28: null | Q28: 0 | R28: 3 | S28: 0
A29: https://www.facebook.com/groups/366950274676457/permalink/1704122087625929/ | B29: Ka Ka Lam | C29: 46107 | E29: 尚翹峰灣仔街市停車場，新安裝左充電機， 以後食飯買餸又可以充電，真係好方便啊～ | G29: https://scontent-lga3-1.xx.fbcdn.net/v/t39.30808-6/658398685_1299013122146964_7224062660589709086_n.jpg?stp=dst-jpg_s600x600_tt6&_nc_cat=103&ccb=1-7&_nc_sid=aa7b47&_nc_ohc=vDbxTkPgM8sQ7kNvwFd9n0d&_nc_oc=AdrYwVb4Ni9_MTkLN-KnSRwH6xVpuShq2QXDlWXBH6yep1wypXWEbiMD28pgnyO6d8I&_nc_zt=23&_nc_ht=scontent-lga3-1.xx&_nc_gid=3hK_bdqP4gD59nuNbioZwQ&_nc_ss=72289&oh=00_Af5QC4U1k117JK9ZYJvz8hs_DFD4imBjynLKMwnvLIxXSg&oe=6A109265 | H29: 正面 | I29: 開心 | J29: 充電站設施/位置 | K29: 純分享 | L29: 直接相關 | M29: 灣仔尚翹峰灣仔街市 | N29: null | O29: null | P29: null | Q29: 22 | R29: 5 | S29: 0
A30: https://www.facebook.com/groups/366950274676457/permalink/1696900318348106/ | B30: Jack Chan | C30: 46098 | E30: 佐敦西貢街月租停車場，地點方便，易泊 呢頭又多個選擇 | G30: https://scontent-lga3-3.xx.fbcdn.net/v/t39.30808-6/652379669_122197761530581123_7638020414330014135_n.jpg?stp=cp6_dst-jpg_s720x720_tt6&_nc_cat=106&ccb=1-7&_nc_sid=aa7b47&_nc_ohc=enRBHQ-ZwF8Q7kNvwHnlS7-&_nc_oc=Adqvvf25Zsc-9Y3o7pRqzwQGYGcw8axpvUTrJj666Bdso_h1EZLjDuNEJ0LzJkDyA9Q&_nc_zt=23&_nc_ht=scontent-lga3-3.xx&_nc_gid=h-bfZUZaPpmZp4tyPNuESQ&_nc_ss=72289&oh=00_Af7So2A1d6uuQ2LrscVewMJ1MJ1cQV8rYgGHHSZvAqh65A&oe=6A1094BA | H30: 正面 | I30: 滿意 | J30: 充電站設施/位置 | K30: 純分享 | L30: 間接相關 | M30: 佐敦西貢街 | N30: null | O30: null | P30: null | Q30: 4 | R30: 0 | S30: 1
A31: https://www.facebook.com/groups/366950274676457/permalink/1691833838854754/ | B31: King King | C31: 46092 | D31: This content isn't available right now | E31: ＃格林Greentrac 感謝支持 格林輪呔 --- - - - 銷售地點 港島區： 鴻記電池輪呔 香港田灣漁歌街3號地下 ☎️90455553 中國膠輪電池 幹諾道西160號 ☎️25480222 筲箕灣汽車唧油 香港筲箕灣新成街2號G H I舖 ☎️96089819 金威膠輪有限公司 柴灣豐業街12號 ☎️28978520 九龍區： 通明膠輪公司 觀塘通明街64號地下 ☎️2343 5516 金鋒汽車服務 九龍樂富靜安街36號地下 ☎️9523 1657 灝天輪呔 九龍深水埗海壇街166號地下 ☎️69708432 棠記膠輪 九龍深水埗福華街77號地下 ☎️9234 1185 新界區： 金威膠輪有限公司 沙田火炭坳背灣街53-55 號美高工業大廈地下A舖 ☎️26620588 新昌膠輪公司 上水嘉富坊貿易廣場B座地下5號 ☎️9837 9847 新金成膠輪電池公司 粉嶺安居街8號地下 ☎️2674 6144 大眾輪胎行 元朗媽橫路47號 ☎️2477 2356 萬昌行 屯門建泰街6號恒威工業中心地下155號 ☎️91333830 合各類型貨van，夠磅驗車 ＃各類型貨VAN ＃標緻貨van ＃TRAVELLER ＃平治貨van ＃BENZ ＃VITO ＃福特貨van ＃FORD ＃福士貨van ＃t5 ＃t6 ＃現代貨van ＃H1 ＃STARIA ＃豐田貨van ＃hiace200 ＃hiace300 ＃日産貨van ＃NV350 ＃E25 ＃E26 性價比之選，夠磅驗車 215/70/15，$680 215/65/16，$780 225/65/16，$820 225/55/17，$850 235/55/17，$980 235/50/18，$950 255/45/18，$1080 245/45/19，$980 255/45/19，$1180 275/40/19，$1250 245/40/20，$1280 245/45/20，$1300 255/40/20，$1350 275/35/20，$1450 歐洲品牌格林輪胎 熱賣好評！德國技術，品質保證！ 多謝大家的支持‍♂️‍♂️！ 本公司繼續極力推薦使用 歐洲品牌 格林輪胎 進化科技 定義未來 高強度胎體設計,完美匹配，表現出精湛抓地力與轉向性能。 胎邊結構:雙層聚酯纖維 雙層胎邊結構設計,提供絕佳過彎支撐性能,給於胎面在彎道中保有最大摩擦面積,賦予極佳的安全性與操控性能 A級濕滑✅胎面特殊配方，直線紋路設計有效降低阻滾動噪音，提高濕地性能。 強力轉向✅胎圈特殊材料補強設計提升輪胎支撐性，同時為轉向性能提供強力保障。 ＃歐洲品牌 ＃格林輪胎 ＃Greentrac ＃舒適低噪音 ＃最大排水量 ＃高穩定性擋塊 ＃降低道路噪音 ＃超低滾動阻力 ＃燃油節省 ＃超高性能輪胎 Greentrac Quest-X UHP 超高性能輪胎 採用德國技術3D主動靜音設計！ 熱賣中 性價比高 一致讚好 持續發威 另備有多款專為私家車型號(格林輪呔) 滿足有要求的客人 歡迎各位查詢預約 ＃港澳總代理 ＃智盈實業 https://wa.me/85297840529 | H31: 正面 | I31: 期待 | J31: 廣告/促銷 | K31: 廣告 | L31: 無關 | M31: 田灣, 筲箕灣, 柴灣, 觀塘, 樂富, 深水埗, 沙田火炭, 上水, 粉嶺, 元朗, 屯門 | N31: null | O31: null | P31: null | Q31: 0 | R31: 0 | S31: 0
A32: https://www.facebook.com/groups/366950274676457/permalink/1685054832865988/ | B32: Anonymous participant | C32: 46083 | E32: 放一換一電動車quota，留言我pm你傾 | H32: 中性 | I32: 陳述 | J32: 廣告/促銷 | K32: 廣告 | L32: 間接相關 | M32: null | N32: null | O32: null | P32: null | Q32: 0 | R32: 0 | S32: 0
A33: https://www.facebook.com/groups/366950274676457/permalink/1685047799533358/ | B33: Electway | C33: 46083 | E33: # GB/T to CHAdeMO adapter | G33: https://scontent-ord5-3.xx.fbcdn.net/v/t39.30808-6/643573320_1448517500618420_3728041026410020012_n.jpg?stp=dst-jpg_p526x296_tt6&_nc_cat=100&ccb=1-7&_nc_sid=aa7b47&_nc_ohc=T5PU9cIY7xIQ7kNvwHH4F83&_nc_oc=AdonvIor2jyCajU_ZGIc94xZKezbM6lZzN-qoQEoc3iol7Gu0x_mUmXAM3Zyk7aimMY&_nc_zt=23&_nc_ht=scontent-ord5-3.xx&_nc_gid=Rft2ww9Bm913JFbqk7hngA&_nc_ss=72289&oh=00_Af76B5mANZ8Cc8P2UaI5omH9DtjIl6cptjktFr0Jb-SxdQ&oe=6A10B09C | H33: 中性 | I33: 陳述 | J33: 安裝/硬件/技術 | K33: 純分享 | L33: 直接相關 | M33: null | N33: null | O33: null | P33: CHAdeMO | Q33: 0 | R33: 0 | S33: 0
A34: https://www.facebook.com/groups/366950274676457/permalink/1684735942897877/ | B34: JoJo Bee | C34: 46082 | E34: 全新DUOSIDA 22kwh 5米充電線 Type2出讓 | H34: 中性 | I34: 陳述 | J34: 廣告/促銷 | K34: 廣告 | L34: 直接相關 | M34: null | N34: null | O34: null | P34: Type 2, 22kW | Q34: 3 | R34: 0 | S34: 0
A35: https://www.facebook.com/groups/366950274676457/permalink/1684129122958559/ | B35: Miya Yip | C35: 46082 | E35: 私人放一換一quota 車已劏 已注銷 可即簽 $25000 煩請PM | H35: 中性 | I35: 陳述 | J35: 廣告/促銷 | K35: 廣告 | L35: 直接相關 | M35: null | N35: null | O35: null | P35: null | Q35: 0 | R35: 0 | S35: 0
A36: https://www.facebook.com/groups/366950274676457/permalink/1683741336330671/ | B36: Anonymous participant | C36: 46081 | E36: 放一換一quota 可以二簽（時間彈性） 連車$38000 | H36: 中性 | I36: 陳述 | J36: 廣告/促銷 | K36: 廣告 | L36: 間接相關 | M36: null | N36: null | O36: null | P36: null | Q36: 0 | R36: 0 | S36: 0
A37: https://www.facebook.com/groups/366950274676457/permalink/1682756033095868/ | B37: Dasyvin | C37: 46080 | E37: 荃灣又多個充電站，有8支快充，免停車費 | H37: 正面 | I37: 滿意 | J37: 充電站設施/位置 | K37: 純分享 | L37: 直接相關 | M37: 荃灣 | N37: null | O37: null | P37: 快充 | Q37: 3 | R37: 1 | S37: 0
A38: https://www.facebook.com/groups/366950274676457/permalink/1682637959774342/ | B38: Amuro Lee | C38: 46080 | E38: https://unwire.hk/2026/02/27/osaka-expo-ev-bus-graveyard-evmj-president-resign/life-tech/auto/ | H38: 負面 | I38: 失望 | J38: 安裝/硬件/技術 | K38: 純分享 | L38: 間接相關 | M38: 大阪 | N38: null | O38: null | P38: null | Q38: 0 | R38: 0 | S38: 0
A39: https://www.facebook.com/groups/366950274676457/permalink/1682372743134197/ | B39: 騎師政府私家車驗車 | C39: 46080 | E39: https://www.facebook.com/share/p/1GVZDQUDXm/?mibextid=wwXIfr | H39: 中性 | I39: 陳述 | J39: 其他 | K39: 純分享 | L39: 無關 | M39: null | N39: null | O39: null | P39: null | Q39: 0 | R39: 0 | S39: 0
A40: https://www.facebook.com/groups/366950274676457/permalink/1681367443234727/ | B40: Thomson Leung | C40: 46079 | E40: 私放1換1 車已劏 文件手續齊全 歡迎報價$35000 可大刀 | H40: 中性 | I40: 陳述 | J40: 其他 | K40: 廣告 | L40: 無關 | M40: null | N40: null | O40: null | P40: null | Q40: 0 | R40: 0 | S40: 0
A41: https://www.facebook.com/groups/366950274676457/permalink/1681328033238668/ | B41: Ann Mak | C41: 46079 | E41: 私人放一換一quota 歡迎 出價 未劏車 可兩簽 可以隨時交收 PM 或 Whatsapp 97231779 | H41: 中性 | I41: 陳述 | J41: 廣告/促銷 | K41: 廣告 | L41: 間接相關 | M41: null | N41: null | O41: null | P41: null | Q41: 0 | R41: 0 | S41: 0
A42: https://www.facebook.com/groups/366950274676457/permalink/1677664946938310/ | B42: Frank Yip | C42: 46074 | E42: 請教大家幫襯個邊間裝家用充電器？ | H42: 中性 | I42: 疑問 | J42: 疑問/求助 | K42: 求助 | L42: 直接相關 | M42: null | N42: null | O42: null | P42: null | Q42: 1 | R42: 1 | S42: 0
A43: https://www.facebook.com/groups/366950274676457/permalink/1677465290291609/ | B43: Abbie Lo | C43: 46074 | E43: 電動車攜帶式充電器問卷 新年快樂 身體健康 路路亨通 馬到功成 我係讀緊產品設計的學生 今個sem要設計「電動車攜帶式充電器」 電動車越來越普及 ,想提升方便性和效率 懇求電動車車主花幾分鐘時間幫忙以下填寫問卷 讓我們了解電動車使用者在充電上遇到的問題 分享您的使用經驗 感謝各位 問卷連結:https://forms.cloud.microsoft/Pages/ResponsePage.aspx?id=YOVOzyieL0G0yqk_QEveTmMfK8S-WhpNktEswy9nl09UM0lJUk1KRk0zNjZVNDBBMTg0RDFJOE1QRy4u | G43: https://scontent.fabe1-1.fna.fbcdn.net/v/t39.30808-6/637671234_10163322406481633_4285210761847722355_n.jpg?stp=dst-jpg_s640x640_tt6&_nc_cat=106&ccb=1-7&_nc_sid=aa7b47&_nc_ohc=AF2eUuC1EWUQ7kNvwEzj6g4&_nc_oc=AdolBAHKG3Ptc3w2NYK1S0FyNwz3RtRen5hyVmliwNUoZNCzTy0cAX1TgCcQ2tfHb8A&_nc_zt=23&_nc_ht=scontent.fabe1-1.fna&_nc_gid=FQfXzSleIhpZk7kBP7PQmg&_nc_ss=72289&oh=00_Af5ze62TYhzm3XQSG0GdsHGqkgP8YMHIlQ5jJyqthFQQSQ&oe=6A10A89C | H43: 中性 | I43: 陳述 | J43: 資訊分享 | K43: 求助 | L43: 直接相關 | M43: null | N43: null | O43: null | P43: null | Q43: 1 | R43: 0 | S43: 0
A44: https://www.facebook.com/groups/366950274676457/permalink/1676256717079133/ | B44: C Lok Leung | C44: 46073 | E44: Well Done Charge $2.5 / kWh 鴻圖道6號 DC直流電 快充 (都算幾快) 八達通收費 ( 首次幫襯，感覺唔錯 ) | H44: 正面 | I44: 滿意 | J44: 充電站設施/位置 | K44: 純分享 | L44: 直接相關 | M44: 鴻圖道6號 | N44: null | O44: Well Done Charge | P44: 快充 | Q44: 59 | R44: 13 | S44: 0
A45: https://www.facebook.com/groups/366950274676457/permalink/1671036250934513/ | B45: King King | C45: 46067 | D45: This content isn't available right now | E45: ＃格林Greentrac 感謝支持 格林輪呔 --- - - - 銷售地點 港島區： 鴻記電池輪呔 香港田灣漁歌街3號地下 ☎️90455553 中國膠輪電池 幹諾道西160號 ☎️25480222 筲箕灣汽車唧油 香港筲箕灣新成街2號G H I舖 ☎️96089819 金威膠輪有限公司 柴灣豐業街12號 ☎️28978520 九龍區： 通明膠輪公司 觀塘通明街64號地下 ☎️2343 5516 金鋒汽車服務 九龍樂富靜安街36號地下 ☎️9523 1657 灝天輪呔 九龍深水埗海壇街166號地下 ☎️69708432 棠記膠輪 九龍深水埗福華街77號地下 ☎️9234 1185 新界區： 金威膠輪有限公司 沙田火炭坳背灣街53-55 號美高工業大廈地下A舖 ☎️26620588 新昌膠輪公司 上水嘉富坊貿易廣場B座地下5號 ☎️9837 9847 新金成膠輪電池公司 粉嶺安居街8號地下 ☎️2674 6144 大眾輪胎行 元朗媽橫路47號 ☎️2477 2356 萬昌行 屯門建泰街6號恒威工業中心地下155號 ☎️91333830 歐洲品牌格林輪胎 熱賣好評！德國技術，品質保證！ 多謝大家的支持‍♂️‍♂️！ 本公司繼續極力推薦使用 歐洲品牌 格林輪胎 進化科技 定義未來 高強度胎體設計,完美匹配，表現出精湛抓地力與轉向性能。 胎邊結構:雙層聚酯纖維 雙層胎邊結構設計,提供絕佳過彎支撐性能,給於胎面在彎道中保有最大摩擦面積,賦予極佳的安全性與操控性能 A級濕滑✅胎面特殊配方，直線紋路設計有效降低阻滾動噪音，提高濕地性能。 強力轉向✅胎圈特殊材料補強設計提升輪胎支撐性，同時為轉向性能提供強力保障。 ＃歐洲品牌 ＃格林輪胎 ＃Greentrac ＃舒適低噪音 ＃最大排水量 ＃高穩定性擋塊 ＃降低道路噪音 ＃超低滾動阻力 ＃燃油節省 ＃超高性能輪胎 Greentrac Quest-X UHP 超高性能輪胎 採用德國技術3D主動靜音設計！ 熱賣中 性價比高 一致讚好 持續發威 另備有多款專為私家車型號(格林輪呔) 滿足有要求的客人 歡迎各位查詢預約 ＃港澳總代理 ＃智盈實業 https://wa.me/85297840529 | H45: 正面 | I45: 開心 | J45: 廣告/促銷 | K45: 廣告 | L45: 無關 | M45: 香港田灣, 幹諾道西, 筲箕灣, 柴灣, 觀塘, 樂富, 深水埗, 沙田火炭, 上水, 粉嶺, 元朗, 屯門 | N45: null | O45: null | P45: null | Q45: 0 | R45: 0 | S45: 0
A46: https://www.facebook.com/groups/366950274676457/permalink/1668946281143510/ | B46: Cheng Chris CC | C46: 46064 | E46: 路過火炭某品牌充電站，$10/度電 係咪真事 | G46: https://scontent-lax3-2.xx.fbcdn.net/v/t39.30808-6/631930484_793057963823140_3342356604380094594_n.jpg?stp=dst-jpg_s720x720_tt6&_nc_cat=103&ccb=1-7&_nc_sid=aa7b47&_nc_ohc=NVoNA922eBQQ7kNvwG8D_I2&_nc_oc=AdqL09s_hu9FZbBtKIAX9UrXH5b3Ixbk0UFSLIM1CohrfOGJNiLIyo2vx47oLNzIMOg&_nc_zt=23&_nc_ht=scontent-lax3-2.xx&_nc_gid=6g1ahlhL5sNWeG2B7XzX6A&_nc_ss=72289&oh=00_Af4E2gALKviVzCOaM-SAVEHyUwnBfjJLlrZxxUI04cBVnA&oe=6A109F44 | H46: 中性 | I46: 疑問 | J46: 收費/價錢 | K46: 求助 | L46: 直接相關 | M46: 火炭 | N46: null | O46: null | P46: null | Q46: 205 | R46: 85 | S46: 1
A47: https://www.facebook.com/groups/366950274676457/permalink/1666801761357962/ | B47: Megan Lin | C47: 46062 | E47: **已售** 我買多左，有無人有興趣，全新無用過，平價轉讓 | H47: 中性 | I47: 陳述 | J47: 其他 | K47: 廣告 | L47: 無關 | M47: null | N47: null | O47: null | P47: null | Q47: 3 | R47: 15 | S47: 0
A48: https://www.facebook.com/groups/366950274676457/permalink/1663965798308225/ | B48: Anonymous participant | C48: 46058 | D48: Tesla Wall Connector Gen 3 解鎖服務 | E48: 我有Tesla 充電器已安裝好三相電，因為Tesla 已賣，换了豐田Bz4x ，能改充電器可以充豐田嗎？謝解答 | H48: 中性 | I48: 疑問 | J48: 安裝/硬件/技術 | K48: 求助 | L48: 直接相關 | M48: null | N48: Tesla, 豐田Bz4x | O48: null | P48: 三相電 | Q48: 8 | R48: 10 | S48: 0
A49: https://www.facebook.com/groups/366950274676457/permalink/1661380738566731/ | B49: Tang Johnson | C49: 46056 | E49: 新人請教，一般用開邊幾個apps查找叉電位置？唔該 | H49: 中性 | I49: 疑問 | J49: 疑問/求助 | K49: 求助 | L49: 直接相關 | M49: null | N49: null | O49: null | P49: null | Q49: 1 | R49: 2 | S49: 0
A50: https://www.facebook.com/groups/366950274676457/permalink/1659371078767697/ | B50: Amuro Lee | C50: 46053 | E50: 《為何貨車電動化，會比私家車來得更快？誰會先到終點？》 談交通電動化，很多人直覺以為私家車會走在最前。但如果把情緒拿走，只看數字，答案其實相反：真正會率先完成轉型的，是貨車，而且會以更快、更乾脆的方式發生。 私家車的購買，往往混雜情感與身份。外形、品牌、引擎聲，經常壓過理性計算。一輛車一年跑一兩萬公里，入油固然浪費金錢，但不少人仍覺得「可以接受」。即使電動車在帳面上更省錢，也未必足以構成「非換不可」的壓力。 貨車完全不是這回事。它不是消費品，而是生產工具。車存在的意義只有一個：用最低成本，把貨準時送到。貨車一年行駛的里程，往往是私家車的數倍，燃料與維修費在總成本中所佔比例，遠高於買車本身。 對一輛年跑八萬公里的貨車而言，柴油與電力之間每公里那一點點差距，一年累積下來，已可達約十萬港元。五年下來，省下的燃料與維修費，足以抵消電動貨車較高的車價，甚至還有餘。這不是「環保加分」，而是直接改寫回本期與現金流的硬數字。CFO 不會為引擎聲浪動心，只會對著帳目下單。 更關鍵的是，貨車的更換周期本來就短。很多商用貨車跑到五年左右，已接近經濟壽命。每一次換車，都是重新計數的一次機會。只要新技術在五年總成本上佔優，整個車隊就會迅速翻頁，根本不需要等待社會共識。 使用模式亦令貨車更適合電動化。固定路線、固定倉庫、固定回站時間，意味著充電可以集中部署。對企業而言，自建充電設施不是負擔，而是一項可計算回報的基建投資。相比之下，私家車高度分散，對公共充電的依賴，反而拖慢了轉型節奏。 不同貨車類型，轉型速度亦不一樣。城市配送車、垃圾車、工程車，對續航要求不高，卻極度重視成本與耐用度。鈉離子電池的成熟，正好切中這些需求。一旦電池成本再被壓低，這類貨車的轉型只會更快。 真正困難的，是長途重型貨車。它們每天行駛數百公里，對重量、續航與補能時間都極為敏感。現有鋰電技術並非不能用，而是用得勉強：電池愈大，載貨愈少；充電愈快，壽命愈受影響。但隨著固態電池逐步進場，其潛在的高能量密度、快充能力與安全邊際，正好對準長途貨車的痛點，為全面電動化提供了真正可行的技術條件。 交通電動化，從來不是一場道德運動，而是一道算術題。私家車的轉變，取決於人心；貨車的轉變，只取決於帳目。當高里程遇上低營運成本，再加上日新月異的電池技術，結果不只是私家車的慢慢轉向，而更可能是一場來勢洶洶的電動貨車革命。 | H50: 中性 | I50: 陳述 | J50: 資訊分享 | K50: 純分享 | L50: 間接相關 | M50: null | N50: null | O50: null | P50: null | Q50: 0 | R50: 0 | S50: 0
A51: https://www.facebook.com/groups/366950274676457/permalink/1657317052306433/ | B51: Well Done Charge | C51: 46051 | E51: 觀塘鴻圖道6號新開張有10支車充 250KW 開張期2.2/kWh | H51: 中性 | I51: 陳述 | J51: 充電站設施/位置 | K51: 純分享 | L51: 直接相關 | M51: 觀塘鴻圖道6號 | N51: null | O51: null | P51: 250kW | Q51: 107 | R51: 73 | S51: 8
A52: https://www.facebook.com/groups/366950274676457/permalink/1657843698920435/ | B52: Amuro Lee | C52: 46051 | E52: 近代史上最失敗的車：Tesla Cybertruck 今日英國雜誌 Auto Express 出了一個專題：《近代最失敗的車》。天行入去掃了一掃，這談不上是嚴謹的研究，有些入選者甚至不算失敗 (平治 A-class 三代半賣了6百萬部都算失敗？)，但其他大部分確是銷售數字跟原本預算相距甚遠，往往相差幾倍。以我寫了近30年車的印象，圖中黃色那部小車應該是其中的表表者。 它名為 Nano，由印度車廠 Tata 在2008年推出，賣點是全世界最平的車，各方面都設計到節省生產成本，兼且慳油，目的是令貧窮的印度普羅大眾都可以負擔得起買車，不用再靠危險的電單車代步。老闆 Ratan Tata 雄心壯志，自視為印度的亨利福特，誓要憑個人之力把印度推進全民汽車時代，當時我都對他肅然起敬。 Tata 的目標是每年賣至少25萬架，但廠房的最高容量可達50萬架。如果也爆滿，還可以外判組裝。 結果銷量大失所望，第一個全年賣了7萬架，第二個全年7萬5千架…… 最終累積生產30萬部便停產了。換句話說，頭兩年的銷量分別只及原本目標下限的28%和30%，看來當時印度人的經濟狀況還未準備好迎接汽車時代。 不過，Auto Express 沒有提到的是，其實 Tata Nano 的記錄已經被 Tesla Cybertruck 打破了。根據研究機構 Cox Automotive 的推算，Cybertruck 在頭兩個銷售全年分別只賣了3萬9千架 (2024) 和2萬架 (2025)，只及原來目標下限25萬架的16%和8%。這個記錄，印象中在大量生產的汽車中從來都未見過，至少在過去40年也沒有。無須多說，使用率低下的德州廠房正在虧蝕營運。 為了避免尷尬，Elon Musk 已經竭盡所能，例如把 Cybertruck 的銷量數字混入 Model S 和 Model X 而不公開。傳聞他旗下的 SpaceX 也買了1000輛 Cybertruck 來幫忙 (有沒有大幅 discount 便不得而知了)。另一單來自IT界的獨立新聞說，他旗下的 xAI 為了獎勵員工，完成工作 target 便可獲贈一輛 Cybertruck！反正賣唔出，送員工好過。😂 過去多年來，Elon Musk 一次又一次創造奇跡，令他成為了許多人的偶像，甚至是神。不過 Cybertruck 一役可稱為他的滑鐵盧，「不敗戰神」的神話幻滅。更令人擔心的是，Cybertruck 的失敗反映出他的市場觸覺可以有幾差，樂觀的預測可以有幾離譜。如果說 Tesla 的造車業務由盛轉衰，走向沒落，Cybertruck 就是轉捩點。 | H52: 負面 | I52: 失望 | J52: 資訊分享 | K52: 純分享 | L52: 無關 | M52: null | N52: Tesla Cybertruck, Tata Nano | O52: Tesla, Tata | P52: null | Q52: 0 | R52: 0 | S52: 0
A53: https://www.facebook.com/groups/366950274676457/permalink/1657380435633428/ | B53: Namrr Leung | C53: 46051 | E53: 請問紅磡區邊度有地舖ev充電站？ | H53: 中性 | I53: 疑問 | J53: 疑問/求助 | K53: 求助 | L53: 直接相關 | M53: 紅磡 | N53: null | O53: null | P53: null | Q53: 0 | R53: 0 | S53: 0
A54: https://www.facebook.com/groups/366950274676457/permalink/1651859559518849/ | B54: Amuro Lee | C54: 46044 | E54: 內文： https://unwire.hk/2026/01/22/geotab-ev-battery-health-fast-charging-study-2025/life-tech/auto/ | H54: 中性 | I54: 陳述 | J54: 資訊分享 | K54: 純分享 | L54: 直接相關 | M54: null | N54: null | O54: null | P54: null | Q54: 0 | R54: 1 | S54: 0
A55: https://www.facebook.com/groups/366950274676457/permalink/1651438122894326/ | B55: Anonymous participant | C55: 46044 | E55: 北角有45分鐘充電送 | G55: https://scontent-ord5-2.xx.fbcdn.net/v/t39.30808-6/616391291_2092327904867367_4803528762438411093_n.jpg?stp=dst-jpg_s720x720_tt6&_nc_cat=104&ccb=1-7&_nc_sid=aa7b47&_nc_ohc=zszLHWLF2tEQ7kNvwHZkO3d&_nc_oc=AdrY7SgmCWW-Cs9xe-7oWDf3RQiNar7mBAACBCYMU935LuybnMhHrThyliqUmx6--es&_nc_zt=23&_nc_ht=scontent-ord5-2.xx&_nc_gid=wkgOKGVJHGqfPVz_yaj5MA&_nc_ss=72289&oh=00_Af4WkH9RnOERVQaD7A6tVeNpNhwsh_eTpaG4j1Ltlkj1iw&oe=6A10BF15 | H55: 中性 | I55: 陳述 | J55: 廣告/促銷 | K55: 廣告 | L55: 直接相關 | M55: 北角 | N55: null | O55: null | P55: null | Q55: 13 | R55: 3 | S55: 0
A56: https://www.facebook.com/groups/366950274676457/permalink/1651221639582641/ | B56: Amuro Lee | C56: 46043 | E56: 今日 Tesla，昨日福特。 今日消息：Tesla 失去了坐擁多年的歐洲EV銷量冠軍寶座，首次被福士 (Volkswagen) 超越。 去年 Tesla 在歐洲的銷量下跌了27%，至23.9萬架。相反，福士的EV銷量大增了56%，至27.4萬架。 更恐怖的是，這裡說的只是福士(VW)品牌。福士集團旗下還有 Skoda (17.2萬架，勁升117%)、Audi (15.4萬架，升51%)、Cupra (8萬架，升66%) 和 Porsche 等品牌都有EV，全集團在歐洲共賣了74.3萬架，是 Tesla 的三倍幾。 以型號計，Tesla Model Y 仍是歐洲銷量冠軍 (15.1萬架)，Model 3 則位列第三 (8.6萬架)，第二是 Skoda Elroq (9.4萬架)，第四是 Renault 5 (8.1萬架)，然後是 VW 的 ID4、ID3 和 ID7 (各有約8萬架)，證明 Tesla 單靠兩款車是無法戰勝傳統車廠的多樣化策略，Tesla 雄霸EV市場的日子一去不返。 福士還好戲在後頭，更平價，更大眾化的 ID Polo 和 lD Cross 將會在今年上市，預期銷量會繼續攀升。 Tesla 現在用的產品策略，說穿了，其實是抄襲100年前的美國福特。Henry Ford 當時堅持只專注生產一款型號，就是 Model T，將所有精力用來簡化機械，改善生產流程，提升生產效率，利用規模壓低成本，令 Model T 可以不斷減價，達致雄霸市場。Model T 在1908年推出，至1923至25年間產量達到高峰，連續三年都賣到2百萬架，比現在的 Tesla 更勁！這個紀錄，至今還未有其他車破到。 不過，亦因為過度偏重生產力提升，犧牲了產品的個性和多樣化。當時有一句笑話，據說是亨利福特自己所說：「你可以選擇任何顏色，只要是黑色便可。」，因為全部清一色最容易生產，而且黑色油漆是最快乾的！ 當市場缺乏有競爭力的對手，當然沒有問題。但1920年代通用汽車(GM)掘起，採用截然不同的產品策略。GM收購了多個汽車品牌，為每個品牌都開發不同外形、不同大小、不同引擎、不同配備的車款，以多樣化、不同價錢級數的產品給顧客選擇。結果，1927年GM銷量首次超越福特。亨利福特試圖以新款 Model A 去還擊，雖然在1929和30年奪回銷量冠軍，但此後一直輸給GM，歷時77年。自此，福特也不得不改變策略，跟GM一樣提供多樣化選擇。 有趣的是，Elon Musk 把他的車全部命名為 Model _，明顯是仿效當年的亨利福特。如今，只靠兩款車(還是同一底盤，大量零件共用)走天涯，在競爭日益白熱化，市場上EV選擇越來越多的情況下是否還可行？觀乎福特的歷史教訓，和現在福士集團在歐洲的成績，我認為是否定的。 | H56: 負面 | I56: 失望 | J56: 資訊分享 | K56: 純分享 | L56: 間接相關 | M56: 歐洲 | N56: Tesla Model Y, Tesla Model 3, Skoda Elroq, Renault 5, VW ID4, VW ID3, VW ID7 | O56: Tesla, Volkswagen, Skoda, Audi, Cupra, Porsche, Renault, Ford, GM | P56: null | Q56: 0 | R56: 0 | S56: 0
A57: https://www.facebook.com/groups/366950274676457/permalink/1648642689840536/ | B57: Amuro Lee | C57: 46040 | E57: 講錢傷感情 ‍♂️1）首先用政府津貼作包裝，司哋車場業主講話一蚊都唔洗出，引佢哋落疊。 2）車場業主落疊後，被中天價標，所有車場業主每人要夾2萬多，油車都要夾。 3）車場業主震驚想反口唔俾錢，依家被恐嚇話唔做都要每人夾一萬，住宅業主都要夾。係，你無睇錯，住宅業主都要夾。 1月8日投支持蕉生個3成人，有冇考慮多謝吓趕走佢個7成人。唔係佢隻電樁人fans重日日喺度電樁電樁電樁。好似冇咗電樁，但痴唔出屎咁。領都業委會 如推翻早前業主大會 決定安裝 「EV充電樁工程」 所有住戶單位 需賠萬元以上 並喪失 政府資助 1500萬 | H57: 負面 | I57: 生氣 | J57: 收費/價錢 | K57: 純分享 | L57: 直接相關 | M57: null | N57: null | O57: null | P57: null | Q57: 0 | R57: 0 | S57: 0
A58: https://www.facebook.com/groups/366950274676457/permalink/1648509626520509/ | B58: Roy Ng | C58: 46040 | E58: 浩記汽車美容 如有興趣或其他汽車美容 詳情或預約可聯絡☎️51992395。賢☎️ 未必隨時聽到電話 只用WhatsApp 回覆 https://m.facebook.com/八鄉汽車美容-洗車-打蠟-蒸籠-140889456736875 日本9H 白金塗層復合鍍膜 1-2年期 深層研磨去漬拋光 除花痕去蜘蛛紋 鍍晶水腊人手泡泡洗車 推泥膠 去污 凡惠昌顧9H塗層鍍鏌加送 納米空氣觸媒消毒蒸籠 冷氣殺菌消毒服務 ⛔️半年保養⛔️ 現優惠價2️⃣5️⃣0️⃣0️⃣ （全車深層清潔消毒套餐 ） 鍍鏌洗車液 人手泡泡洗車 推泥膠 去污 ➕吸塵 洗鈴 清潔玻璃 ➕ 霧化藥水消毒 除甲醛 除味 防霉 ➕ 藥水泡泡深層清潔內籠 ➕納米空氣觸媒殺菌消毒除味 ➕冷氣殺菌消毒服務 現優惠價9️⃣5️⃣0️⃣ （ 跣水3M三重水晶蠟消毒蒸籠套餐 ） 鍍鏌洗車液 人手泡泡洗車 推泥膠 去污 ➕ 吸塵 口清潔玻璃 洗鈴 ➕ 冷氣霧化消毒 除甲醛 除味 防霉 ➕三層3M水晶蠟（深度去漬去花拋光） ➕藥水泡泡深層清潔內籠 ➕納米空氣觸媒殺菌消毒除味 ➕冷氣殺菌消毒服務 現優惠價 1️⃣8️⃣8️⃣8️⃣ 以下個別項目因應車輛大小 有所調整 以下是各式單項服務及價錢 A : 鍍鏌洗車液 人手洗車 推泥膠 內籠吸塵清潔 洗鈴 1️⃣4️⃣8️⃣起 B：納米空氣觸媒霧化消毒 內籠連冷氣 除菌 除味防霉 4️⃣2️⃣0️⃣起 C：藥水泡泡深層清潔蒸籠 包吸塵 （座位 座位底 尾箱 冷氣口 地毯） 4️⃣8️⃣0️⃣起 D: 一層3M打蠟（拋光 輕度去花去漬） 洗車 吸塵 推泥膠 洗鈴及清潔玻璃 5️⃣0️⃣0️⃣ E: 跣水3M三重水晶蠟 （深度去花去漬拋光水晶臘） 洗車 吸塵 推泥膠 洗鈴及清潔玻璃 9️⃣8️⃣8️⃣ 起 F: 玻璃鍍晶 線水 去油膜 起污漬 5️⃣0️⃣0️⃣起 G: 清洗引擎箱 3️⃣0️⃣0️⃣ H: 頭燈翻新（一對） 6️⃣0️⃣0️⃣ #洗車 #打臘 #汽車美容 #蒸籠 #除味消毒 #八鄉汽車美容 #去漬 #9H鍍鏌 #內籠清潔 #打腊 #霧化消毒 #拋光 #去花痕 #元朗 #保護層 #撥水 | H58: 中性 | I58: 陳述 | J58: 廣告/促銷 | K58: 廣告 | L58: 無關 | M58: 八鄉, 元朗 | N58: null | O58: null | P58: null | Q58: 0 | R58: 0 | S58: 0
A59: https://www.facebook.com/groups/366950274676457/permalink/1644540090250796/ | B59: Amuro Lee | C59: 46035 | E59: 汽車界的望夫石：Tesla Roadster Mk2 沙田有一個名勝叫「望夫石」，話說一個婦人天天背着嬰孩上山眺望，等待出海的丈夫歸來，但年復一年也未見，最終等到變成化石。這個故事車壇都有，就是 Tesla Roadster。 2017年，Elon Musk 公開介紹了這款新產品的原型車，說它是全世界最快、最好的車，定價20萬美元，即時接受預訂，2020年投產。 到了2020年，他改口到2021年投產。 到了2021年，他改口到2022年投產。 2022年還未到，他又改口到2023年投產。 到了2023年，他改口到2024年投產。 到了2024年，他改口到2025年初投產。 到了2025年，他又改口到2027年投產。 這樣便過了10年。10年在車壇來說是很長的時間，即使對傳統車廠來說也是，何況是進展快速的電動車行業？如果Tesla真的10年前已開始研發，現在很多零件和系統已經過時，必須重新設計了。 與其說有什麼技術原因造成這個延誤，不如說是商業原因吧。 第二代 Roadster 是 Tesla 的 "halo car"，一款用來宣傳而非實質有經濟貢獻的跑車。量產型跑車市場在近30年已嚴重衰退，很多車廠都不再生產，因為銷量大不如前。寶馬一年可賣50萬部3系列房車，但Z4跑車只能賣1萬架，連開發成本也賺不回，所以決定不會再有下一代Z4。市場上仍然有利可圖的生產型跑車大概只剩下保時捷911和福特 Mustang，其餘都是小量生產的高端品牌。 就算最終成功投產，Roadster 的20萬美元價格注定每年只能賣數千輛，對 Musk 或 Tesla 的業務來說只是可有可無，用來粉飾一下櫥窗而已。 在我來看，這款車只是煙幕，每當 Tesla 的新產品計劃乏善足陳時，Musk 便會在 X 發佈關於 Roadster 的新消息，有什麼新噱頭，伴隨一個再次延後的投產時間。其他車廠的 halo car 都是用來提升自家形象的蝕本貨，但 Musk 的 halo car 更高明，連生產也不用投入，光靠在 X 發一兩句文便樂壞教徒了，一毫子也不用花。 | H59: 負面 | I59: 失望 | J59: 資訊分享 | K59: 純分享 | L59: 間接相關 | M59: null | N59: null | O59: null | P59: null | Q59: 0 | R59: 0 | S59: 0
A60: https://www.facebook.com/groups/366950274676457/permalink/1643684383669700/ | B60: Amuro Lee | C60: 46034 | E60: 試駕 Tesla 剛休學回來的香港學生要買車。因為對方早上才成功重新申領駕照，暫時只得臨時駕照，只能由我代為試車。他對一輛價錢約一萬九千美元的二手 2021 Tesla Model 3 三心兩意。於是我們下午來到 Tesla 的經銷商。原來 Tesla 的二手車是不能試駕的，結果他們安排了一輛 2024 年的 Model 3 展銷品給我們體驗一下。 出發前，職員給我們講解汽車的基本功能與操作。當然比起我的二十年車齡老車先進得多了。 職員給我們放行以後，我們先啟動全自動駕駛模式 Full Self-Driving (supervised)，開往附近的超級巿場。汽車在巿區的道路行走自如，曉得自己切線、轉彎，甚至來到超級巿場以後，懂得自己找泊位，然後自行倒車泊進去，看得我目瞪口呆。這個功能，對於泊車技術拙劣，經常偏向左邊甚至踩線的我，非常有用。 然後我們決定關掉 FSD，開上高速公路跑一小段，看看它的 adaptive cruise control 到底如何。然後發現原來 Tesla 雖然跟一般的汽車一樣有兩個腳踏，但實際上是採用 single-pedal driving 模式，在巿區的道路上面，如果把腳從「油門」鬆開，汽車就會很快停下，效果跟 hard braking 沒有分別。短短半小時的測試時間，還沒有適應這種運行模式，反倒因此覺得有點兒暈昡。 來到公路，adaptive cruise control 大派用場。雖然只是一小段，但真的會緊隨前車而自動加快減慢。只是與前車之間的距離，雖然還沒有達到 tailgating，但還是比起我平常覺得舒服的距離要短。也許是我平常開得比較保守，也因此經常製造機會給其他汽車切線超越吧。 抵達目的地以後，我們決定回程。本來打算 FSD 上公路回去經銷商那裡，但搞了老半天，我們都無法迫使系統取道高速公路，於是只能死死氣的讓 FSD 自己走巿區道路回家了，走了十分鐘。期間行車表現，遠比我剛才手動開車更為順暢。 回到經銷商以後，FSD 自己找泊車位，然後倒車進去。兩旁的都是 Tesla，但 FSD 卻不跟兩旁的車平排，而是逐點逐點的繼續倒後。 之後好像撞到後方的另一架 Tesla，然後就自動停止了。幸好原來 Tesla 的防撞桿是塑膠的，因此兩車絲毫無損。最後我們手動把車子移前少許，完成今天的試駕體驗。 雖然我真的很不喜歡 Elon Musk 這個人，也對 Tesla 的質量與安全性無從置喙，但也不得不承認 Tesla 在一些方面的確很有遠見、很先進。這是一次相當有趣的體驗，讓我大開眼界。當然，我習慣不了 Tesla 的操控；反正自的老車還可以走，也不打算換車，可見將來也沒有意思買他們的產品。 | H60: 中性 | I60: 陳述 | J60: 資訊分享 | K60: 純分享 | L60: 間接相關 | M60: null | N60: Tesla Model 3 | O60: Tesla | P60: null | Q60: 1 | R60: 0 | S60: 0
A61: https://www.facebook.com/groups/366950274676457/permalink/1641695733868565/ | B61: Teddy Tong | C61: 46031 | E61: Model Y 唔使30萬？ | G61: https://scontent-sjc6-1.xx.fbcdn.net/v/t39.30808-6/613083739_122259926210190439_3347382445980746545_n.jpg?stp=dst-jpg_s720x720_tt6&_nc_cat=104&ccb=1-7&_nc_sid=aa7b47&_nc_ohc=jHZ9n3ZMJj4Q7kNvwH6tr66&_nc_oc=Adrodd3LJ2fZzAnULfV1ujtAsg7YIZLBpnDFzAZxtrc_AKJ8mEBDpLmbpmYr6RDe4P0&_nc_zt=23&_nc_ht=scontent-sjc6-1.xx&_nc_gid=Il4HE2c_YBEaCjFZchdSuA&_nc_ss=72289&oh=00_Af68zPuyzvJHPW0wWqgMtDLpvDEUqTG0j4QCVOnOZeZfkQ&oe=6A10C7BE | H61: 中性 | I61: 疑問 | J61: 疑問/求助 | K61: 求助 | L61: 間接相關 | M61: null | N61: Tesla Model Y | O61: null | P61: null | Q61: 92 | R61: 105 | S61: 1
A62: https://www.facebook.com/groups/366950274676457/permalink/1638450820859723/ | B62: Sam Ho | C62: 46027 | E62: ## **新充電站︰中國石油 Flash Charge 灣仔及元朗充電站** | H62: 中性 | I62: 陳述 | J62: 充電站設施/位置 | K62: 純分享 | L62: 直接相關 | M62: 灣仔, 元朗 | N62: null | O62: 中國石油 Flash Charge | P62: null | Q62: 2 | R62: 0 | S62: 0
A63: https://www.facebook.com/groups/366950274676457/permalink/1637231994314939/ | B63: Amuro Lee | C63: 46025 | E63: 電動車的礦產迷思：誰在誇大污染？《電動車的礦產迷思：誰在誇大污染？》 「電動車要挖那麼多礦，污染一定比汽油車更嚴重。」這句話近年反覆出現，聽起來像是理性質疑，實際卻經不起推敲。它抓住了一個真實片段——電動車確實需要鋰、鎳、鈷等礦物——然後把整個故事說反了。 先把事實擺清楚。電動車的污染，主要集中在生產階段，尤其是電池製造。採礦、冶煉、加工，當然會產生排放，這一點無須否認。但內燃機車並非「不用挖礦」。一部汽油車從誕生到報廢，同樣需要大量鋼鐵、鋁材、銅，更依賴一個龐大而且必須每天運轉的系統：石油勘探、鑽井、輸油管、油輪、煉油廠、加油站網絡。只是這些污染被攤散在時間與空間之中，久而久之被視為理所當然。 真正的差別，在於「一次性」與「持續性」。這一點不靠形容詞，靠數字就能說清楚。 以一部中型電動車、配備 60 kWh 的 LFP（磷酸鐵鋰）電池為例，電池中大致包含 約 6 公斤金屬鋰、約 41 公斤鐵、約 70 公斤磷酸根（PO₄）。這些礦物在出廠前一次性投入，用十多年，之後仍可回收再用，並非每行駛一公里就要再挖一次。 若換成同樣容量的 NMC（三元鋰）電池，結構不同，但量級同樣清楚。以現行高鎳配方的平均值計算，一組 60 kWh NMC 電池大約包含 約 9 公斤金屬鋰、約 33 公斤鎳、約 5 公斤鈷，以及約 18 公斤錳與鋁、銅等其他金屬。合計起來，仍然只是「數十公斤級」的金屬材料，而不是無限擴大的礦產需求。 把同一把尺放到汽油車身上，畫面立刻失衡。一部汽油車行駛 150,000 公里，以 6.3 公升／百公里的油耗計，整個使用期會燒掉約 9,450 公升汽油。這些汽油背後，大約對應 約 20,000 公升原油的開採與煉製，換算成重量，約 17,000 公斤原油。這不是一次性投入，而是在車輛壽命中被一點一滴燃燒、排放、消失。 於是對照非常直接： 電動車被反覆放大的，是一次性投入的 數十公斤可循環金屬； 汽油車被習慣性忽略的，卻是整個生命週期中燃燒掉的 萬公斤級不可回收原油。 把這兩者放在同一個「誰比較污染」的框架下，本身就已經錯位。 再看全生命週期。即使把採礦與製造的碳排放全部算進去，在歐洲或英國現時的電力結構下，電動車在行駛數萬公里後，總排放已低於同級汽油車；之後跑得越久，差距越大。原因很簡單：電網在去碳化，而汽油車的排放路徑是固定的，永遠靠燃燒化石燃料前進。 有人說，不只二氧化碳，還有空氣與水污染。這話聽來全面，其實結論一樣。內燃機車的空氣污染是即時、分散、貼近人群的：氮氧化物、揮發性有機物、PM₂.₅，每一公里都在城市街道排放，直接構成公共衞生風險。電動車在行駛時沒有尾氣；即使電力仍有少量來自化石燃料，污染也集中在固定電廠，能監管、能改善，性質完全不同。 水污染亦然。鋰礦等電池礦產的開採，確實可能對局部水資源造成壓力，這是電動車產業需要面對的現實問題；但石油體系的水污染是長期而系統性的：油田含油廢水、輸油管滲漏、油輪事故與煉油排放，任何一次大型漏油，都可能對海洋與地下水造成以十年計的破壞。這不是偶發事故，而是化石燃料體系內建的風險。 談到這裏，往往有人追問：「電池報廢怎麼辦？」現實卻比想像清楚得多。現行回收技術下，鈷、鎳、銅等金屬的回收率已普遍可達九成以上，鋰亦進入七至九成的量級。金屬會留下來，再被利用；那 17,000 公斤原油，一經燃燒，就不可能回收一克。 還有一個經常被忽略的對照：我們每天都在使用含鋰與多種金屬礦物的產品。手機、筆電、平板、藍牙耳機，裏面同樣含有鋰、鎳、鈷、銅等材料，卻很少有人因此質疑「用手機是否不環保」。原因其實很直覺：材料是一次性投入，可以回收；真正造成持續污染的，是每天被燃燒掉的能源。這套常識用在消費電子上毫無爭議，卻突然否定在電動車身上，本身就是雙重標準。 更何況，電池技術仍在演進。鈉離子電池不需要鋰、鎳、鈷，已開始進入市場，有潛力在部分應用上取代 LFP；更長遠看，固態電池若能成熟，亦可能逐步取代現行的 NMC。換言之，電動車對關鍵礦產的依賴，是下降中的變數，而不是固定不變的負擔。 當然，電動車並非完美。它仍然有輪胎磨損造成的微粒污染，也無法解決交通擠塞這類城市結構問題。但這些問題，汽油車一樣存在，還要額外加上引擎與排氣系統的污染。電動車不是萬靈丹，但在幾乎每一個可量化的環境指標上，都比內燃機車更好。 把「數十公斤可循環金屬」無限放大，卻對「萬公斤不可回收原油」的日常燃燒視而不見，這不是理性比較，而是一種讓人安心維持舊系統的說法。真正值得被質疑的，從來不是電動車用了多少礦，而是我們為何仍願意接受一個必然持續燃燒、持續排放，還伴隨漏油風險的交通方式。 | H63: 中性 | I63: 陳述 | J63: 資訊分享 | K63: 純分享 | L63: 間接相關 | M63: null | N63: null | O63: null | P63: null | Q63: 0 | R63: 0 | S63: 0
A64: https://www.facebook.com/groups/366950274676457/permalink/1637074907663981/ | B64: Amuro Lee | C64: 46025 | E64: Tesla自2017年把Motors一詞從公司名稱中刪去開始，早已不是以電動車生產商為定位了‍♂️2025年過去，Tesla 連續2年全球銷量下跌，比之前一年又跌了9%至只有160萬架。同期BYD的純電動車銷量大增29%至226萬架，超越 Tesla 成為電動車一哥。 正如之前的預測，所謂「平價版」Model Y 和小改款的 Model 3 對扭轉跌勢無濟於事，在未有新車開發的情況下，今年跌勢恐怕只會加劇…… Elon Musk 的如意算盤是 Robotaxi 試用進展加快，Optimus 機械人順利推出和受市場歡迎，那麼 Tesla 便能成功轉型為自動駕駛網約車服務商和機械人公司。 個人維持原有看法，Tesla 作為汽車生產商的日子已寥寥可數，也許只剩下三數年。即使 Robotaxi 成功，由於它只是軟件，硬件仍沿用現有的車款，基本上不用生產新車，可以如 Uber 般利用現有顧客的車提供服務，近乎無本生利。隨著新車銷量持續下跌，工廠使用率也下跌，零件供貨價格反而上升，賣車業務的利潤只會下挫，甚至轉虧…… 不過這一切應該都是在 Musk 的預算中，最後兩間美國工廠(加州和德州)會不會賣給中資，成為BYD等進軍美國市場的橋頭堡？反正自己都要退出造車業務，對他已經毫不重要了，價高者得便是了。 對於現有 Tesla 的車主，羡慕他們的樂觀，他們是幸福的，因為可以擁有一輛品牌將會絕跡的「名車」，正如買了末代 Saab 或 Rover 的朋友。不過將來要修車的話便麻煩了，問問開 Saab 或 Rover 的人便知。 | H64: 負面 | I64: 失望 | J64: 資訊分享 | K64: 純分享 | L64: 間接相關 | M64: null | N64: Tesla Model Y, Tesla Model 3 | O64: Tesla, BYD | P64: null | Q64: 0 | R64: 0 | S64: 0
A65: https://www.facebook.com/groups/366950274676457/permalink/1636497594388379/ | B65: Amuro Lee | C65: 46024 | E65: 電動車最耐用的其實是那嚿電池 ‍♂️《電動車最耐用的，其實就是那舊電池》 很多人至今仍然深信一個說法：電動車電池用幾年就要換，成本高、風險大，好似手機電池一樣。這個印象流傳多年，但其實從一開始就建基於一個錯誤類比。電動車電池之所以被誤解，並不是因為數據不足，而是因為大家太習慣用手機去想像一部車。 首先要講清楚一個關鍵事實：手機與電動車，用的並不是同一種取向的電池化學。現今智能手機的電池，仍然主要以 LCO（鋰鈷氧化物） 為核心。LCO 的最大優點，是能量密度高，容易做到又薄又輕，正好配合手機對體積與重量的極端要求；但代價亦很清楚——結構穩定性較低，並不適合承受長時間、高循環的使用。 這並不是失誤，而是產品策略。手機本來就被設計為數年一換，電池追求的是即時體驗，而不是二十年壽命。每日由低電量充到滿格，反覆完成完整充放電循環，加上幾乎沒有主動散熱，電池老化自然來得快。廠商亦心知肚明，所以會提供付費更換電池的選項，作為產品生命周期的一部分。 電動車則走在完全相反的方向。車用電池的主流陰極化學，是 NMC（鎳錳鈷）或 LFP（磷酸鐵鋰）。這兩者的共同點，不是極致能量密度，而是穩定、耐用、可承受長期循環。尤其是 LFP，續航表現未必最亮眼，但壽命長、安全性高，正正反映車廠的工程取態：寧願犧牲一點性能，也不要短命。 除了化學本身不同，電動車還多了一層手機沒有的保護。整個電池組配備完整的熱管理系統，長期將溫度控制在理想範圍；電池管理系統亦刻意限制充放電上下限。儀表顯示的 100%，並非真正用盡；顯示的 0%，亦未到極限。這些看不見的保守設計，正是電池能夠慢慢老化，而不是迅速衰退的原因。 使用方式亦大相逕庭。手機幾乎每天都完成一次完整循環；電動車多數時間只是部分充放電，例如由 40% 補到 80%。對電池而言，這屬於溫和操作，對陰極結構的破壞遠低於手機那種「用盡再充」的節奏。 這些差異，已在現實數據中反映出來。來自 Geotab 的研究，分析大量實際行駛中的電動車後發現，現代電動車電池的平均容量衰減率，每年只有約 1–2%。按這個速度推算，電池使用 20 年後仍然具備實際用途。在不少情況下，反而是車身老化、技術淘汰或維修成本不合比例，電池本身仍然可以繼續工作。 因此，所謂「電動車最大風險是電池」，更多是一種心理投射。人們把手機電池的經驗，錯誤地套用到一個完全不同的工程產品上。手機電池短命，是因為它本來就被設計成短命；電動車電池長命，亦不是奇蹟，而是從化學選擇開始就已經鎖定的結果。 當這一點被看清，電池焦慮其實就失去了立足之地。真正會先被淘汰的，往往不是那舊電池，而是整部車。 | H65: 正面 | I65: 陳述 | J65: 安裝/硬件/技術 | K65: 純分享 | L65: 間接相關 | M65: null | N65: null | O65: null | P65: null | Q65: 2 | R65: 0 | S65: 0
A66: https://www.facebook.com/groups/366950274676457/permalink/1635670447804427/ | B66: 陳傲輝 | C66: 46023 | E66: 咁大架車，1度行6公里，為起3毫，堅唔堅呀？ | H66: 中性 | I66: 疑問 | J66: 收費/價錢 | K66: 求助 | L66: 直接相關 | M66: null | N66: null | O66: null | P66: null | Q66: 1 | R66: 1 | S66: 0
A67: https://www.facebook.com/groups/366950274676457/permalink/1635664104471728/ | B67: 陳傲輝 | C67: 46023 | E67: 各位新年快樂，齊給滿電出發 | H67: 正面 | I67: 開心 | J67: 其他 | K67: 純分享 | L67: 間接相關 | M67: null | N67: null | O67: null | P67: null | Q67: 0 | R67: 0 | S67: 0
A68: https://www.facebook.com/groups/366950274676457/permalink/1634075887963883/ | B68: Chan Fai | C68: 46021 | E68: # 各位師兄好，分享今日幫一個師兄台E-GOLF加裝電池包，從原先電池衰減到20KWH只可以行120KM左右，升級後可以行到250左右kM，到時候驗車又可以拆返出來，電池同充同放，香港都可以裝，有續航焦慮慨師兄可以PM我！ | H68: 正面 | I68: 期待 | J68: 廣告/促銷 | K68: 廣告 | L68: 直接相關 | M68: 香港 | N68: E-GOLF | O68: null | P68: null | Q68: 2 | R68: 0 | S68: 0
A69: https://www.facebook.com/groups/366950274676457/permalink/1633979174640221/ | B69: WingMan Tong | C69: 46021 | E69: 想問有冇貼PPF好介紹？ | H69: 中性 | I69: 疑問 | J69: 疑問/求助 | K69: 求助 | L69: 無關 | M69: null | N69: null | O69: null | P69: null | Q69: 0 | R69: 0 | S69: 0
A70: https://www.facebook.com/groups/366950274676457/permalink/1633366641368141/ | B70: Amuro Lee | C70: 46020 | E70: Elon Musk: ‍♂️當傳統車廠還在糾結「電動車是不是為了減碳」，馬斯克已經直接下了重話。針對 Ford 縮減電動車策略的消息，他直言這象徵傳統汽車產業正走向無可避免的衰亡，甚至形容是「注定的死路一條」，言辭一如既往地毒辣，也再次點燃電動化與自動駕駛的論戰。 馬斯克也重申他多年前的預言：沒有自動駕駛能力的內燃機汽車，就像一邊騎馬一邊用摺疊手機，看似能動，實際卻已脫離時代。傳統產業往往不是看不懂，而是不願改變，最後只能眼睜睜走向被淘汰的結局。這番話不只是嘲諷福特，更像是在替整個汽車產業畫出一條殘酷的未來分界線。 https://www.techbang.com/posts/127017 | H70: 負面 | I70: 陳述 | J70: 資訊分享 | K70: 純分享 | L70: 間接相關 | M70: null | N70: null | O70: Ford, Tesla | P70: null | Q70: 0 | R70: 0 | S70: 0
A71: https://www.facebook.com/groups/366950274676457/permalink/1631506264887512/ | B71: Lo Yuk Fai | C71: 46017 | D71: www.etnet.com.hk | E71: 有冇電車車主試過冇番廠定檢，但之後要番廠用保養服務，如壞大電？ | H71: 中性 | I71: 疑問 | J71: 疑問/求助 | K71: 求助 | L71: 直接相關 | M71: null | N71: null | O71: null | P71: null | Q71: 0 | R71: 2 | S71: 0
A72: https://www.facebook.com/groups/366950274676457/permalink/1629840078387464/ | B72: Chan Fai | C72: 46015 | E72: 各位師兄好 分享一個電池外裝，升級續航方案，唔使郁電池，唔使拆線，同充同放，唔使驚驗車，香港都可以安裝，有興趣慨師兄可以PM我，根據你的車型詳細傾 | H72: 中性 | I72: 陳述 | J72: 廣告/促銷 | K72: 廣告 | L72: 直接相關 | M72: null | N72: null | O72: null | P72: null | Q72: 0 | R72: 2 | S72: 0
A73: https://www.facebook.com/groups/366950274676457/permalink/1630272261677579/ | B73: Jack Chan | C73: 46015 | E73: 荃灣 Matakok （ 馬角街18號）個場新淨、闊落，好泊 有月租私家車及貨車位 | H73: 正面 | I73: 滿意 | J73: 充電站設施/位置 | K73: 純分享 | L73: 間接相關 | M73: 荃灣馬角街18號 | N73: null | O73: null | P73: null | Q73: 1 | R73: 0 | S73: 0
A74: https://www.facebook.com/groups/366950274676457/permalink/1628884555149683/ | B74: Cheng Chris CC | C74: 46014 | E74: 1蚊1蚊1蚊 | G74: https://scontent-atl3-2.xx.fbcdn.net/v/t39.30808-6/602942210_753742077754729_5598415628283943375_n.jpg?stp=cp6_dst-jpg_p526x296_tt6&_nc_cat=104&ccb=1-7&_nc_sid=aa7b47&_nc_ohc=YNwOsljmW2cQ7kNvwHvv9Bg&_nc_oc=AdrZvmCb9jjezCvYZ1qsC3BpcKmZDwn_GSUCbXXs2V-ItSfv-HJO0oBvTt5WSiZTk7c&_nc_zt=23&_nc_ht=scontent-atl3-2.xx&_nc_gid=85YXJ32WzjlrWKIjXKN7Wg&_nc_ss=72289&oh=00_Af4soD2sAC2MMtYktb14P5ze9_u-8X6kV2q73qoCMbcQ7w&oe=6A10AD4D | H74: 中性 | I74: 陳述 | J74: 收費/價錢 | K74: 純分享 | L74: 直接相關 | M74: null | N74: null | O74: null | P74: null | Q74: 5 | R74: 0 | S74: 0
A75: https://www.facebook.com/groups/366950274676457/permalink/1626670218704450/ | B75: Anonymous participant | C75: 46011 | E75: 手機同model 3 connect咗後，用WhatsApp錄音使唔使撳軚盤或者螢光幕任何掣？ 用返手機錄音錄唔錄到？ | H75: 中性 | I75: 疑問 | J75: 疑問/求助 | K75: 求助 | L75: 間接相關 | M75: null | N75: Tesla Model 3 | O75: null | P75: null | Q75: 1 | R75: 0 | S75: 0
A76: https://www.facebook.com/groups/366950274676457/permalink/1625272168844255/ | B76: Amuro Lee | C76: 46009 | E76: 停售燃油車不是因為電動車完美，而是因為時日無多。界線畫得愈早、愈清楚，轉型成本就愈低；拖得愈久，代價只會愈集中、愈昂貴。真正不切實際的，不是 2035，而是以為可以一路拖延，卻不用為後果付帳。 #2035 #電動車 #氣候政策 #淨零 #Column | H76: 中性 | I76: 陳述 | J76: 資訊分享 | K76: 純分享 | L76: 間接相關 | M76: null | N76: null | O76: null | P76: null | Q76: 0 | R76: 0 | S76: 0
A77: https://www.facebook.com/groups/366950274676457/permalink/1624655718905900/ | B77: Anonymous participant | C77: 46008 | E77: 數碼通12月震撼快閃⚡️優惠 立即按以下連接： Whatsapp: wa.me/85295422229 電話：95422229 12月專享： 1.現有手機及寬頻用戶開新線減$18 2.指定Plan免$18行政費 3.指定Plan送超市禮券 4.指定Plan送中國澳門數據 5.指定Plan送大陸號碼 6.指定Plan送買機禮券—————————————————————— 5G Plan A 5G 家庭Plan限時優惠 選項1： 1Sim $239 110GB 2Sim $344 120GB 3Sim $449 130GB 4Sim $554 140GB 5Sim $659 150GB 上台即享以下多項優惠： 推薦人月費回贈$600 免$18行政費 送3GB中國+澳門漫遊數據 送合約期內15GB亞太區漫遊數據 送本地數據滾存 無限分鐘本地通話 免數據任用 Zoom/ Teams 加4.5G副卡 $80全速 簽30個月合約 選項2： 1Sim $399 180GB 2Sim $504 190GB 3Sim $609 200GB 4Sim $714 210GB 5Sim $819 220gb 上台即享以下多項優惠： 推薦人月費回贈$600 送$600超市禮券，送完即止‼️ 漫遊數據組合二選一 送15GB+200分鐘中國澳門漫數據組合 或 送3GB中國澳門漫遊數據+合約期70GB亞太區漫遊數據連100分鐘中國澳門通話 送本地數據滾存 無限分鐘本地通話 免數據任用 Zoom/ Teams 加4.5G副卡 $80全速 簽24個月合約 需付$18行政費 Whatsapp: wa.me/85295422229 —————————————————————— 5G Plan B 5G限時無限數據 $239-110GB 上台即享以下多項優惠： 推薦人月費回贈$600 免$18行政費 送3GB中國+澳門漫遊數據 送合約期內15GB亞太區漫遊數據 送本地數據滾存 無限分鐘本地通話 免數據任用 Zoom/ Teams 簽30個月合約 Whatsapp: wa.me/85295422229 —————————————————————— 5G Plan C 大灣區高用量之選 $299 110GB 上台即享以下優惠： 推薦人月費回贈$600 送$600超市禮券，送完即止 ✈️送每月10GB大灣區數據 ✈️送每月200分鐘大灣區通話分鐘 送本地數據滾存 免數據任用 Zoom/ Teams 本地無限通話分鐘 簽24個月合約 以上服務需加$18行政費 Whatsapp: wa.me/85295422229 ————————————————————— 5G Plan D ✈️暢遊亞太區精選優惠✈️ $299 110GB 上台即享以下優惠： 推薦人月費回贈$600 送$600超市禮券，送完即止 ✈️送70GB亞太區數據 ✈️送100分鐘大灣區通話分鐘 ✈️送每月2GB大灣區數據 送本地數據滾存 免數據任用 Zoom/ Teams 本地無限通話分鐘 簽28個月合約 以上服務需加$18行政費 Whatsapp: wa.me/85295422229 —————————————————————— 5G Plan E 快閃優惠 ⚡️$179 50GB⚡️ 上台即享以下多項優惠： 推薦人月費回贈$600 送$200超市禮券，送完即止 送3GB中國澳門漫遊數據 送本地數據滾存 無限通話分鐘 免數據任用 Zoom/ Teams 簽30個月合約 以上服務需加$18行政費 Whatsapp: wa.me/85295422229 —————————————————————— 5G Plan F 限時優惠 $149/20GB 5G全速 上台即享以下多項優惠： 推薦人月費 回贈$600 無限通話分鐘 免數據任用 Zoom/ Teams 簽24個月合約 以上服務需加$18行政費 Whatsapp: wa.me/85295422229 ————————————————————— 5G Plan G 2025 SmarT Pass機王 早鳥優惠 G1： $149 20GB 推薦人月費回贈$600 送$1400買機禮券 ⚒送12個月爆Mon保養 無限分鐘本地通話 免數據任用 Zoom/ Teams 簽30個月合約 G2：$179 50GB 推薦人月費回贈$600 送$1700買機禮券 ⚒送12個月爆Mon保養 送3GB中國澳門數據 送本地數據滾存 無限分鐘本地通話 免數據任用 Zoom/ Teams 簽30個月合約 G3：$239 110GB 推薦人月費回贈$600 送$2200買機禮券 ⚒送12個月爆Mon保養 送3GB中國澳門數據 送合約期內15GB亞太區漫遊數據 送本地數據滾存 無限分鐘本地通話 免數據任用 Zoom/ Teams 簽30個月合約 G4：$299 110GB 推薦人月費回贈$600 送$2200買機禮券 ⚒送12個月爆Mon保養 送10GB+200分鐘中國澳門數據組合 送本地數據滾存 無限分鐘本地通話 免數據任用 Zoom/ Teams 簽30個月合約 G5：$399 180GB其後 推薦人月費回贈$600 送$3200買機禮券 ⚒送12個月爆Mon保養 送15GB+200分鐘中國澳門數據組合 送本地數據滾存 無限分鐘本地通話 免數據任用 Zoom/ Teams 簽30個月合約 以上服務需加$18行政費 Whatsapp: wa.me/85295422229 ————————————————————— 5G Plan H 最強$0機價出機Plan 選項1-$538 100GB 選項2-$738 150GB 上台即享以下多項優惠： 選項1-送手機及配件禮券$8000 （預繳$7200） 選項2-送手機及配件禮券$12000 （預繳$11000） 推薦人月費回贈$600 送12個月雙面爆Mon換新 選項1送每月3GB大灣區數據連號碼 選項2送每月5GB大灣區數據連號碼 送每月100分鐘中國澳門通話分鐘 ✈️送合約期內36GB亞太區漫遊數據 可加副卡5G$105，4.5G全速$80 無限分鐘本地通話 免數據任用 Zoom/ Teams 簽36個月合約 以上服務需加$18行政費 Whatsapp: wa.me/85295422229 —————————————————————— 4.5G Plan A $158 4.5G 全速任用 低延時，超高速，玩乜都唔使等 上台即享以下多項優惠： 推薦人月費回贈$600 20GB 其後FUP無限數據，不限速 最高可達700Mps 本地通話分鐘4000 送免費數據任用zoom/teams 現有用戶開新線再減$18/月 SmarTone plus 會藉 ：plus 簽約24個月 以上服務需加$18行政費 Whatsapp: wa.me/85295422229—————————————————————— 4.5G Plan B ✨ $120 4.5G 42Mb任用✨ 煲劇首選，任用數據 推薦人月費回贈$200 限時免$18行政費 限時送1GB中國澳門數據 14GB其後FUP無限數據 無限通話分鐘 簽約24/30個月 Whatsapp: wa.me/85295422229 —————————————————————— 4.5G Plan C ⚡️快閃優惠⚡️ $99/15GB 4.5G 42Mb 推薦人優惠回贈$200 免$18行政費 限時送1GB中國澳門數據 無限通話分鐘 送zoom/Teams免數據任用 14GB數據其後升級2Mb任用 簽24個月合約 Whatsapp: wa.me/85295422229 —————————————————————— 4.5G Plan D $79/10GB 4.5G 42Mb 推薦人優惠回贈$200 ⚡️免$18行政費 ⚡️無限通話分鐘 ⚡️10GB數據其後128kb任用 簽24個月合約 Whatsapp: wa.me/85295422229 ================================ 史無前例5G大專生優惠 Plan A $108-10GB Plan B $128-30GB （送3GB大灣區數據） Plan C $158-50GB （送$1200手機及配件禮券+4G大灣區數據） 專享以下優惠 轉台免$18行政費 送免數據任用zoom/teams 送免數據任聽Apple Music.JOOX.KKBOX 送SmarTone plus 會藉 ：plus 加$18數據智滾存 簽24個月合約 Whatsapp: wa.me/85295422229 ================================ 數碼通5G無線寬頻 家用或商用，一插即用，無需安裝 ♥️限時優惠（原價$238） $98x 30個月快閃優惠 $148x 24個月（免租機費） $128 x36個月（免租機費） $198x 12個月（免租機費） ⚡️$238x 6個月（免租機費） 另加$65租機 買機（$2160） WIFI 7 更快覆蓋更廣 $289 x6個月（已包租機） $229 x12個月（已包租機） $209 x24個月（已包租機）免一個月月費 $199 x36個月（已包租機）免一個月月費 可享 7日免費試用保證 200GB 其後 送FUP*無限數據 必須使用指定Router: 5G CPE Pro 5 5G CPE Pro 3 5G CPE 5 ZTE 5G CPE MC888 Pro ZTE 5G CPE MC888 ZTE 5G CPE MC8020 ZTE 5G CPE MC801A Linksys FGW5500 Linksys FGW3000 OPPO 5G CPE T2 OPPO 5G CPE T1a TP-Link Deco X80-5G TP-Link Deco X50-5G Whatsapp: wa.me/85295422229 —————————————————————— ⚡️SmarTone 家居光纖寬頻+家居電話⚡️ 光纖寬頻月費低至$88 家居電話$58，轉台客戶可享優惠價$48 客戶尊享： 1.指定地點免安裝費 2.24x7T 支援 3.先安裝後啟動 優惠均受有關條款及細則限制 ^ 不同時段會有不同的優惠^ #APPLE #5G家居寬頻 #消費券 #HKBN #光纖 #報價鴨 #SmarTone #CSL #5G #轉台優惠 #寬頻上網 #數碼通轉台 #數碼通上台 #iPhone15 #家庭plan #中國移動 #數碼通 #唐樓上網 #5G無線寬頻 #FamilyPlan #無限上網 ＃任用數據 #手機轉台 #5Gplan #免拉線 #村屋上網 #無限數據 #4G無限上網 #5G數據 | G77: https://scontent.fsac1-2.fna.fbcdn.net/v/t39.30808-6/597283585_721498304341860_2464794307891792752_n.jpg?stp=dst-jpg_p526x296_tt6&_nc_cat=105&ccb=1-7&_nc_sid=aa7b47&_nc_ohc=80GocI1kj0oQ7kNvwHXs_Tm&_nc_oc=AdrIeHWJrBzB0h2K2TjbIuJ_c1v-t8X-jL4NuchLNCRuzLQbnobC-hmFWTN2467kYc8&_nc_zt=23&_nc_ht=scontent.fsac1-2.fna&_nc_gid=ZuM6XEoVuvWVMxYMF1AgMQ&_nc_ss=72289&oh=00_Af4GmPDpMkcWuvwwgqN53yDTYk8CpAeuPLvwuqBVrBajdQ&oe=6A109213 | H77: 中性 | I77: 陳述 | J77: 廣告/促銷 | K77: 廣告 | L77: 無關 | M77: null | N77: null | O77: null | P77: null | Q77: 0 | R77: 0 | S77: 0
A78: https://www.facebook.com/groups/366950274676457/permalink/1624546012250204/ | B78: Amuro Lee | C78: 46008 | E78: 內文： https://www.supermoto8.com/articles/16594 | H78: 中性 | I78: 陳述 | J78: 資訊分享 | K78: 純分享 | L78: 間接相關 | M78: 歐盟 | N78: null | O78: null | P78: null | Q78: 0 | R78: 0 | S78: 0
A79: https://www.facebook.com/groups/366950274676457/permalink/1623800325658106/ | B79: Lester Lee | C79: 46007 | E79: 其實香港好多人真係好雙標，早日睇到新聞奧海城有部Tesla冒煙，但好多車group好似當冇事發生咁完全冇人講，平時國產車一有少少問題，一定會有一大班人出來踩同唱，真係睇到得啖笑☺️ | H79: 中性 | I79: 陳述 | J79: 其他 | K79: 純分享 | L79: 直接相關 | M79: 奧海城 | N79: Tesla | O79: null | P79: null | Q79: 3 | R79: 7 | S79: 0
A80: https://www.facebook.com/groups/366950274676457/permalink/1623820665656072/ | B80: Amuro Lee | C80: 46007 | E80: 電動車是否真比汽油車環保？《電動車是否真比汽油車環保？》 香港電動車愈來愈普及，但疑問始終存在：本港的發電廠仍大量燃燒天然氣與燃煤，電動車是否真的較環保？要回答這個問題，不能靠印象，而要算清楚。 先看最直接的二氧化碳排放。一輛普通汽油車在香港路況的實際油耗大約 7.5 L/100 km。每公升汽油燃燒排放約 2.3 kg CO₂，換算每公里約 170 g；再加上開採、煉油、運輸等上游排放，合共約 200 g/km。而一輛中型電動車，每 100 km 耗電約 18 kWh，以本港電網每度約 0.40–0.45 kg CO₂ 計算，每公里排放約 72–81 g，大致只有汽油車的一半。 把這差距拉長來看更清楚。如果每年行駛 10,000 km，汽油車排放約 2 t CO₂；電動車約 1–1.2 t，差距接近 1 t，相當於少飛一兩程長途機。若行車里數較多，節省亦會相應增加。 真正的關鍵在於全生命週期的計算。電動車製造階段，特別是電池生產，確實會產生較高的「碳負擔」。但這筆排放並不會永遠壓著電動車。以香港現時電網強度推算，電動車行駛約 12,000–20,000 km 後，累積排放便會低於汽油車；而在 100,000–150,000 km 的整個車生涯裏，電動車的全生命週期排放一般比汽油車低約 30–50%。隨着電網減煤，這個差距只會愈來愈大。 此外，全生命週期並不止於車輛「退役」，電池的「第二生命」正在重寫環境賬目。現時不少退役電動車電池仍有 70–80% 容量，普遍再利用於儲能系統，平衡電網負荷、支援再生能源。這意味著電池的碳排放並非一次性，而是可以攤分至更長的使用年期。至於報廢後的回收，全球技術進展迅速，如濕法冶金（hydrometallurgy）可回收鋰、鎳、鈷等金屬，效率高達 90% 左右，使下一代電池的原材料排放大幅降低。換言之，電池製造的環境負擔正隨技術進步而下降。 在香港，更切身的問題其實不是氣候，而是路邊空氣污染。香港的 NO₂ 與懸浮粒子濃度長年偏高，汽油與柴油車尾氣正是主要來源。電動車雖仍需用電，但在道路上是零尾管排放，巴士站、學校門口、行人路邊的污染可立即下降。發電廠具備集中治理，而路邊則是市民直接吸入，兩者對健康的影響不可同日而語。 當然，電動車並非毫無環境代價。鋰、鎳、鈷的開採有其足跡，車身越大、電池越大，用料越多，排放自然越高。從環保角度看，電動車是「較好的汽車」，但對多數香港人而言，公共交通往往更佳。 因此，在香港的具體情況下，電動車較汽油車環保的結論清晰：使用階段排放遠低於汽油車，行駛 12,000–20,000 km 後便開始「淨減排」，整個生命週期比汽油車低約 30–50%；加上電池再利用和高效回收，長期環境負擔會持續下降。但要讓電動車的優勢完全發揮，香港仍需讓電網徹底變綠，包括淘汰煤電、提升可再生能源比例，以及認真探索核能等穩定低碳方案。交通電動化只是上半場，下半場是能源系統的根本改革。 #電動車 #減碳 #空氣污染 #環保政策 #香港 #能源轉型 #Column | H80: 中性 | I80: 陳述 | J80: 資訊分享 | K80: 求助 | L80: 間接相關 | M80: 香港 | N80: null | O80: null | P80: null | Q80: 0 | R80: 0 | S80: 0
A81: https://www.facebook.com/groups/366950274676457/permalink/1620341066004032/ | B81: Lo Yuk Fai | C81: 46002 | E81: Jove 同三號連埋咗？ | G81: https://scontent-lga3-3.xx.fbcdn.net/v/t39.30808-6/597360941_3417098901774931_498128647131360027_n.jpg?stp=dst-jpegr_p526x296_tt6&_nc_cat=108&ccb=1-7&_nc_sid=aa7b47&_nc_ohc=m8Wqx8p9bDgQ7kNvwHSfKD3&_nc_oc=AdqoYyK-c2uVj_2TxlnnOSoayYY1nwXtEIykimNn6q7MpTkd60mFjkEZuFD32gNLOkA&_nc_zt=23&se=-1&_nc_ht=scontent-lga3-3.xx&_nc_gid=IB2QE-pKsShav9mlVemLsw&_nc_ss=72289&oh=00_Af6f_57zVtYGyoKOFsmydsPfTWrK9x0c_c91gDqcc3dCvw&oe=6A10A0E8 | H81: 中性 | I81: 疑問 | J81: 疑問/求助 | K81: 求助 | L81: 直接相關 | M81: null | N81: null | O81: Jove | P81: null | Q81: 6 | R81: 0 | S81: 0
A82: https://www.facebook.com/groups/366950274676457/permalink/1617407059630766/ | B82: Anonymous participant | C82: 45998 | E82: 想問吓各位師兄 1. 揸電動車有冇咩app係必須？ 2. 有啲咩Tesla 設定應該要整？ 3.￼會唔會訂閱Tesla嘅網絡？ | H82: 中性 | I82: 疑問 | J82: 疑問/求助 | K82: 求助 | L82: 直接相關 | M82: null | N82: Tesla | O82: null | P82: null | Q82: 1 | R82: 2 | S82: 0
A83: https://www.facebook.com/groups/366950274676457/permalink/1615930433111762/ | B83: CT IP Joe | C83: 45996 | E83: AION UT終於發佈 | H83: 中性 | I83: 陳述 | J83: 資訊分享 | K83: 純分享 | L83: 直接相關 | M83: null | N83: AION UT | O83: null | P83: null | Q83: 1 | R83: 1 | S83: 0
A84: https://www.facebook.com/groups/366950274676457/permalink/1613665543338251/ | B84: Roy Ng | C84: 45993 | E84: 八鄉汽車美容 如有興趣或其他汽車美容 地址: 八鄉消防局附近橫台山 查詢 ☎️ WhatsApp 51992395 賢☎️ https://m.facebook.com/八鄉汽車美容-洗車-打蠟-蒸籠-140889456736875 日本9H 白金塗層復合鍍膜 1年期 深層研磨去漬拋光 除花痕去蜘蛛紋 凡惠昌顧9H塗層鍍鏌加送 納米空氣觸媒消毒蒸籠 冷氣殺菌消毒服務 ⛔️半年保養⛔️ 現優惠價 2️⃣5️⃣0️⃣0️⃣ （全車深層清潔消毒套餐 ） 人手泡抹洗車 推泥膠 去污 ➕吸塵 洗鈴 清潔玻璃 ➕ 霧化藥水消毒 除甲醛 除味 防霉 ➕ 藥水泡泡深層清潔內籠 ➕納米空氣觸媒殺菌消毒除味 ➕冷氣殺菌消毒服務 現優惠價 9️⃣5️⃣0️⃣ （ 跣水3M三重水晶蠟消毒蒸籠套餐 ） 人手泡抹洗車 推泥膠 去污 ➕ 吸塵 清潔玻璃 洗鈴 ➕ 冷氣霧化消毒 除甲醛 除味 防霉 ➕三層3M水晶蠟（深度去漬去花拋光） ➕藥水泡泡深層清潔內籠 ➕納米空氣觸媒殺菌消毒除味 ➕冷氣殺菌消毒服務 現優惠價 1️⃣8️⃣8️⃣8️⃣ 以下個別項目因應車輛大小 有所調整 以下是各式單項服務及價錢 A :腊水洗車 推泥膠 吸塵 洗鈴 清潔玻璃 1️⃣2️⃣8️⃣起 B：納米空氣觸媒霧化消毒 內籠連冷氣 除菌 除味防霉 4️⃣2️⃣0️⃣起 C：藥水泡泡深層清潔蒸籠 包吸塵 （座位 座位底 尾箱 冷氣口 地毯） 4️⃣8️⃣0️⃣起 D: 一層3M打蠟（拋光 輕度去花去漬） 洗車 吸塵 推泥膠 洗鈴及清潔玻璃 5️⃣0️⃣0️⃣起 E: 跣水3M三重水晶蠟 （深度去花去漬拋光水晶臘） 洗車 吸塵 推泥膠 洗鈴及清潔玻璃 9️⃣8️⃣8️⃣起 F: 玻璃鍍晶 線水 去油面 污漬 5️⃣0️⃣0️⃣起 G: 清洗引擎箱 3️⃣0️⃣0️⃣ H: 頭燈翻新（一對） 6️⃣0️⃣0️⃣ #洗車 #打臘 #汽車美容 #蒸籠 #除味消毒 #八鄉汽車美容 #去漬 #9H鍍鏌 #內籠清潔 #打腊 #霧化消毒 #拋光 #去花痕 #元朗 #保護層 #撥水 | H84: 中性 | I84: 陳述 | J84: 廣告/促銷 | K84: 廣告 | L84: 無關 | M84: 八鄉, 橫台山, 元朗 | N84: null | O84: null | P84: null | Q84: 0 | R84: 0 | S84: 0
A85: https://www.facebook.com/groups/366950274676457/permalink/1612959376742201/ | B85: Yeung Ben | C85: 45992 | E85: 請問觀塘充電有乜好介紹？ | H85: 中性 | I85: 疑問 | J85: 疑問/求助 | K85: 求助 | L85: 直接相關 | M85: 觀塘 | N85: null | O85: null | P85: null | Q85: 1 | R85: 1 | S85: 0
A86: https://www.facebook.com/groups/366950274676457/permalink/1612181996819939/ | B86: 電車充電槍代購 | C86: 45991 | E86: 電動車車主 在安裝電動車充電器時，先要留意香港「機電工程署EMSD」的要求，如下： JB Sir 香港新能源學院 HK EV Academy 有興趣加入我Facebook 我一一分析電動車及電動充電的各項安全要求 | G86: https://scontent-lax7-1.xx.fbcdn.net/v/t39.30808-6/592491219_122247077396137441_8572162257882529931_n.jpg?stp=dst-jpg_p180x540_tt6&_nc_cat=105&ccb=1-7&_nc_sid=aa7b47&_nc_ohc=gkBzpudY5iEQ7kNvwFM1m1u&_nc_oc=Adoeb1EEp9aE32XjKM-_WFMrDu4s60lgSiRwEvF9OuX8tPeFyP1ar8iOWDRR8fzwK5o&_nc_zt=23&_nc_ht=scontent-lax7-1.xx&_nc_gid=M1VpYM8fqmEjlMkWIaLv4w&_nc_ss=72289&oh=00_Af6zteOn7yk9pZBY7hFgGjEateONuvQ-YeQ4iD-x4J581w&oe=6A10C6A7 | H86: 中性 | I86: 陳述 | J86: 安裝/硬件/技術 | K86: 純分享 | L86: 直接相關 | M86: null | N86: null | O86: null | P86: null | Q86: 8 | R86: 0 | S86: 1
A87: https://www.facebook.com/groups/366950274676457/permalink/1606726287365510/ | B87: 電車充電槍代購 | C87: 45984 | E87: 香港新能源學院 HK EV Academy 選購新能源充電器須合乎以下要求： CE 「Conformité Européenne」 「符合歐洲指令規範」 電子/電器產品：充電器、電源供應器：有CE 標誌，才能在歐洲境內出售。 IP 「Ingress Protection」 國際公認的防護等級認證 IP 等級由兩個數字所組成 第一個數防塵等級（等級為 0 至 6） 第二個數防水等級（等級為 0 至 8） 數字愈大表示其防護等級愈佳 IP65/68（e.g) 「6」是防塵等級； 後面的防水等級分別有「5」和「8」， IP68 的意思是該產品能夠在 1 米水深下使用。因此就出現 IP65/68 寫在一起的情況。 ￼每日知多啲 查詢JB Sir whatsapp 95598310 | H87: 中性 | I87: 陳述 | J87: 資訊分享 | K87: 廣告 | L87: 直接相關 | M87: null | N87: null | O87: null | P87: null | Q87: 0 | R87: 0 | S87: 0
A88: https://www.facebook.com/groups/366950274676457/permalink/1594645835240222/ | B88: 陳傲輝 | C88: 45969 | E88: 過夜充電的選擇 | H88: 中性 | I88: 陳述 | J88: 資訊分享 | K88: 純分享 | L88: 直接相關 | M88: null | N88: null | O88: null | P88: null | Q88: 1 | R88: 0 | S88: 0
A89: https://www.facebook.com/groups/366950274676457/permalink/1593579378680201/ | B89: Lei Tat | C89: 45968 | E89: 安盛AXA港澳車北上熱門方案 TESLA 特斯拉 MODEL 3 Y X （首次登記三年或以上） ✅澳車北上 ✅港車北上 ✅橫琴單牌車 ✅個人兩地牌 交強險+商業險方案，低至¥1448/¥1674起，還包含高速/港珠澳大橋內地段拖車 粵港澳出行北上牌證車保（交強和商業險）， 請添加微信號：CnHkMo001 名稱：粵港澳-1@利達（依序回覆） #澳車北上保險 #港車北上保險 #兩地牌保險 #橫琴單牌保險 | H89: 正面 | I89: 期待 | J89: 廣告/促銷 | K89: 廣告 | L89: 間接相關 | M89: null | N89: Tesla Model 3, Tesla Model Y, Tesla Model X | O89: null | P89: null | Q89: 0 | R89: 0 | S89: 0
A90: https://www.facebook.com/groups/366950274676457/permalink/1592215025483303/ | B90: 昌泰-配車匙服務 | C90: 45966 | E90: 安裝汽車充電介紹 | H90: 中性 | I90: 陳述 | J90: 安裝/硬件/技術 | K90: 純分享 | L90: 直接相關 | M90: null | N90: null | O90: null | P90: null | Q90: 1 | R90: 0 | S90: 0
A91: https://www.facebook.com/groups/366950274676457/permalink/1589734102398062/ | B91: Honnmono | C91: 45963 | E91: 全球轉插供應商 公認優質 信心之選 Honnmono獨家 App 功能，內置eSIM 港車北上 快充轉插 穩定性安全性兼容性 香港行貨2年保養 香港數碼港公司 南方電網孵化企業 hkt 1010 租賃合作 香港百老￼滙 服務各大車廠 及 電網公司 •專業售後服務容服團隊,，隨時解答您的疑問 •全面兼容，適用所有 CCS2 電動車及充電椿 | H91: 正面 | I91: 期待 | J91: 廣告/促銷 | K91: 廣告 | L91: 直接相關 | M91: 香港數碼港 | N91: null | O91: null | P91: 快充, CCS2 | Q91: 0 | R91: 0 | S91: 0
A92: https://www.facebook.com/groups/366950274676457/permalink/1585657712805701/ | B92: 陳傲輝 | C92: 45958 | E92: 充電流程 | H92: 中性 | I92: 陳述 | J92: 資訊分享 | K92: 純分享 | L92: 直接相關 | M92: null | N92: null | O92: null | P92: null | Q92: 0 | R92: 0 | S92: 0
A93: https://www.facebook.com/groups/366950274676457/permalink/1584537532917719/ | B93: Amuro Lee | C93: 45957 | E93: 全固態電池終於實用化？Nissan 今年起開始試生產全固態電池，並夥拍美國 LiCAP Technologies 推動先進乾式製程技術，成功將充電時間縮短至 30 分鐘，續航力提升至鋰離子電池兩倍。搭載新電池的電動車原型，目標 2028 財政年度推出 👇詳細看留言連結👇 | H93: 正面 | I93: 期待 | J93: 安裝/硬件/技術 | K93: 求助 | L93: 間接相關 | M93: null | N93: null | O93: Nissan | P93: null | Q93: 0 | R93: 0 | S93: 0
A94: https://www.facebook.com/groups/366950274676457/permalink/1583587149679424/ | B94: Honnmono | C94: 45956 | E94: 全球轉插供應商 公認優質 信心之選 Honnmono獨家 App 功能，內置eSIM 港車北上 快充轉插 穩定性安全性兼容性 香港行貨2年保養 香港數碼港公司 南方電網孵化企業 hkt 1010 租賃合作 香港百老￼滙 服務各大車廠 及 電網公司 •專業售後服務容服團隊,，隨時解答您的疑問 •全面兼容，適用所有 CCS2 電動車及充電椿 | H94: 正面 | I94: 期待 | J94: 廣告/促銷 | K94: 廣告 | L94: 直接相關 | M94: 數碼港 | N94: null | O94: null | P94: 快充, CCS2 | Q94: 1 | R94: 0 | S94: 0
A95: https://www.facebook.com/groups/366950274676457/permalink/1580939323277540/ | B95: Honnmono | C95: 45953 | E95: 全球轉插供應商 公認優質 信心之選 Honnmono獨家 App 功能，內置eSIM 港車北上 快充轉插 穩定性安全性兼容性 香港行貨2年保養 香港數碼港公司 南方電網孵化企業 hkt 1010 租賃合作 香港百老￼滙 服務各大車廠 及 電網公司 •專業售後服務容服團隊,，隨時解答您的疑問 •全面兼容，適用所有 CCS2 電動車及充電椿 | H95: 正面 | I95: 滿意 | J95: 廣告/促銷 | K95: 廣告 | L95: 直接相關 | M95: 數碼港, 百老匯 | N95: null | O95: null | P95: 快充, CCS2 | Q95: 0 | R95: 0 | S95: 0
A96: https://www.facebook.com/groups/366950274676457/permalink/1577285266976279/ | B96: Honnmono | C96: 45949 | E96: 全球轉插供應商 公認優質 信心之選 Honnmono獨家 App 功能，內置eSIM 港車北上 快充轉插 穩定性安全性兼容性 香港行貨2年保養 香港數碼港公司 南方電網孵化企業 hkt 1010 租賃合作 香港百老￼滙 服務各大車廠 及 電網公司 •專業售後服務容服團隊,，隨時解答您的疑問 •全面兼容，適用所有 CCS2 電動車及充電椿 | H96: 正面 | I96: 期待 | J96: 安裝/硬件/技術 | K96: 廣告 | L96: 直接相關 | M96: 數碼港 | N96: null | O96: null | P96: CCS2, 快充 | Q96: 0 | R96: 0 | S96: 0
A97: https://www.facebook.com/groups/366950274676457/permalink/1576330203738452/ | B97: Honnmono | C97: 45948 | E97: 全球轉插供應商 公認優質 信心之選 Honnmono獨家 App 功能，內置eSIM 港車北上 快充轉插 穩定性安全性兼容性 香港行貨2年保養 香港數碼港公司 南方電網孵化企業 hkt 1010 租賃合作 香港百老￼滙 服務各大車廠 及 電網公司 •專業售後服務容服團隊,，隨時解答您的疑問 •全面兼容，適用所有 CCS2 電動車及充電椿 | H97: 正面 | I97: 期待 | J97: 廣告/促銷 | K97: 廣告 | L97: 直接相關 | M97: 數碼港, 百老滙 | N97: null | O97: null | P97: 快充, CCS2 | Q97: 0 | R97: 0 | S97: 0
A98: https://www.facebook.com/groups/366950274676457/permalink/1571411044230368/ | B98: Honnmono | C98: 45942 | E98: 全球轉插供應商 公認優質 信心之選 Honnmono獨家 App 功能，內置eSIM 港車北上 快充轉插 穩定性安全性兼容性 香港行貨2年保養 香港數碼港公司 南方電網孵化企業 hkt 1010 租賃合作 香港百老￼滙 服務各大車廠 及 電網公司 •專業售後服務容服團隊,，隨時解答您的疑問 •全面兼容，適用所有 CCS2 電動車及充電椿 | H98: 正面 | I98: 期待 | J98: 廣告/促銷 | K98: 廣告 | L98: 直接相關 | M98: 數碼港, 百老匯 | N98: null | O98: null | P98: 快充, CCS2 | Q98: 0 | R98: 0 | S98: 0
... A114: https://www.facebook.com/groups/366950274676457/permalink/1540177937353679/ | B114: Honnmono | C114: 45906 | E114: 全球轉插供應商 公認優質 信心之選 Honnmono獨家 App 功能，內置eSIM 港車北上 快充轉插 穩定性安全性兼容性 香港行貨2年保養 香港數碼港公司 南方電網孵化企業 hkt 1010 租賃合作 香港百老￼滙 服務各大車廠 及 電網公司 •專業售後服務容服團隊,，隨時解答您的疑問 •全面兼容，適用所有 CCS2 電動車及充電椿 | H114: 正面 | I114: 期待 | J114: 廣告/促銷 | K114: 廣告 | L114: 直接相關 | M114: 數碼港 | N114: null | O114: null | P114: CCS2, 快充 | Q114: 0 | R114: 0 | S114: 0
A115: https://www.facebook.com/groups/366950274676457/permalink/1539846120720194/ | B115: Lo Yuk Fai | C115: 45905 | E115: 冇咗夜早特價時段，貴少少但唔駛排隊 | G115: https://scontent-atl3-1.xx.fbcdn.net/v/t39.30808-6/544902739_3307446789406810_6653327958861671188_n.jpg?stp=dst-jpg_p180x540_tt6&_nc_cat=103&ccb=1-7&_nc_sid=aa7b47&_nc_ohc=CVuIQjDNv9YQ7kNvwGobmBQ&_nc_oc=AdpTbRE40CYBRdB0yGr4KF0FKLIW80gRzPQVa_c3VlbJdBSyFopktQJBUQeAKvZnf1A&_nc_zt=23&_nc_ht=scontent-atl3-1.xx&_nc_gid=3eJGpv_S1fdRXGywEOoxMw&_nc_ss=7c289&oh=00_Af4740oJJLgqEVVEOeH-96p07sdG7VNHV6uQh0tXuilaKQ&oe=6A10C38C | H115: 中性 | I115: 陳述 | J115: 收費/價錢 | K115: 純分享 | L115: 直接相關 | M115: null | N115: null | O115: null | P115: null | Q115: 14 | R115: 14 | S115: 0
...

Sheet 香港電動車資訊及充電交流谷⚡️2
A1: url | B1: user_name | C1: title | D1: text | E1: time | F1: video_url_one | G1: photo_url_one | H1: emotion_basic | I1: emotion_detailed | J1: theme | K1: info_value | L1: ev_relevance | M1: Location_Mentioned | N1: EV_Model_Mentioned | O1: Competitor_Brand | P1: Charging_Type | Q1: likesCount | R1: commentsCount | S1: sharesCount
A2: https://www.facebook.com/groups/hkevcharging/permalink/3838738269754532/ | B2: Man Leung Tang | D2: 想問下係街超充,見到之槍180kw,但用時只食40kw ,係我車有問題定支槍唔得?定2樣都有影響? byd atto2 新手求教 | E2: 46159 | H2: 中性 | I2: 疑問 | J2: 充電速度 | K2: 求助 | L2: 直接相關 | M2: null | N2: BYD Atto 2 | O2: null | P2: 超充, 180kW | Q2: 6 | R2: 33 | S2: 0
A3: https://www.facebook.com/groups/hkevcharging/permalink/3840167806278245/ | B3: Simon Chan | D3: 請教下淘寶果D充電椿有邊隻介紹？ | E3: 46159 | H3: 中性 | I3: 疑問 | J3: 安裝/硬件/技術 | K3: 求助 | L3: 直接相關 | M3: null | N3: null | O3: null | P3: null | Q3: 0 | R3: 0 | S3: 0
A4: https://www.facebook.com/groups/hkevcharging/permalink/3836719756623050/ | B4: Mourinhang Chan | D4: 喺深水埗the clampton充電 超級搵笨 扣咗我錢又叉唔到電 同佢哋講佢話部機轉藍燈 係正常 係我個架車setting同條線有問題 叫佢refund話冇得回 係咪痴L線㗎？？？？ | E4: 46156 | H4: 負面 | I4: 生氣 | J4: 顧客服務/投訴 | K4: 純分享 | L4: 直接相關 | M4: 深水埗the clampton | N4: null | O4: the clampton | P4: null | Q4: 15 | R4: 7 | S4: 0
A5: https://www.facebook.com/groups/hkevcharging/permalink/3834822616812764/ | B5: RelaxingPhoenix4030 | D5: 新收車無送中充線，想問下有無推介？ 有睇過下淘寶，我見淘寶頭牌子嗰d個價錢同喺香港買好似唔爭得遠，想問下有無推介？ thx thx!!!! | E5: 46153 | H5: 中性 | I5: 疑問 | J5: 疑問/求助 | K5: 求助 | L5: 直接相關 | M5: null | N5: null | O5: null | P5: 中充 | Q5: 4 | R5: 11 | S5: 0
A6: https://www.facebook.com/groups/hkevcharging/permalink/3834781553483537/ | B6: Daniel Tsang | D6: 中充$25/15分鐘，會唔會好貴？ | E6: 46153 | G6: https://scontent-lga3-1.xx.fbcdn.net/v/t39.30808-6/694768414_10163781285722626_1755478839361862595_n.jpg?stp=dst-jpg_s720x720_tt6&_nc_cat=111&ccb=1-7&_nc_sid=aa7b47&_nc_ohc=E5cnWTQTWwAQ7kNvwFBcTeF&_nc_oc=AdqoRSCfBdmdbQdLupiVBo_5FUjAFlyZuVpUI-7aNcPsJrR-_sRlNHK1nquLwkv7LCI&_nc_zt=23&_nc_ht=scontent-lga3-1.xx&_nc_gid=3j0lBml65shZDASSRGFMrQ&_nc_ss=72289&oh=00_Af5q_bNSCtfkS-ZIESQMW4GFG5-ElujBF6E6YmWKc5D0yg&oe=6A109928 | H6: 中性 | I6: 疑問 | J6: 收費/價錢 | K6: 求助 | L6: 直接相關 | M6: null | N6: null | O6: null | P6: 中充 | Q6: 26 | R6: 48 | S6: 0
A7: https://www.facebook.com/groups/hkevcharging/permalink/3831851643776528/ | B7: Simon Lee | D7: 大角咀 One Bedford Place 停車場，終於有TESLA免費EV充電 | E7: 46150 | G7: https://scontent-lga3-3.xx.fbcdn.net/v/t39.30808-6/690754592_122181778604912952_4892225293964943803_n.jpg?stp=dst-jpg_p180x540_tt6&_nc_cat=102&ccb=1-7&_nc_sid=aa7b47&_nc_ohc=A-DemmPUU6QQ7kNvwGQzFhx&_nc_oc=AdpEwWgiIS-nuDKq0gZwaP15n9RiqLGH9ud4QzejSXvPtYzBOtKF1VibHGAuRqQAwM4&_nc_zt=23&_nc_ht=scontent-lga3-3.xx&_nc_gid=11Ag9PaxbTjF5sjYlX57lQ&_nc_ss=72289&oh=00_Af4cIiWzNQGCVloUYTfinQeG_yEWS7LK5K6EHN-FiZxPZg&oe=6A109913 | H7: 正面 | I7: 開心 | J7: 充電站設施/位置 | K7: 純分享 | L7: 直接相關 | M7: 大角咀 One Bedford Place | N7: null | O7: Tesla | P7: null | Q7: 2 | R7: 0 | S7: 0
A8: https://www.facebook.com/groups/hkevcharging/permalink/3830326100595749/ | B8: Wai Kin Lam | D8: 想問下各位師兄，最近入咗部電動車，本身租緊村屋泊樓下，係咪買條13A充電線比較好？買原廠定淘寶就得？ | E8: 46149 | H8: 中性 | I8: 疑問 | J8: 安裝/硬件/技術 | K8: 求助 | L8: 直接相關 | M8: null | N8: null | O8: null | P8: 13A | Q8: 8 | R8: 32 | S8: 0
A9: https://www.facebook.com/groups/hkevcharging/permalink/3830612397233786/ | B9: Man Leung Tang | D9: 元朗不用泊車錢充電站,請師兄們比意見 想問元朗充電邊度平同唔洗停車場錢? | E9: 46149 | H9: 中性 | I9: 疑問 | J9: 收費/價錢 | K9: 求助 | L9: 直接相關 | M9: 元朗 | N9: null | O9: null | P9: null | Q9: 0 | R9: 2 | S9: 0
A10: https://www.facebook.com/groups/hkevcharging/permalink/3826833960944963/ | B10: ExcellentCapybara4767 | D10: 請問大家屋苑停車場裝充電係裝type A 定Type B?Thanks | E10: 46146 | H10: 中性 | I10: 疑問 | J10: 安裝/硬件/技術 | K10: 求助 | L10: 直接相關 | M10: null | N10: null | O10: null | P10: null | Q10: 1 | R10: 9 | S10: 0
A11: https://www.facebook.com/groups/hkevcharging/permalink/3819746774987015/ | B11: Lisa Chun | D11: 各位師兄姐，請問如果係租屋住（可能住兩年就搬），裝咩充電樁性價比較高？ | E11: 46139 | H11: 中性 | I11: 疑問 | J11: 安裝/硬件/技術 | K11: 求助 | L11: 直接相關 | M11: null | N11: null | O11: null | P11: null | Q11: 5 | R11: 14 | S11: 0
A12: https://www.facebook.com/groups/hkevcharging/permalink/3817298091898550/ | B12: 6969everyday | D12: 請問屋苑掛充電錶有冇邊間好？同埋有咩野要注意？ | E12: 46134 | H12: 中性 | I12: 疑問 | J12: 安裝/硬件/技術 | K12: 求助 | L12: 直接相關 | M12: null | N12: null | O12: null | P12: null | Q12: 1 | R12: 3 | S12: 0
A13: https://www.facebook.com/groups/hkevcharging/permalink/3811755882452771/ | B13: Sheldon Cso | D13: 準備搬村屋，想裝掛牆充電，屋企單相電，而我自己本身有Tesla 充電樁大家有冇介紹啊或者13a三腳插，有冇邊款安全啲？ | E13: 46128 | H13: 中性 | I13: 疑問 | J13: 安裝/硬件/技術 | K13: 求助 | L13: 直接相關 | M13: null | N13: null | O13: null | P13: 13A | Q13: 1 | R13: 9 | S13: 0
A14: https://www.facebook.com/groups/hkevcharging/permalink/3809003552728004/ | B14: Yat Him Li | D14: 想問下大家，第一次換電車，村屋裝充電器，有冇公司/師傅推介？Maxus mifa7，唔該 | E14: 46125 | H14: 中性 | I14: 疑問 | J14: 安裝/硬件/技術 | K14: 求助 | L14: 直接相關 | M14: null | N14: Maxus Mifa 7 | O14: null | P14: null | Q14: 2 | R14: 5 | S14: 0
A15: https://www.facebook.com/groups/hkevcharging/permalink/3809407896020903/ | B15: Kelvin Kwan | D15: 各位師兄師姐，想請教大家，小弟剛換電車，剛申請港車北上，想問問國內歐標轉國標邊款快充安全又穩陣，可否給我品牌意見 | E15: 46125 | H15: 中性 | I15: 疑問 | J15: 疑問/求助 | K15: 求助 | L15: 直接相關 | M15: null | N15: null | O15: null | P15: 快充 | Q15: 2 | R15: 17 | S15: 0
A16: https://www.facebook.com/groups/hkevcharging/permalink/3807290412899318/ | B16: BIG ECHO 大迴音國際有限公司 | D16: 岩岩去左偉業街間充電加洗車，兩樣都平又唔洗充值次次八達通清。洗車100，充電百幾kw $2.5 | E16: 46123 | H16: 正面 | I16: 滿意 | J16: 收費/價錢 | K16: 純分享 | L16: 直接相關 | M16: 偉業街 | N16: null | O16: null | P16: 快充 | Q16: 61 | R16: 23 | S16: 4
A17: https://www.facebook.com/groups/hkevcharging/permalink/3806245859670440/ | B17: Ka Ka Chan | D17: Cornerstone 6折充電私放 有意請PM | E17: 46121 | H17: 正面 | I17: 期待 | J17: 廣告/促銷 | K17: 廣告 | L17: 間接相關 | M17: null | N17: null | O17: Cornerstone | P17: null | Q17: 3 | R17: 2 | S17: 0
A18: https://www.facebook.com/groups/hkevcharging/permalink/3801129613515398/ | B18: Kilowatt 充電入油地圖 - 香港駕車資訊平台 | D18: **【一換一結束】2026年3月電動車首次登記9,000輛創新高！BYD比亞迪超1,700輛‼️** 一換一結束最後機會下，3月一共登記咗超過 9,000部 電動私家車，創歷史單月新高！BYD比亞迪超1,700輛；其後是Tesla超1,650輛。最受歡迎電動車是BYD ATTO 2 有近1,500輛；其後是Tesla Model Y 1,000輛 。 電動車銷量排名頭五位： 1️⃣ BYD ATTO 2 - 1497 輛 2️⃣ Tesla Model Y - 989 輛 3️⃣ DFSK Nammi VIGO - 844輛 4️⃣ ZEEKR 7X – 732輛 5️⃣ Tesla Model 3 – 686輛 *以運輸署登記數字為準 想知邊款電動車最好賣？ 即下載 Kilowatt App 睇詳細數據 [kilowatt.hk/download](http://kilowatt.hk/download) | E18: 46115 | H18: 中性 | I18: 陳述 | J18: 資訊分享 | K18: 廣告 | L18: 直接相關 | M18: null | N18: BYD ATTO 2, Tesla Model Y, DFSK Nammi VIGO, ZEEKR 7X, Tesla Model 3 | O18: Kilowatt | P18: null | Q18: 3 | R18: 0 | S18: 0
A19: https://www.facebook.com/groups/hkevcharging/permalink/3794213707540322/ | B19: Leon Lee | D19: 想請教一下大家 又kWh / kw充電點計?入電入到幾多? 電池容量83kwh , 800v平台, 功率80kw 謝謝 | E19: 46108 | H19: 中性 | I19: 疑問 | J19: 疑問/求助 | K19: 求助 | L19: 直接相關 | M19: null | N19: null | O19: null | P19: 80kW, 800V | Q19: 14 | R19: 36 | S19: 0
A20: https://www.facebook.com/groups/hkevcharging/permalink/3792852127676480/ | B20: Hongkonger852 | D20: 康城商場，麻煩車主見到請盡快移走！ | E20: 46107 | G20: https://scontent-iad3-2.xx.fbcdn.net/v/t39.30808-6/658404380_1612343260097066_3105031426292490265_n.jpg?stp=dst-jpg_p526x296_tt6&_nc_cat=111&ccb=1-7&_nc_sid=aa7b47&_nc_ohc=-38ifBI-dhQQ7kNvwFpeom0&_nc_oc=AdoB4Z8GRHGBmBWkzgywLHShvQH9Xa73DgsPiThJ2xpoN2CMd5bnWcus9AJA0Ux21FM&_nc_zt=23&_nc_ht=scontent-iad3-2.xx&_nc_gid=wHWi3smkAzLjRG6GFjJwoA&_nc_ss=7c289&oh=00_Af6w2nOfOVyr_jM-XwpraaiE1wUL-qZbvvN8I6gkFZLTvw&oe=6A10B387 | H20: 負面 | I20: 生氣 | J20: 排隊/打尖/霸位 | K20: 純分享 | L20: 直接相關 | M20: 康城商場 | N20: null | O20: null | P20: null | Q20: 34 | R20: 41 | S20: 0
A21: https://www.facebook.com/groups/hkevcharging/permalink/3792170717744621/ | B21: Yang Sunny | D21: 各位師兄，有無平靚正維修特斯拉溫度控製糸統（無冷氣，加左雪種又漏曬)的廠房介紹？原廠太貴了 | E21: 46106 | H21: 中性 | I21: 疑問 | J21: 疑問/求助 | K21: 求助 | L21: 無關 | M21: null | N21: Tesla | O21: null | P21: null | Q21: 0 | R21: 2 | S21: 0
A22: https://www.facebook.com/groups/hkevcharging/permalink/3789772817984411/ | B22: Sophia Wong | E22: 46103 | Q22: 1 | R22: 0 | S22: 0
A23: https://www.facebook.com/groups/hkevcharging/permalink/3787336534894706/ | B23: MK Hei | D23: 改版SU7 22萬人仔，可以返珠海買返架玩吓￼ | E23: 46100 | G23: https://scontent-mia3-1.xx.fbcdn.net/v/t39.30808-6/654296295_10164069748667748_6641903258806315416_n.jpg?stp=dst-jpg_s565x565_tt6&_nc_cat=106&ccb=1-7&_nc_sid=aa7b47&_nc_ohc=mb8Lvt-pXLEQ7kNvwFZ4xRr&_nc_oc=AdqiT2s8zOF0JEODJ-9tpT0rEpl6Mk7kiKUU49L3YQ5rWHk2WRkffUB16-AVQpbFFeU&_nc_zt=23&_nc_ht=scontent-mia3-1.xx&_nc_gid=BrW9EJNMrZz3Uq5qCE4NxQ&_nc_ss=72289&oh=00_Af799xhfzMGi4lK0vUCmSB2INryqdUiBzGN__EFyqpUdAQ&oe=6A10C604 | H23: 中性 | I23: 陳述 | J23: 資訊分享 | K23: 有行動意向 | L23: 直接相關 | M23: 珠海 | N23: SU7 | O23: null | P23: null | Q23: 63 | R23: 29 | S23: 0
A24: https://www.facebook.com/groups/hkevcharging/permalink/3782775732017453/ | B24: Chan Po Man | D24: #ev 全新平治VLE 系列（廣東話翻譯介紹）Mercedes-Benz VLE Electric MPV 全面取代EQV系列 內部配置全面升級｜續航力達700公里｜#vle #eqv #benz https://youtu.be/SfIOvQe_O38 | E24: 46095 | G24: https://scontent-iad3-1.xx.fbcdn.net/v/t39.30808-6/651678700_1613101989998604_2508606350972551329_n.jpg?stp=dst-jpg_s960x960_tt6&_nc_cat=110&ccb=1-7&_nc_sid=aa7b47&_nc_ohc=ObQLW5ojfpQQ7kNvwFJA_-Z&_nc_oc=Ado2wkBYasFwxqJXgoKNy3AbL7sKtQ4qFbkt-1hvzImKRz6e_KDnExCOAQiCl8TdC-k&_nc_zt=23&_nc_ht=scontent-iad3-1.xx&_nc_gid=7aHhyHut_VSUKuW2xgasVg&_nc_ss=72289&oh=00_Af5F5xYJa_0Xud4akWbedGFXA024BR1ghXfD5ntp4PsBXQ&oe=6A10AFBF | H24: 正面 | I24: 期待 | J24: 廣告/促銷 | K24: 廣告 | L24: 間接相關 | M24: null | N24: Mercedes-Benz VLE, Mercedes-Benz EQV | O24: null | P24: null | Q24: 0 | R24: 0 | S24: 0
A25: https://www.facebook.com/groups/hkevcharging/permalink/3781772132117813/ | B25: Wai So | D25: 新用比亚比迪海獅7普通版，一星期用三天車左右，家裏装了獨立13A單相電掣，問問各師兄師姊有甚麼13A充電線好介紹？ | E25: 46094 | H25: 中性 | I25: 疑問 | J25: 疑問/求助 | K25: 求助 | L25: 直接相關 | M25: null | N25: 比亞迪海獅7 | O25: null | P25: 13A | Q25: 2 | R25: 17 | S25: 0
A26: https://www.facebook.com/groups/hkevcharging/permalink/3780866132208413/ | B26: Rebecca Lam | D26: 家用汽車叉电机，請問大家有無推介? | E26: 46093 | H26: 中性 | I26: 疑問 | J26: 疑問/求助 | K26: 求助 | L26: 直接相關 | M26: null | N26: null | O26: null | P26: null | Q26: 0 | R26: 3 | S26: 0
A27: https://www.facebook.com/groups/hkevcharging/permalink/3775221122772914/ | B27: MK Hei | D27: ￼一月暫時Zeekr 7X排第一，嚟緊睇吓三月一換一deadline邊個排第一先 | E27: 46086 | G27: https://scontent-ord5-2.xx.fbcdn.net/v/t39.30808-6/646136323_10163994273737748_3263070594301087378_n.jpg?stp=cp6_dst-jpg_p526x296_tt6&_nc_cat=104&ccb=1-7&_nc_sid=aa7b47&_nc_ohc=lecjNyDk_SYQ7kNvwHrXws2&_nc_oc=Adqv18fCv9Au_BIz1GNGHQ4qmItsgzJnrVIBe3veS5HIKmk2B2fRiiiL5vnXTannMoI&_nc_zt=23&_nc_ht=scontent-ord5-2.xx&_nc_gid=inwYP-ZINVkb3BPfq3NmOg&_nc_ss=7d289&oh=00_Af5Jhpi-w09z-qvEJVIN62R74427PzJoPs4AYlfsgCgTiA&oe=6A109C58 | H27: 中性 | I27: 陳述 | J27: 資訊分享 | K27: 純分享 | L27: 間接相關 | M27: null | N27: Zeekr 7X | O27: null | P27: null | Q27: 155 | R27: 31 | S27: 1
A28: https://www.facebook.com/groups/hkevcharging/permalink/3771795243115502/ | B28: Tsui Yu Ting | D28: 邊隻牌子嘅叉電機 比較易用 | E28: 46082 | H28: 中性 | I28: 疑問 | J28: 疑問/求助 | K28: 求助 | L28: 直接相關 | M28: null | N28: null | O28: null | P28: null | Q28: 0 | R28: 2 | S28: 0
A29: https://www.facebook.com/groups/hkevcharging/permalink/3769151960046497/ | B29: Victor Fung | D29: 請問Tesla Model Y 港車北上，中／快充轉換頭那款穩陣？ 淘寶的可以嗎？ | E29: 46080 | H29: 中性 | I29: 疑問 | J29: 疑問/求助 | K29: 求助 | L29: 直接相關 | M29: null | N29: Tesla Model Y | O29: null | P29: 中充/快充轉換頭 | Q29: 2 | R29: 9 | S29: 0
A30: https://www.facebook.com/groups/hkevcharging/permalink/3768334086794951/ | B30: Kwok Frankie | D30: 有無Brother 裝了A1w既充電器.comment如何.Thx | E30: 46078 | G30: https://scontent.fagc1-1.fna.fbcdn.net/v/t39.30808-6/642710550_25194664206874330_8166633197619759916_n.jpg?stp=dst-jpg_p526x296_tt6&_nc_cat=101&ccb=1-7&_nc_sid=aa7b47&_nc_ohc=7tXoKrFtv1AQ7kNvwGhHzju&_nc_oc=AdojbQ0Q5FNZ7NDizYpdZ6SZ0egzRqRqU7FFIASU8vifDcjjaZt69c2H6YXviKsm0XJP0F7lUxzyeC6Adi-Gb-Lh&_nc_zt=23&_nc_ht=scontent.fagc1-1.fna&_nc_gid=qGdLuqZxiF0hjhF2jHFUjg&_nc_ss=72289&oh=00_Af7XXxDeMbbXBU6r-SaS3cDOPgH1Z07-_Z8nnVBIxFpkRw&oe=6A10AE9D | H30: 中性 | I30: 疑問 | J30: 疑問/求助 | K30: 求助 | L30: 直接相關 | M30: null | N30: null | O30: null | P30: A1w | Q30: 0 | R30: 0 | S30: 0
A31: https://www.facebook.com/groups/hkevcharging/permalink/3753938491567844/ | B31: CopperPeapod2800 | D31: 60kw得24 kw | E31: 46078 | H31: 負面 | I31: 失望 | J31: 充電速度 | K31: 純分享 | L31: 直接相關 | M31: null | N31: null | O31: null | P31: 60kW, 24kW | Q31: 9 | R31: 7 | S31: 0
A32: https://www.facebook.com/groups/hkevcharging/permalink/3755099904785036/ | B32: Cheng Chris CC | D32: 經過見到火炭工業區充電站 $10度電？！係咪真架 | E32: 46078 | G32: https://scontent-dfw6-1.xx.fbcdn.net/v/t39.30808-6/629436437_793057113823225_58077082496708103_n.jpg?stp=dst-jpg_s720x720_tt6&_nc_cat=101&ccb=1-7&_nc_sid=aa7b47&_nc_ohc=Z8PzkEzOqRsQ7kNvwG_ueu2&_nc_oc=AdoiVGuw1NY6vT-8pWPjQ9JaYfIGLRNsSaA36ZTV6bepBUopPBvpXHeOnl2u2MU3sL0&_nc_zt=23&_nc_ht=scontent-dfw6-1.xx&_nc_gid=Ox6QFjUEige0dERYcTu9Aw&_nc_ss=72289&oh=00_Af4_YomIRoX1q43bidCGYhqQqZt6yrbF4fgjs9ydyA1USg&oe=6A10AAB9 | H32: 中性 | I32: 疑問 | J32: 收費/價錢 | K32: 求助 | L32: 直接相關 | M32: 火炭工業區 | N32: null | O32: null | P32: null | Q32: 29 | R32: 11 | S32: 0
A33: https://www.facebook.com/groups/hkevcharging/permalink/3752841158344244/ | B33: Sammy Ng | D33: 最近換電車，但屋苑車場冇充電位，想問下各位大圍/沙田有冇唔駛收泊車費的充電設施？ 預1個月充2次左右 | E33: 46062 | H33: 中性 | I33: 疑問 | J33: 充電站設施/位置 | K33: 求助 | L33: 直接相關 | M33: 大圍, 沙田 | N33: null | O33: null | P33: null | Q33: 23 | R33: 46 | S33: 0
A34: https://www.facebook.com/groups/hkevcharging/permalink/3742447299383630/ | B34: Well Done Charge | D34: 觀塘鴻圖道6-8號 設有10枝高達250kWh 車充，開張期$2.2/Kw 不用按金可八達通付款 | E34: 46051 | H34: 中性 | I34: 陳述 | J34: 收費/價錢 | K34: 廣告 | L34: 直接相關 | M34: 觀塘 | N34: null | O34: null | P34: 250kW | Q34: 61 | R34: 17 | S34: 0
A35: https://www.facebook.com/groups/hkevcharging/permalink/3741543679473992/ | B35: KC Wong | D35: 北角消防局對面車場，叉電45分中有叉電券送 | E35: 46051 | H35: 中性 | I35: 陳述 | J35: 資訊分享 | K35: 純分享 | L35: 直接相關 | M35: 北角 | N35: null | O35: null | P35: null | Q35: 3 | R35: 0 | S35: 2
A36: https://www.facebook.com/groups/hkevcharging/permalink/3734565240171836/ | B36: Tere Wong | D36: 請問各位師美孚附近嘅充電有無抵用好介紹呢 THX | E36: 46043 | H36: 中性 | I36: 疑問 | J36: 疑問/求助 | K36: 求助 | L36: 直接相關 | M36: 美孚 | N36: null | O36: null | P36: null | Q36: 2 | R36: 8 | S36: 1
A37: https://www.facebook.com/groups/hkevcharging/permalink/3727459897549037/ | B37: Louis Lai | D37: 小弟新嚟，想請教下各位師兄，請問而家係咪全部電動車嘅原廠保養，都係要定時大概每一萬公裡就要返廠檢查，仲要每個月只係限行三千公里？ 如果唔做嘅話就會即刻冇咗個新車保養？ 謝謝 | E37: 46036 | H37: 中性 | I37: 疑問 | J37: 疑問/求助 | K37: 求助 | L37: 直接相關 | M37: null | N37: null | O37: null | P37: null | Q37: 1 | R37: 15 | S37: 0
A38: https://www.facebook.com/groups/hkevcharging/permalink/3727154894246204/ | B38: Laurent Chang | D38: 想請教大家如果想知邊啲充電站係唔使入場或或無需停車場費 (例如 xeco, 大昌, 3號 等等) 淨係畀充電費嘅場 可以點樣搵？ 我見kilowatt都冇得咁樣分類 | E38: 46033 | H38: 中性 | I38: 疑問 | J38: 收費/價錢 | K38: 求助 | L38: 直接相關 | M38: null | N38: null | O38: Kilowatt, xeco, 大昌, 3號 | P38: null | Q38: 10 | R38: 12 | S38: 0
A39: https://www.facebook.com/groups/hkevcharging/permalink/3719067748388252/ | B39: Angel Chung | D39: 各位，請問紅磡附近會唔會有平而又快的充電地方，又唔使俾停車場費？ | E39: 46024 | H39: 中性 | I39: 疑問 | J39: 充電站設施/位置 | K39: 求助 | L39: 直接相關 | M39: 紅磡 | N39: null | O39: null | P39: null | Q39: 9 | R39: 17 | S39: 0
A40: https://www.facebook.com/groups/hkevcharging/permalink/3718633041765056/ | B40: 陳傲輝 | D40: 咁大架車，1度行6公里，為起3毫，堅唔堅呀？ | E40: 46023 | H40: 中性 | I40: 疑問 | J40: 收費/價錢 | K40: 求助 | L40: 直接相關 | M40: null | N40: null | O40: null | P40: null | Q40: 4 | R40: 11 | S40: 0
A41: https://www.facebook.com/groups/hkevcharging/permalink/3716140572014303/ | B41: Joe Cheung | D41: 356KW充電速度，唔使5分鐘30度電 觀塘偉業街95號地下 | E41: 46022 | H41: 正面 | I41: 期待 | J41: 充電速度 | K41: 廣告 | L41: 直接相關 | M41: 觀塘偉業街95號 | N41: null | O41: null | P41: 356kW | Q41: 28 | R41: 13 | S41: 2
A42: https://www.facebook.com/groups/hkevcharging/permalink/3717425001885860/ | B42: Anonymous participant | D42: 想問下九龍灣大昌行充電有冇超時收費？ | E42: 46022 | H42: 中性 | I42: 疑問 | J42: 收費/價錢 | K42: 求助 | L42: 直接相關 | M42: 九龍灣大昌行 | N42: null | O42: null | P42: null | Q42: 5 | R42: 22 | S42: 0
A43: https://www.facebook.com/groups/hkevcharging/permalink/3715236668771360/ | B43: Keven Leung | D43: 各位 師兄/師姐 請問鑽石山附近，邊度有平，快充電，使唔使俾停車場費？ | E43: 46020 | H43: 中性 | I43: 疑問 | J43: 充電站設施/位置 | K43: 求助 | L43: 直接相關 | M43: 鑽石山 | N43: null | O43: null | P43: 快充 | Q43: 4 | R43: 15 | S43: 0
A44: https://www.facebook.com/groups/hkevcharging/permalink/3711327155828978/ | B44: Gan Lo | D44: 長沙灣東京街 The Vertex 做緊聖誕優惠, 每度電$2.3 , 做到4-1-2026 11pm | E44: 46016 | G44: https://scontent.fric1-2.fna.fbcdn.net/v/t39.30808-6/604823766_1401853611535123_9065648715558759029_n.jpg?stp=dst-jpg_s640x640_tt6&_nc_cat=104&ccb=1-7&_nc_sid=aa7b47&_nc_ohc=ybfVsBM7_mwQ7kNvwGlpAS7&_nc_oc=AdpQom7FDab6GVlZMVkAhLyh4SJucfCKZJO8zZA0lsEDCXNrrhxAMRx94QeaE82DJN8&_nc_zt=23&_nc_ht=scontent.fric1-2.fna&_nc_gid=BwjW3zKIM1WTDwKZCClrIw&_nc_ss=72289&oh=00_Af43_qEo0_RpR0Hwcy9_c3ji_5XYYbAJLxVk6eUuMQykZg&oe=6A10CA2F | H44: 中性 | I44: 陳述 | J44: 收費/價錢 | K44: 廣告 | L44: 直接相關 | M44: 長沙灣東京街 The Vertex | N44: null | O44: null | P44: null | Q44: 10 | R44: 4 | S44: 3
A45: https://www.facebook.com/groups/hkevcharging/permalink/3709468786014815/ | B45: Davy Yu | C45: 網絡熱話｜將軍澳屋苑裝充電樁 每車位業主夾$2.1萬 網民：直頭係搶錢 | D45: https://ps.hket.com/article/4056722/網絡熱話｜將軍澳屋苑裝充電樁%20每車位業主夾-2.1萬%20網民：直頭係搶錢?mtc=60007 | E45: 46014 | H45: 負面 | I45: 生氣 | J45: 收費/價錢 | K45: 純分享 | L45: 直接相關 | M45: 將軍澳 | N45: null | O45: null | P45: null | Q45: 0 | R45: 4 | S45: 0
A46: https://www.facebook.com/groups/hkevcharging/permalink/3709636772664683/ | B46: Derek Leung | D46: 各位師兄，荃灣、葵涌邊到有免時租平啲嘅充電￼ | E46: 46014 | H46: 中性 | I46: 疑問 | J46: 充電站設施/位置 | K46: 求助 | L46: 直接相關 | M46: 荃灣, 葵涌 | N46: null | O46: null | P46: null | Q46: 8 | R46: 13 | S46: 0
A47: https://www.facebook.com/groups/hkevcharging/permalink/3709476522680708/ | B47: Davy Yu | D47: 麗港城同樣使用強迫手段要所有車位業主安裝供電設施(刀制)並集資工程分費，即使你不需要電車供設施並反對，一律強迫要承擔HK$2萬8千多(扣除政府資助)！還有，這費用的決定權是由麗港城所有業主(住宅及車位)投票，即純住宅沒有車位的業主都有權投票，而這些業是不用承擔工程費用，即是不用付錢的業主來決定所有車位業主都要比錢及比幾多錢！ | E47: 46014 | H47: 負面 | I47: 生氣 | J47: 安裝/硬件/技術 | K47: 純分享 | L47: 直接相關 | M47: 麗港城 | N47: null | O47: null | P47: null | Q47: 0 | R47: 13 | S47: 0
A48: https://www.facebook.com/groups/hkevcharging/permalink/3711254002502960/ | B48: Anonymous participant | D48: 啱啱屋企車位裝咗32A充電器，想請問各位師兄平時唔用充電器時，是否需要關刀制電源，定係由得充電器長著? | E48: 46014 | H48: 中性 | I48: 疑問 | J48: 疑問/求助 | K48: 求助 | L48: 直接相關 | M48: null | N48: null | O48: null | P48: 32A | Q48: 4 | R48: 11 | S48: 0
A49: https://www.facebook.com/groups/hkevcharging/permalink/3706651126296581/ | B49: Anonymous participant | D49: 請教：G6同海獅 四驅版 1516中 各位師兄會點揀 | E49: 46011 | H49: 中性 | I49: 疑問 | J49: 疑問/求助 | K49: 求助 | L49: 直接相關 | M49: null | N49: G6 (小鵬), 海獅 (比亞迪) | O49: null | P49: null | Q49: 2 | R49: 10 | S49: 0
A50: https://www.facebook.com/groups/hkevcharging/permalink/3705586846403009/ | B50: Toy Duck | D50: 想問咁多位意見， 15萬買電車買二手model 3 LR 定係 新車 mg4 LR 定係仲有其他選擇， 感謝！ | E50: 46008 | H50: 中性 | I50: 疑問 | J50: 疑問/求助 | K50: 求助 | L50: 直接相關 | M50: null | N50: Tesla Model 3 LR, MG4 LR | O50: null | P50: null | Q50: 13 | R50: 96 | S50: 0
A51: https://www.facebook.com/groups/hkevcharging/permalink/3705810643047296/ | B51: Anonymous participant | D51: 九龍灣大昌行 繁忙時段每度電 $2.3 至 2026-1-4為止 | E51: 46008 | H51: 中性 | I51: 陳述 | J51: 收費/價錢 | K51: 純分享 | L51: 直接相關 | M51: 九龍灣大昌行 | N51: null | O51: null | P51: null | Q51: 37 | R51: 18 | S51: 3
A52: https://www.facebook.com/groups/hkevcharging/permalink/3706202709674756/ | B52: CatBaba WiWi | D52: (村屋)想搵師傅拉線去泊車位牆上裝充電樁，有冇朋友用開邊間公司或者師傅？ | E52: 46008 | H52: 中性 | I52: 疑問 | J52: 安裝/硬件/技術 | K52: 求助 | L52: 直接相關 | M52: null | N52: null | O52: null | P52: null | Q52: 1 | R52: 1 | S52: 0
A53: https://www.facebook.com/groups/hkevcharging/permalink/3701733370121690/ | B53: Macus Lo | D53: 請問e-charge公屋車場如果夜晚充電過夜，會唔會有逾期收費㗎？ 個場有20個充電位，平時極少人充電，夜晚1架車都冇充，新車到咗想搵個鄰居問下都未遇過 | E53: 46003 | H53: 中性 | I53: 疑問 | J53: 收費/價錢 | K53: 求助 | L53: 直接相關 | M53: null | N53: null | O53: e-charge | P53: null | Q53: 5 | R53: 18 | S53: 0
A54: https://www.facebook.com/groups/hkevcharging/permalink/3693824887579205/ | B54: WaiMan Ieong | D54: 這 請問各位師兄， 有沒有電動車檢查維修服務嘅相熟車房介紹？ 本人是揸 EQB 250 已經揸咗三年原廠保養太貴￼ | E54: 45999 | H54: 中性 | I54: 疑問 | J54: 疑問/求助 | K54: 求助 | L54: 直接相關 | M54: null | N54: EQB 250 | O54: null | P54: null | Q54: 1 | R54: 11 | S54: 0
A55: https://www.facebook.com/groups/hkevcharging/permalink/3693051850989842/ | B55: Jane Wong | D55: 考慮換電車Zeekr x / G6 同價，電池保養G6永久優勢，Zeekr 保8年後等於0，想知各位意見 | E55: 45999 | H55: 中性 | I55: 疑問 | J55: 疑問/求助 | K55: 求助 | L55: 直接相關 | M55: null | N55: Zeekr X, G6 | O55: null | P55: null | Q55: 17 | R55: 67 | S55: 0
A56: https://www.facebook.com/groups/hkevcharging/permalink/3692678731027154/ | B56: Anonymous participant | D56: 想請教粉嶺充電攻略 最近出左部新Model Y，我住近華明個頭。我見雍盛個到有兩個快充，大部分時間都有空位，幾方便。但每次充電用快充係咪唔太好？定其實無咩所謂，或者有無住開呢頭係點玩法？ 感謝 | E56: 45999 | H56: 中性 | I56: 疑問 | J56: 疑問/求助 | K56: 求助 | L56: 直接相關 | M56: 粉嶺, 雍盛 | N56: Tesla Model Y | O56: null | P56: 快充 | Q56: 1 | R56: 5 | S56: 0
A57: https://www.facebook.com/groups/hkevcharging/permalink/3692611657700528/ | B57: Anonymous participant | D57: 想買架電動車，續航力約400km，有咩牌子介紹？ 唔想買國產牌子。 | E57: 45999 | H57: 中性 | I57: 疑問 | J57: 疑問/求助 | K57: 求助 | L57: 間接相關 | M57: null | N57: null | O57: null | P57: null | Q57: 10 | R57: 106 | S57: 0
... A59: https://www.facebook.com/groups/hkevcharging/permalink/3690126787949015/ | B59: Ken Leung | D59: 新車就到 請教屯門充電攻略 | E59: 45989 | H59: 中性 | I59: 疑問 | J59: 疑問/求助 | K59: 求助 | L59: 直接相關 | M59: 屯門 | N59: null | O59: null | P59: null | Q59: 4 | R59: 14 | S59: 0
A60: https://www.facebook.com/groups/hkevcharging/permalink/3685794925048868/ | B60: Anonymous participant | D60: 請問呢度仲有冇營運 ？ | E60: 45988 | G60: https://scontent-iad3-1.xx.fbcdn.net/v/t39.30808-6/586515673_10162474062972981_9187388815549626381_n.jpg?stp=dst-jpg_p526x296_tt6&_nc_cat=110&ccb=1-7&_nc_sid=aa7b47&_nc_ohc=nkse8Amsis8Q7kNvwFmB_KL&_nc_oc=AdrJ61cCk5Lqv4Ov9Lj1kktG4SApsUSpoVni4zzG0kz8I6r2wENNQ_uUBVbPLp3AcDY&_nc_zt=23&_nc_ht=scontent-iad3-1.xx&_nc_gid=hYqIRHsCz7-CAdIQL4O_sg&_nc_ss=72289&oh=00_Af48DBKr-uqRHWBvVNn2bWMZuvsCrP-Dx9y50O-76YP7Yg&oe=6A10C62B | H60: 中性 | I60: 疑問 | J60: 疑問/求助 | K60: 求助 | L60: 直接相關 | M60: null | N60: null | O60: null | P60: null | Q60: 0 | R60: 3 | S60: 0
A61: https://www.facebook.com/groups/hkevcharging/permalink/3686603284968032/ | B61: SuperMe Lim | D61: 請問有冇人知，九龍灣大昌充電站，如果過咗90分鐘要唔要罰錢？ 謝謝 | E61: 45988 | H61: 中性 | I61: 疑問 | J61: 疑問/求助 | K61: 求助 | L61: 直接相關 | M61: 九龍灣 | N61: null | O61: 大昌 | P61: null | Q61: 0 | R61: 5 | S61: 0
A62: https://www.facebook.com/groups/hkevcharging/permalink/3686839631611064/ | B62: Tan Tan | D62: 請問一換一計劃係咪到2026年3月就完? 有冇消息延長或減減免額? | E62: 45988 | H62: 中性 | I62: 疑問 | J62: 疑問/求助 | K62: 求助 | L62: 直接相關 | M62: null | N62: null | O62: null | P62: null | Q62: 0 | R62: 4 | S62: 0
A63: https://www.facebook.com/groups/hkevcharging/permalink/3689220531372974/ | B63: Marco Chan | D63: 計劃買電車 請教九龍灣充電攻略￼ | E63: 45988 | H63: 中性 | I63: 疑問 | J63: 疑問/求助 | K63: 求助 | L63: 直接相關 | M63: 九龍灣 | N63: null | O63: null | P63: null | Q63: 5 | R63: 17 | S63: 0
A64: https://www.facebook.com/groups/hkevcharging/permalink/3683860228575671/ | B64: Hm Tang | D64: 長沙灣係元州邨隔離 *THE VERTEX *有免時租充電$2.6m 一度電 位置冇得頂 免時租雖然暫時得一個月, 袋住先, 現場有3支120kW & 1支60kW https://maps.app.goo.gl/EMXRYw9oHCXdo6QF7 | E64: 45982 | H64: 正面 | I64: 開心 | J64: 收費/價錢 | K64: 純分享 | L64: 直接相關 | M64: 長沙灣, THE VERTEX, 元州邨 | N64: null | O64: null | P64: 120kW, 60kW | Q64: 91 | R64: 17 | S64: 2
A65: https://www.facebook.com/groups/hkevcharging/permalink/3683971488564545/ | B65: Gary Yip | D65: 請問元朗 區，外面有冇咩地方可以充電。利申博愛醫院對面的充電，因系統升級未能提供充值服務。要找個另外一個多快充樁的地方。 | E65: 45982 | H65: 中性 | I65: 疑問 | J65: 充電站設施/位置 | K65: 求助 | L65: 直接相關 | M65: 元朗,博愛醫院 | N65: null | O65: null | P65: 快充 | Q65: 1 | R65: 4 | S65: 0
A66: https://www.facebook.com/groups/hkevcharging/permalink/3680539975574363/ | B66: Szeto Pong | D66: 想問下咁多位師兄 如果廿零萬預算 ， 大家會出Model 3 定係小鵬G6定BYD SEAL 由於新手唔多識電車方面 所以想聽聽大家意見 ‍♂️麻煩晒各位 | E66: 45977 | H66: 中性 | I66: 疑問 | J66: 疑問/求助 | K66: 求助 | L66: 直接相關 | M66: null | N66: Tesla Model 3, 小鵬G6, BYD SEAL | O66: null | P66: null | Q66: 8 | R66: 65 | S66: 1
A67: https://www.facebook.com/groups/hkevcharging/permalink/3665160350445659/ | B67: Anonymous participant | D67: 新手請教，請問將軍澳區哪裡有免費充電/免時租充電？ | E67: 45961 | H67: 中性 | I67: 疑問 | J67: 疑問/求助 | K67: 求助 | L67: 直接相關 | M67: 將軍澳 | N67: null | O67: null | P67: null | Q67: 2 | R67: 3 | S67: 0
A68: https://www.facebook.com/groups/hkevcharging/permalink/3662334577394903/ | B68: Sunny Xiao | D68: 請問大家，沙田附近比亞迪快充邊度可以？ | E68: 45959 | H68: 中性 | I68: 疑問 | J68: 疑問/求助 | K68: 求助 | L68: 直接相關 | M68: 沙田 | N68: 比亞迪 | O68: null | P68: 快充 | Q68: 0 | R68: 2 | S68: 0
A69: https://www.facebook.com/groups/hkevcharging/permalink/3662983413996686/ | B69: 關嘉文 | D69: 今日去葵涌果邊充電，發現咗個新開嘅A1W充電站。 最吸引係快充240kW，充得好快，同埋有優惠$2.6一度電，幾抵用！ 地點喺大連排道金星工業大廈地下，有需要可以去試下。 | E69: 45959 | G69: https://scontent.foma1-2.fna.fbcdn.net/v/t39.30808-6/571213845_797237619968259_176482617158324699_n.jpg?stp=dst-jpg_p526x296_tt6&_nc_cat=108&ccb=1-7&_nc_sid=aa7b47&_nc_ohc=XlP7zox-DDkQ7kNvwFTAAki&_nc_oc=AdoJvaaMEHS2f5nauGHwfzqs6qZLT6aQKuyqdQmVZT0BbvVMr2GHE2eVGUf6V3gmftBRO0DRBw0zRbuRqzBtWLLX&_nc_zt=23&_nc_ht=scontent.foma1-2.fna&_nc_gid=K6mVUsEqC-JJCwseyxiRpQ&_nc_ss=72289&oh=00_Af7JuVJw9Aj8qb3CwVy8vr0kohmY-RKB6Vyn9bBYWUry1w&oe=6A10A610 | H69: 正面 | I69: 滿意 | J69: 充電速度 | K69: 純分享 | L69: 直接相關 | M69: 葵涌, 大連排道金星工業大廈 | N69: null | O69: A1W | P69: 240kW | Q69: 39 | R69: 29 | S69: 0
A70: https://www.facebook.com/groups/hkevcharging/permalink/3656499057978455/ | B70: Anonymous participant | E70: 45953 | Q70: 1 | R70: 0 | S70: 0
A71: https://www.facebook.com/groups/hkevcharging/permalink/3656990801262614/ | B71: Lenxis Shao | D71: 請教一下，我係三號電站充電，以前無為意，但最近3次先留意到充電公司每次入電kW數同我架車唔相符，每次都差2度電左右，大家有無試過？或者係咪正常？係電樁問題定係架車問題？ 雖然唔係多，但每架車都相差兩度約$6咁就大問題 求解答 | E71: 45953 | H71: 中性 | I71: 疑問 | J71: 疑問/求助 | K71: 求助 | L71: 直接相關 | M71: null | N71: null | O71: 三號電站 | P71: null | Q71: 13 | R71: 27 | S71: 0
A72: https://www.facebook.com/groups/hkevcharging/permalink/3655932808035080/ | B72: Sam Chan | D72: 想問問自己本身有tesla wall connector 想搵師傅裝 開錶 大概要幾錢 ehss | E72: 45950 | H72: 中性 | I72: 疑問 | J72: 安裝/硬件/技術 | K72: 求助 | L72: 直接相關 | M72: null | N72: null | O72: null | P72: null | Q72: 2 | R72: 13 | S72: 3
A73: https://www.facebook.com/groups/hkevcharging/permalink/3654526194842408/ | B73: Keith Leung | C73: 全新第二代S3XYEV 32A三相Type 2 to Type 2中速充電線(現貨發售) | S3XYEV | D73: 想請教下圖中充電樁，是買中叉線就可以嗎？新手請教。 | E73: 45950 | H73: 中性 | I73: 疑問 | J73: 疑問/求助 | K73: 求助 | L73: 直接相關 | M73: null | N73: null | O73: null | P73: 中充, Type 2 | Q73: 33 | R73: 34 | S73: 0
A74: https://www.facebook.com/groups/hkevcharging/permalink/3648007942160900/ | B74: Jack Tsui | D74: 有冇師兄可以分享下屋苑完成ehss工程後請人安裝充電樁嘅步驟，大概需時幾耐完成，唔該曬。 | E74: 45944 | H74: 中性 | I74: 疑問 | J74: 安裝/硬件/技術 | K74: 求助 | L74: 直接相關 | M74: null | N74: null | O74: null | P74: null | Q74: 4 | R74: 22 | S74: 0
A75: https://www.facebook.com/groups/hkevcharging/permalink/3644752415819786/ | B75: Kin Lam Ma | D75: 安裝充電器有冇好介紹 | E75: 45939 | H75: 中性 | I75: 疑問 | J75: 安裝/硬件/技術 | K75: 求助 | L75: 直接相關 | M75: null | N75: null | O75: null | P75: null | Q75: 1 | R75: 2 | S75: 0
A76: https://www.facebook.com/groups/hkevcharging/permalink/3643789595916068/ | B76: Kong Bji | D76: 元朗麗珊園有免費充電(9/10-11/10) | E76: 45938 | G76: https://scontent-phx1-1.xx.fbcdn.net/v/t39.30808-6/558805359_122265536996223844_6885238847861211894_n.jpg?stp=dst-jpg_p526x296_tt6&_nc_cat=111&ccb=1-7&_nc_sid=aa7b47&_nc_ohc=RXjxiZ_U8rwQ7kNvwH8fF7s&_nc_oc=AdpJ5i9tqNDSvBNADGu2oB3QIkufnQIHtSCQ0u6ZXMDcBacyVyJ1Vr3YE3OQ_Bl5gEQ&_nc_zt=23&_nc_ht=scontent-phx1-1.xx&_nc_gid=QNTptIwX8TLqYDiOW-zIHQ&_nc_ss=72289&oh=00_Af6W7rifQ69jrgvPWzFE5nJEarX5UTVybTsQSOjlLVo6Mw&oe=6A10AB44 | H76: 中性 | I76: 陳述 | J76: 資訊分享 | K76: 純分享 | L76: 直接相關 | M76: 元朗麗珊園 | N76: null | O76: null | P76: null | Q76: 15 | R76: 6 | S76: 0
A77: https://www.facebook.com/groups/hkevcharging/permalink/3628386060789755/ | B77: Anonymous participant | D77: 想問下寶琳新都城一期有冇得充電？ | E77: 45922 | H77: 中性 | I77: 疑問 | J77: 充電站設施/位置 | K77: 求助 | L77: 直接相關 | M77: 寶琳新都城一期 | N77: null | O77: null | P77: null | Q77: 1 | R77: 3 | S77: 0
A78: https://www.facebook.com/groups/hkevcharging/permalink/3625556891072672/ | B78: Gary Tai | D78: 各位師兄師姐，大家好，請問東涌邊度有得充車？收費喺點？ | E78: 45919 | Q78: 1 | R78: 4 | S78: 0
A79: https://www.facebook.com/groups/hkevcharging/permalink/3620496738245354/ | B79: Anonymous participant | D79: 屯門有冇大型叉電場？ | E79: 45914 | H79: 中性 | I79: 疑問 | J79: 疑問/求助 | K79: 求助 | L79: 直接相關 | M79: 屯門 | N79: null | O79: null | P79: null | Q79: 4 | R79: 1 | S79: 0
A80: https://www.facebook.com/groups/hkevcharging/permalink/3619691551659206/ | B80: Anonymous participant | D80: 元朗友又多個選择了，三號電站又系博愛隔离，新港酒店後面開多個超充站，有8個超充位，仲有又快又輕的液冷機。仲有埋車棚吾使日晒雨淋，又吾使停車費。 充電首選。 | E80: 45913 | H80: 正面 | I80: 開心 | J80: 充電站設施/位置 | K80: 純分享 | L80: 直接相關 | M80: 元朗, 博愛, 新港酒店 | N80: null | O80: 三號電站 | P80: 超充, 液冷 | Q80: 19 | R80: 11 | S80: 1
A81: https://www.facebook.com/groups/hkevcharging/permalink/3616178332010528/ | B81: Yat Ku | D81: 新手一間，電車車頭大燈燈組同油車車頭燈燈組一樣嗎？ | E81: 45909 | H81: 中性 | I81: 疑問 | J81: 疑問/求助 | K81: 求助 | L81: 間接相關 | M81: null | N81: null | O81: null | P81: null | Q81: 1 | R81: 1 | S81: 0
A82: https://www.facebook.com/groups/hkevcharging/permalink/3612600255701669/ | B82: Siu Lun Wong | D82: $1.98/kWh | E82: 45904 | H82: 中性 | I82: 陳述 | J82: 收費/價錢 | K82: 純分享 | L82: 直接相關 | M82: null | N82: null | O82: null | P82: null | Q82: 1 | R82: 2 | S82: 0
A83: https://www.facebook.com/groups/hkevcharging/permalink/3612237195737975/ | B83: Amuro Lee | C83: 一場有關特斯拉Autopilot而引起的死亡車禍，Tesla被判需賠償高達77億台幣！ | E83: 45904 | H83: 負面 | I83: 驚 | J83: 其他 | K83: 純分享 | L83: 間接相關 | M83: null | N83: Tesla | O83: null | P83: null | Q83: 0 | R83: 0 | S83: 0
A84: https://www.facebook.com/groups/hkevcharging/permalink/3611499062478455/ | B84: Ricky Chen | D84: 送的充電裝置包埋安裝，禽晚第一次用wall connector，剩返廿幾%電charge滿大約咁多錢，唔知準唔準。 | E84: 45903 | H84: 中性 | I84: 疑問 | J84: 收費/價錢 | K84: 求助 | L84: 直接相關 | M84: null | N84: null | O84: Tesla | P84: null | Q84: 3 | R84: 1 | S84: 0
A85: https://www.facebook.com/groups/hkevcharging/permalink/3609179249377103/ | B85: Anonymous participant | D85: 唔好意思, 上網搵咗好耐都唔係有d太明要求教大家。 岩岩買了MODEL 3等攞車，公司有13A位，樓下車場有cornerstone中充位，咁係咪應該買一條13A (tesla umc), 同埋一條type 2線? 有冇線兼容13a同type 2? 最後, 比較唔明的地方係，係咪有d 中充站跟機有線唔駛用自己線, 有d中充站就要自己線? 我見樓下cornerstone好似冇線在機附近。網上睇中電充站又好似充電有線。 唔該大家先 | E85: 45901 | H85: 中性 | I85: 疑問 | J85: 疑問/求助 | K85: 求助 | L85: 直接相關 | M85: null | N85: Tesla Model 3 | O85: Cornerstone, 中電 | P85: 13A, 中充, Type 2 | Q85: 1 | R85: 7 | S85: 0
A86: https://www.facebook.com/groups/hkevcharging/permalink/3606907939604234/ | B86: Amuro Lee | E86: 45898 | Q86: 0 | R86: 0 | S86: 0
A87: https://www.facebook.com/groups/hkevcharging/permalink/3597605347201160/ | B87: Amuro Lee | E87: 45888 | Q87: 1 | R87: 0 | S87: 0
A88: https://www.facebook.com/groups/hkevcharging/permalink/3598340210461007/ | B88: Jerry Zhang | D88: 邊間公司可以建超充充電站呢 | E88: 45888 | H88: 中性 | I88: 疑問 | J88: 疑問/求助 | K88: 求助 | L88: 直接相關 | M88: null | N88: null | O88: null | P88: 超充 | Q88: 4 | R88: 9 | S88: 0
A89: https://www.facebook.com/groups/hkevcharging/permalink/3598375053790856/ | B89: Amuro Lee | D89: 小馬橫行 | E89: 45888 | H89: 負面 | I89: 生氣 | J89: 排隊/打尖/霸位 | K89: 純分享 | L89: 直接相關 | M89: null | N89: null | O89: null | P89: null | Q89: 1 | R89: 0 | S89: 1
A90: https://www.facebook.com/groups/hkevcharging/permalink/3595457420749286/ | B90: Wai Fay Chai Wai | D90: 藍塘匯十點前充電係平，但係已經試過兩次，吾知係唔係因為人地充多，調慢充電，但十點後去充幾次都沒問題 | E90: 45885 | H90: 中性 | I90: 疑問 | J90: 充電速度 | K90: 純分享 | L90: 直接相關 | M90: 藍塘匯 | N90: null | O90: null | P90: null | Q90: 13 | R90: 24 | S90: 0
A91: https://www.facebook.com/groups/hkevcharging/permalink/3588495771445451/ | B91: Amuro Lee | E91: 45878 | Q91: 1 | R91: 0 | S91: 0
A92: https://www.facebook.com/groups/hkevcharging/permalink/3588713688090326/ | B92: Anonymous participant | D92: 想請問吓，EHSS計劃下嘅屋苑，裝完基礎設施後，車位業主如唔想俾錢裝7kwh叉機，咁租客有冇得同中電申請開電錶，用13A嚟慢充㗎？唔該晒。 | E92: 45878 | H92: 中性 | I92: 疑問 | J92: 疑問/求助 | K92: 求助 | L92: 直接相關 | M92: null | N92: null | O92: null | P92: 慢充, 13A, 7kW | Q92: 1 | R92: 1 | S92: 0
A93: https://www.facebook.com/groups/hkevcharging/permalink/3586306428331052/ | B93: LokLok Lam Draco | D93: Asgard荔枝角呢個場大家小心 睇app顯示仲有位 過到去有部benz係到霸左個位 好聲好氣過去問姐姐點解呢部Benz會霸左呢個位 個場有其他位佢可以泊 個姐姐係cls燥狂 內容不斷重覆如下（你問我做乜？你問個車主囉！佢要擺係到我可以點？你做咩過黎問我！你唔鐘意咪唔好黎去第二到差！你投訴我囉呢到有電話！！期間係不停拍滑鼠bang門）有其他差緊電同等緊既師兄都見到 而最瘋狂我知佢有燥狂都廢事理佢 咪同個師兄吹水 我地吹水又關佢事 又係咁鬧我地 叫我地唔好問佢 有咩問車主 唔鍾意就走個師兄話佢黎親都見到呢部benz停呢個位冇人鎖車 | E93: 45875 | G93: https://scontent.flas1-1.fna.fbcdn.net/v/t39.30808-6/529229823_10161672286381717_7184678381933761045_n.jpg?stp=dst-jpg_p526x296_tt6&_nc_cat=110&ccb=1-7&_nc_sid=aa7b47&_nc_ohc=QJmmKTUABrYQ7kNvwEZ4ncH&_nc_oc=AdqiPUjN3uNlNqnQOo99JbE4waETsMfbk2XPC4wx_FsdR__ewtS3wpTwefJPBDdREP0&_nc_zt=23&_nc_ht=scontent.flas1-1.fna&_nc_gid=IG2mLaZy4cVBiyFNNYfmUw&_nc_ss=72289&oh=00_Af46ssgu_y2QXdKZ4wYwfxGEMUbRtqbsAvE0qVwjuWxaxw&oe=6A10B3BE | H93: 負面 | I93: 生氣 | J93: 排隊/打尖/霸位 | K93: 純分享 | L93: 直接相關 | M93: 荔枝角 | N93: Benz | O93: Asgard | P93: null | Q93: 38 | R93: 56 | S93: 1
A94: https://www.facebook.com/groups/hkevcharging/permalink/3585860771708951/ | B94: Anonymous participant | C94: 澳門半價買電動車 香港駕駛恐違法｜信報專題｜澳門｜電動車｜保時捷｜勞斯萊斯｜機動車輛稅｜港澳ZM牌｜黑中介｜車契｜車保｜第三者保險【論盡熱話系列】 | D94: 請問有冇師兄去澳門出牌買電車返嚟？ | E94: 45874 | H94: 中性 | I94: 疑問 | J94: 疑問/求助 | K94: 求助 | L94: 直接相關 | M94: 澳門 | N94: null | O94: null | P94: null | Q94: 1 | R94: 10 | S94: 0
A95: https://www.facebook.com/groups/hkevcharging/permalink/3584418275186534/ | B95: Lo Yuk Fai | D95: 錦上路站新轉乘停車場 有一堆講明要收錢嘅 Type 2 插位 另外有好多 13A 位唔清楚要不要錢 錦上路站 A 出口行過對面就係 留意番充電收費係每半小時計 注：應該仲有一啲快充位的，不過好熱我唔想行哂成個場，所以冇見到……另外入邉係手機結界 | E95: 45873 | H95: 中性 | I95: 陳述 | J95: 充電站設施/位置 | K95: 純分享 | L95: 直接相關 | M95: 錦上路站 | N95: null | O95: null | P95: Type 2, 13A | Q95: 19 | R95: 8 | S95: 0
A96: https://www.facebook.com/groups/hkevcharging/permalink/3582450638716631/ | B96: Anonymous participant | D96: tesla 部份 wc位 8月1號起 已經正常收費 $2.45 | E96: 45870 | G96: https://scontent-mia5-1.xx.fbcdn.net/v/t39.30808-6/525909662_1922200111911580_1523070301868978072_n.jpg?stp=dst-jpg_s720x720_tt6&_nc_cat=101&ccb=1-7&_nc_sid=aa7b47&_nc_ohc=AGBZYdZmcMoQ7kNvwFMtret&_nc_oc=AdqyLwYsrwzfRaQGNuq_nB7_NQaCWzx8QI6K_EF27FpsqivGtXqIk5xbpruniLFE8Wc&_nc_zt=23&_nc_ht=scontent-mia5-1.xx&_nc_gid=hooZUXShQ6U31wjOvGwaLw&_nc_ss=72289&oh=00_Af67hGkJfQiBMPnWTFxMR7GxwqI2AZubCY67Mdp3aHxWow&oe=6A10BD56 | H96: 中性 | I96: 陳述 | J96: 收費/價錢 | K96: 純分享 | L96: 直接相關 | M96: null | N96: null | O96: Tesla | P96: Wall Connector | Q96: 14 | R96: 1 | S96: 0
A97: https://www.facebook.com/groups/hkevcharging/permalink/3581447812150247/ | B97: KC Wong | D97: # 想問下， 新蒲崗免費充電開始左? | E97: 45869 | G97: https://scontent-mia3-2.xx.fbcdn.net/v/t39.30808-6/525395954_122125075772890508_3768711696796718633_n.jpg?stp=dst-jpg_p526x296_tt6&_nc_cat=103&ccb=1-7&_nc_sid=aa7b47&_nc_ohc=IZqKDn5mBKcQ7kNvwHai-_G&_nc_oc=AdrcIxys713XZJ0rhxNngBieb8ULn6XNw_0VOvXa_bcbJzl3Z_b4PLCap85WV19RxvQ&_nc_zt=23&_nc_ht=scontent-mia3-2.xx&_nc_gid=hooZUXShQ6U31wjOvGwaLw&_nc_ss=72289&oh=00_Af7t9_-aCoIIeEfJel9uvcz6xKEKnkrzS6SyLCAUh0Bnwg&oe=6A10BB9C | H97: 中性 | I97: 疑問 | J97: 充電站設施/位置 | K97: 求助 | L97: 直接相關 | M97: 新蒲崗 | N97: null | O97: null | P97: null | Q97: 4 | R97: 5 | S97: 0
A98: https://www.facebook.com/groups/hkevcharging/permalink/3579878772307151/ | B98: InspiringGiraffe3105 | D98: 想問下有冇知快充， 最平幾多錢/kWh | E98: 45868 | H98: 中性 | I98: 疑問 | J98: 收費/價錢 | K98: 求助 | L98: 直接相關 | M98: null | N98: null | O98: null | P98: 快充 | Q98: 1 | R98: 4 | S98: 0
A99: https://www.facebook.com/groups/hkevcharging/permalink/3580606125567749/ | B99: Kenny Lo | D99: 香園圍停車場R88 可唔可以有好心人幫手禁一下感謝 | E99: 45868 | H99: 中性 | I99: 疑問 | J99: 疑問/求助 | K99: 求助 | L99: 直接相關 | M99: 香園圍停車場 | N99: null | O99: null | P99: null | Q99: 7 | R99: 3 | S99: 0
A100: https://www.facebook.com/groups/hkevcharging/permalink/3579367365691625/ | B100: Lo Yuk Fai | D100: 致：柏麗各住戶 「錦上路港鐵站停車場」啟用事宜 客務處近日收到「錦上路港鐵站」通知，本發展項目內的 B1 地庫車站停車場將於 8 月 3 日凌晨 1 時 30 分正式啟用。住戶可沿 1 號及 2 號地庫穿梭至大堂外之指示前往 B1 地庫車站停車場。以下是該停車場之收費 | E100: 45867 | G100: https://scontent-det1-1.xx.fbcdn.net/v/t39.30808-6/524757689_3264055573745932_5313225725949685040_n.jpg?stp=dst-jpg_s1080x2048_tt6&_nc_cat=108&ccb=1-7&_nc_sid=aa7b47&_nc_ohc=Y6Lind0HcXgQ7kNvwFFffKo&_nc_oc=AdqaPR2c72nTGXFqEXhdUZ8qJIOWfr6Xqw2UJdCI0KQYJhrAnj6WR8Jt6zzVtRoNOYM&_nc_zt=23&_nc_ht=scontent-det1-1.xx&_nc_gid=iIXY0hXhcXW2_LQX_ldiRA&_nc_ss=72289&oh=00_Af4yN9WCN2XsWq0foBBDZrshaM836aMv8_w5QlT71i8r9w&oe=6A10B399 | H100: 中性 | I100: 陳述 | J100: 收費/價錢 | K100: 純分享 | L100: 直接相關 | M100: 錦上路港鐵站 | N100: null | O100: null | P100: 中速, 快充, 7kW, 50kW | Q100: 7 | R100: 7 | S100: 1
A101: https://www.facebook.com/groups/hkevcharging/permalink/3579163302378698/ | B101: Raymond Lau | D101: The Point 充電有咩情況最快只有 40kwh? 近日去充有時最快只有 40kwh, 隔離係冇車充緊 | E101: 45867 | H101: 負面 | I101: 疑問 | J101: 充電速度 | K101: 求助 | L101: 直接相關 | M101: null | N101: null | O101: null | P101: 40kW | Q101: 1 | R101: 19 | S101: 0
...

Sheet 電動車好去處分享 3
A1: url | B1: user_name | C1: text | D1: time | E1: video_url_one | F1: photo_url_one | G1: emotion_basic | H1: emotion_detailed | I1: theme | J1: info_value | K1: ev_relevance | L1: Location_Mentioned | M1: EV_Model_Mentioned | N1: Competitor_Brand | O1: Charging_Type | P1: likesCount | Q1: commentsCount | R1: sharesCount
A2: https://www.facebook.com/groups/hkevdiary/permalink/1742569410489384/ | B2: Samantha Vlog | C2: 3月又真係好多朋友買咗電動車你收咗車未呀🤓 運輸署表示，3月接獲約13,500宗「一換一」申請，較以往按月平均大幅增加超過3倍。截至4月底，已處理約85%，其餘主要於3月下旬遞交的，預計本月中陸續完成。 | D2: 2026/05/09 | G2: 中性 | H2: 陳述 | I2: 資訊分享 | J2: 純分享 | K2: 間接相關 | L2: null | M2: null | N2: null | O2: null | P2: 9 | Q2: 0 | R2: 0
A3: https://www.facebook.com/groups/hkevdiary/permalink/1741975300548795/ | B3: Samantha Vlog | C3: 潮流興L 寶馬 iX1 L 長陣版 IX1 EDRIVE20L M SPORT EDITION U12 中國製造，車長4,616mm (+116mm)，軸距2,802mm (+110mm) 單摩打前驅，電池66.5kWh，續航433km (WLTP) 連稅售價HK$469,900 | D3: 2026/05/08 | G3: 中性 | H3: 陳述 | I3: 資訊分享 | J3: 純分享 | K3: 直接相關 | L3: null | M3: BMW iX1 | N3: null | O3: null | P3: 17 | Q3: 9 | R3: 0
A4: https://www.facebook.com/groups/hkevdiary/permalink/1741192677293724/ | B4: Hin Lo | C4: 【2026年4月份電動車首次登記 仍有8千部‼️】 喺取消一換一餘溫下，4月份共有8,078部電動私家車登記，第一位AION，第二位Tesla，第三位BYD。 頭五位型號： 1️⃣TESLA MODEL Y RWD – 732部 2️⃣TOYOTA BZ3X – 551部 3️⃣BYD SEALION 7 – 485部 4️⃣AION ES – 462部 5️⃣AION UT PREMIUM – 449部 *以運輸署登記型號名稱計 想知邊部電動車好賣啲？Click入黎網站 https://hkevdb.com #AION #TESLA #BYD #ZEEKR #TOYOTA | D4: 2026/05/07 | G4: 中性 | H4: 陳述 | I4: 資訊分享 | J4: 純分享 | K4: 間接相關 | L4: null | M4: BYD ATTO 2, Tesla Model Y RWD, Dongfeng Nammi Vigo Pro, Tesla Model 3 RWD, Zeekr 7X Platinum | N4: null | O4: null | P4: 10 | Q4: 0 | R4: 0
A5: https://www.facebook.com/groups/hkevdiary/permalink/1730490095030649/ | B5: Samantha Vlog | C5: 行車片以前錄得一個鐘，update後有24小時 | D5: 2026/04/24 | F5: https://scontent-atl3-1.xx.fbcdn.net/v/t39.30808-6/678675990_1560797179380012_1336673483405353334_n.jpg?stp=cp6_dst-jpg_s640x640_tt6&_nc_cat=106&ccb=1-7&_nc_sid=aa7b47&_nc_ohc=FHOXL0eZGcUQ7kNvwEnpJ_q&_nc_oc=Adq3jYcdFfORLAzGJMkVSD55o4vRBY3FWGr801sMemmOnlmMkfXREq6bIlNgEf3XAtg&_nc_zt=23&_nc_ht=scontent-atl3-1.xx&_nc_gid=lViGiTko_Pgh41w8qxw_Aw&_nc_ss=72289&oh=00_Af4Ezots8SdMFa-L-xlriMEpMO0y8O0qgtaDIpHLJ2wHFw&oe=6A118E5C | G5: 中性 | H5: 陳述 | I5: 其他 | J5: 純分享 | K5: 無關 | L5: null | M5: null | N5: null | O5: null | P5: 42 | Q5: 9 | R5: 1
A6: https://www.facebook.com/groups/hkevdiary/permalink/1727313928681599/ | B6: Anonymous participant | C6: 網上好多留言話電動車冇靈魂，咁其實啲細cc+cvt波箱嘅油車、7人車，除咗引擎嘈，又有咩靈魂，唔通個個都揸JDM、超跑？ 利申：油車電車都OK，睇個人需要 | D6: 2026/04/20 | G6: 中性 | H6: 陳述 | I6: 其他 | J6: 純分享 | K6: 間接相關 | L6: null | M6: null | N6: null | O6: null | P6: 46 | Q6: 59 | R6: 0
A7: https://www.facebook.com/groups/hkevdiary/permalink/1727256262020699/ | B7: Samantha Vlog | C7: 全新電動C-Class C400 4MATIC - 800V架構，快充最高330kW - 94kWh電池，續航762公里 (WLTP) - 前後雙摩打，後摩打配有兩速波箱 - 馬力360kW、扭力800Nm - 0-100km/h 4秒 - 長4883 x 闊1892 x 高1503mm、軸距2962mm - 車重2460kg - 選配氣壓避震、後輪轉向 | D7: 2026/04/20 | G7: 中性 | H7: 陳述 | I7: 安裝/硬件/技術 | J7: 純分享 | K7: 直接相關 | L7: null | M7: Mercedes-Benz C-Class C400 4MATIC | N7: null | O7: 800V, 快充, 330kW | P7: 49 | Q7: 16 | R7: 4
A8: https://www.facebook.com/groups/hkevdiary/permalink/1725559322190393/ | B8: Anonymous participant | C8: 送免費Supercharging仲好啦，冇永久都送5年吖 你好，全新 6座版Model YL 已經正式推出，車價連稅$499,978。 現有Model Y 特選車主除咗可以享有特高trade in價外，仲有高達$10000 Liberty 保費回贈以及免費升級兩年專享網絡。 | D8: 2026/04/18 | F8: https://scontent-lga3-1.xx.fbcdn.net/v/t39.30808-6/674594046_10162580309556441_3708870992521192479_n.jpg?stp=dst-jpg_s720x720_tt6&_nc_cat=110&ccb=1-7&_nc_sid=aa7b47&_nc_ohc=sVQuixazQ6gQ7kNvwEqIp67&_nc_oc=AdqZyavrPpYaa6qSB1P_Dbp-KjsT7w3sBBTgkHnqDlqq5ceL0y77r8Q4_zwrNORn7vg&_nc_zt=23&_nc_ht=scontent-lga3-1.xx&_nc_gid=Xei9BtAjcdbLc_uq07tikQ&_nc_ss=72289&oh=00_Af64ZFtF-1AFZiULFFws6SfKJETob61CSvjoGkPWjWRPig&oe=6A119D1D | G8: 中性 | H8: 期待 | I8: 廣告/促銷 | J8: 廣告 | K8: 間接相關 | L8: null | M8: Tesla Model Y | N8: null | O8: 超充 | P8: 115 | Q8: 92 | R8: 0
A9: https://www.facebook.com/groups/hkevdiary/permalink/1724727288940263/ | B9: Vincent Chan | C9: 大家有冇用多層停車場嗰d中差74個政府停車場中，有1,600個充電樁的平均使用率是12% 對比去年數字雖有上升，但超過一半充電樁的平均使用率是單位數 | D9: 2026/04/17 | G9: 中性 | H9: 疑問 | I9: 充電站設施/位置 | J9: 純分享 | K9: 直接相關 | L9: null | M9: null | N9: null | O9: 中充 | P9: 2 | Q9: 10 | R9: 0
A10: https://www.facebook.com/groups/hkevdiary/permalink/1724084889004503/ | B10: Perry Leung | C10: 巴打們 如果部車冇Apps 屋企個叉電樁亦都冇Apps 咁我想預設叉電時間之類 係咪有啲乜嘢後加硬件 或者可以set時間嘅叉電線解決呢個問題？ | D10: 2026/04/16 | G10: 中性 | H10: 疑問 | I10: 疑問/求助 | J10: 求助 | K10: 直接相關 | L10: null | M10: null | N10: null | O10: null | P10: 5 | Q10: 20 | R10: 0
A11: https://www.facebook.com/groups/hkevdiary/permalink/1721170199295972/ | B11: Myacc Chak | C11: 一堆大陸賣八萬 十五萬嘅車 1換1都要18至28萬 而家賣到三十 | D11: 2026/04/13 | G11: 負面 | H11: 失望 | I11: 其他 | J11: 純分享 | K11: 無關 | L11: null | M11: null | N11: null | O11: null | P11: 37 | Q11: 54 | R11: 0
A12: https://www.facebook.com/groups/hkevdiary/permalink/1719510786128580/ | B12: Just Be You | C12: Model Y 都轉埋YL 果隻淺灰籠，無左白籠，20寸鈴改埋灰槍色 | D12: 2026/04/10 | G12: 中性 | H12: 陳述 | I12: 其他 | J12: 純分享 | K12: 間接相關 | L12: null | M12: Tesla Model Y | N12: null | O12: null | P12: 19 | Q12: 2 | R12: 0
A13: https://www.facebook.com/groups/hkevdiary/permalink/1718804729532519/ | B13: Anonymous participant | C13: 行到條鈴變鈴冚 | D13: 2026/04/09 | F13: https://scontent-bos5-1.xx.fbcdn.net/v/t39.30808-6/669921882_1768057301245775_2339100306200886391_n.jpg?stp=dst-jpg_p526x296_tt6&_nc_cat=109&ccb=1-7&_nc_sid=aa7b47&_nc_ohc=Q3_s1Df2XT0Q7kNvwGxZfAi&_nc_oc=AdoKpuMfhPtJoqrk2icTdcNOZJ137owgapRCmbFBE7-VPnutPQmfx99zPJNxupxl1DQ&_nc_zt=23&_nc_ht=scontent-bos5-1.xx&_nc_gid=Ar1Gyn_YHLSLsiqKtQ3YyQ&_nc_ss=7d289&oh=00_Af73fqZOubCppe2zC1sbhYiviOqlavUSXvsOciFqKLxxhA&oe=6A118AB5 | G13: 中性 | H13: 陳述 | I13: 其他 | J13: 純分享 | K13: 直接相關 | L13: null | M13: null | N13: null | O13: null | P13: 176 | Q13: 27 | R13: 1
A14: https://www.facebook.com/groups/hkevdiary/permalink/1713324203413905/ | B14: Hin Lo | C14: 一個3月登記左9千部電動車!!【2026年3月份電動車首次登記 超過9千部‼️】 喺取消一換一效應下，3月份共有9,150部電動私家車登記，相信係有史以嚟最多嘅一個月，第一位BYD Hong Kong - Harmony Auto，第二位Tesla，第三位AION。 頭五位型號： 1️⃣BYD ATTO 2 – 1,495部 2️⃣TESLA MODEL Y RWD – 811部 3️⃣DONGFENG NAMMI VIGO PRO – 665部 4️⃣TESLA MODEL 3 RWD – 512部 5️⃣ZEEKR 7X PLATINUM – 498部 *以運輸署登記型號名稱計 想知邊部電動車好賣啲？Click入黎網站 https://hkevdb.com #BYD #TESLA #AION #ZEEKR #DONGFENG | D14: 2026/04/02 | G14: 中性 | H14: 陳述 | I14: 資訊分享 | J14: 純分享 | K14: 間接相關 | L14: null | M14: BYD ATTO 2, Tesla Model Y RWD, Dongfeng Nammi Vigo Pro, Tesla Model 3 RWD, Zeekr 7X Platinum | N14: null | O14: null | P14: 18 | Q14: 13 | R14: 0
A15: https://www.facebook.com/groups/hkevdiary/permalink/1713269290086063/ | B15: Vincent Chan | C15: 去差電又要俾多5蚊喇.領展於4月8日起取消免費泊車優惠，改為指定時數優惠價時租$5，電動車1小時免費泊車優惠「EV泊」亦會於同日終止，同樣改為時租$5，優惠1小時 | D15: 2026/04/02 | G15: 負面 | H15: 失望 | I15: 充電站設施/位置 | J15: 純分享 | K15: 直接相關 | L15: null | M15: null | N15: 領展 | O15: null | P15: 1 | Q15: 1 | R15: 0
A16: https://www.facebook.com/groups/hkevdiary/permalink/1713166036763055/ | B16: Anonymous participant | C16: 28car已經有人將炒價Model Y 0公里車放上去賣 唔係犯法咩？ | D16: 2026/04/02 | G16: 中性 | H16: 疑問 | I16: 疑問/求助 | J16: 求助 | K16: 間接相關 | L16: null | M16: Tesla Model Y | N16: null | O16: null | P16: 66 | Q16: 67 | R16: 1
A17: https://www.facebook.com/groups/hkevdiary/permalink/1712346946844964/ | B17: Richard Tang | C17: https://news.now.com/home/local/player?newsId=642162 | D17: 2026/04/02 | G17: 中性 | H17: 陳述 | I17: 收費/價錢 | J17: 純分享 | K17: 直接相關 | L17: null | M17: null | N17: null | O17: null | P17: 12 | Q17: 11 | R17: 0
A18: https://www.facebook.com/groups/hkevdiary/permalink/1712789756800683/ | B18: Anonymous participant | C18: 環境及生態局表示，習慣駕駛燃油車是5000元一個月的油費，轉用電動車就是4、500元，那個巨大的相差，見到電動車已經完全有競爭力在當中，毋須再有一換一 | D18: 2026/04/01 | G18: 中性 | H18: 陳述 | I18: 收費/價錢 | J18: 純分享 | K18: 直接相關 | L18: null | M18: null | N18: null | O18: null | P18: 58 | Q18: 67 | R18: 0
A19: https://www.facebook.com/groups/hkevdiary/permalink/1712101603536165/ | B19: Samantha Vlog | C19: 六座Model Y L香港發佈 最心痛是來得太遲‍ | D19: 2026/04/01 | G19: 負面 | H19: 失望 | I19: 資訊分享 | J19: 純分享 | K19: 直接相關 | L19: 香港 | M19: Tesla Model Y | N19: null | O19: null | P19: 35 | Q19: 9 | R19: 0
A20: https://www.facebook.com/groups/hkevdiary/permalink/1711782370234755/ | B20: Vena Pa | C20: 啱啱喺灣仔終於都見到佢真身, 已經放咗入showroom。 | D20: 2026/04/01 | G20: 正面 | H20: 期待 | I20: 其他 | J20: 純分享 | K20: 間接相關 | L20: 灣仔 | M20: null | N20: null | O20: null | P20: 193 | Q20: 95 | R20: 0
A21: https://www.facebook.com/groups/hkevdiary/permalink/1711739160239076/ | B21: Anonymous participant | C21: Model YL | D21: 2026/03/31 | F21: https://scontent-lga3-1.xx.fbcdn.net/v/t39.30808-6/658396936_2057371594829457_19252370893683681_n.png?_nc_cat=110&ccb=1-7&_nc_sid=aa7b47&_nc_ohc=RkAZBnQyoLUQ7kNvwFLCoyr&_nc_oc=AdptXyPT9YS1YV07YqxcZhgTxOXzBAhqDZOiWOaBnuSuybeoLgiQu-b-HSb6LbHBer8&_nc_zt=23&_nc_ht=scontent-lga3-1.xx&_nc_gid=YjYLmo2h__kxtM6KYw2fCw&_nc_ss=72289&oh=00_Af4vNanuph66ee5da6QnTm-aLivr7M6bCJNHRr970MTtyw&oe=6A119F7A | G21: 中性 | H21: 陳述 | I21: 其他 | J21: 純分享 | K21: 間接相關 | L21: null | M21: Tesla Model Y | N21: null | O21: null | P21: 47 | Q21: 5 | R21: 0
A22: https://www.facebook.com/groups/hkevdiary/permalink/1710769187002740/ | B22: Samantha Vlog | C22: Model 3 Model Y 有新價錢了 | D22: 2026/03/30 | G22: 中性 | H22: 陳述 | I22: 收費/價錢 | J22: 純分享 | K22: 間接相關 | L22: null | M22: Tesla Model 3, Tesla Model Y | N22: null | O22: null | P22: 24 | Q22: 11 | R22: 0
A23: https://www.facebook.com/groups/hkevdiary/permalink/1710631790349813/ | B23: Lapman Leung | C23: 有無車友用過？快唔快？ | D23: 2026/03/30 | F23: https://scontent-det1-1.xx.fbcdn.net/v/t39.30808-6/658695905_10163203489393387_7295506648678066623_n.jpg?stp=cp6_dst-jpg_p526x296_tt6&_nc_cat=102&ccb=1-7&_nc_sid=aa7b47&_nc_ohc=07O_4QXDzJUQ7kNvwHiBrF5&_nc_oc=AdrUZZAFD1fQQr7rkkUYnXIHRAlpii8vp2MX3OuPc2m5YN1RVpC4LnGT_0zrjy98mUM&_nc_zt=23&_nc_ht=scontent-det1-1.xx&_nc_gid=bsKq4QBhskKBfKXZYfevEA&_nc_ss=72289&oh=00_Af76Bif9QatTV5PksP0zySJO8u6aufgmN-SAvkg0fq66lA&oe=6A11AC4A | G23: 中性 | H23: 疑問 | I23: 疑問/求助 | J23: 求助 | K23: 直接相關 | L23: null | M23: null | N23: null | O23: null | P23: 8 | Q23: 4 | R23: 0
A24: https://www.facebook.com/groups/hkevdiary/permalink/1710014147078244/ | B24: Harry Chan | C24: 無線新聞近期有個節目講電動車維修，訪問一間本地車房做電動車維修，受訪人士姓何，有冇人知道係邊間，請DM | D24: 2026/03/29 | G24: 中性 | H24: 疑問 | I24: 疑問/求助 | J24: 求助 | K24: 間接相關 | L24: null | M24: null | N24: null | O24: null | P24: 5 | Q24: 1 | R24: 0
A25: https://www.facebook.com/groups/hkevdiary/permalink/1710126180400374/ | B25: Anonymous participant | C25: 聽隔離鄰居講，中電可以有電車充電特別優惠電力收費，好似要安裝多一個電錶畀電車用，我就想知道中電會收取幾多錢安裝費 | D25: 2026/03/29 | G25: 中性 | H25: 疑問 | I25: 疑問/求助 | J25: 求助 | K25: 直接相關 | L25: null | M25: null | N25: null | O25: null | P25: 10 | Q25: 30 | R25: 1
A26: https://www.facebook.com/groups/hkevdiary/permalink/1709800520432940/ | B26: Anonymous participant | C26: 大貨 | D26: 2026/03/29 | F26: https://scontent-dfw6-1.xx.fbcdn.net/v/t39.30808-6/657441010_1586589919065369_6783519954386147150_n.png?stp=dst-png_s960x960&_nc_cat=102&ccb=1-7&_nc_sid=aa7b47&_nc_ohc=i2B3LtKPOLUQ7kNvwEdHDzP&_nc_oc=AdpzpXpk-w5vX5Ckqv95ObBuQqBFASdAUxC7Snnaj0mCs3e2Q79ZM-cTqIVhiwr7n0g&_nc_zt=23&_nc_ht=scontent-dfw6-1.xx&_nc_gid=wRmElNe7jwZrNdJhyArfqg&_nc_ss=7c289&oh=00_Af4yC96UQZl0-B8HfNRPDBuCkdABQ-eGTs6Lj_ByYBGT3g&oe=6A117B40 | G26: 中性 | H26: 陳述 | I26: 其他 | J26: 純分享 | K26: 無關 | L26: null | M26: null | N26: null | O26: null | P26: 31 | Q26: 15 | R26: 1
A27: https://www.facebook.com/groups/hkevdiary/permalink/1706258434120482/ | B27: Anonymous participant | C27: 大家點睇呢個驗車報告？ 一位準買家睇中咗一部 2023年 Tesla Model Y，行駛里數大約 46,959 km。外表睇落幾新淨，價錢亦吸引。佢心諗：「二手電動車應該唔會有太大問題啦？」但最後都覺得唔放心，搵咗我哋 Car4HK 上門驗車。 驗車過程：逐項檢查 • 電池系統：容量只剩 56.2 kWh（規格應該有 75 kWh），退化率達 25%。 • 煞車系統：煞車踏板感應器失效，影響再生煞車功能。 • 輪胎狀況：四條輪胎磨損到只剩 0–1 mm，完全冇花紋。 • 冷氣系統：溫度輸出唔穩定，時冷時熱。 專業判斷：上手車主習慣 根據檢測結果，我哋推斷上手車主可能有以下使用模式： • 充電習慣唔理想：電池退化咁快，可能經常用快充，又或者長期充到 100%，令電池壽命大幅縮短。 • 駕駛方式偏激：煞車感應器失效，加上四條輪胎磨到冇花紋，顯示上手車主可能經常急加速、急煞車，甚至長期高速行駛。 • 保養不足：冷氣系統異常，輪胎冇定期更換，反映車主對日常保養唔太上心。 成本風險：潛在黑洞 如果客人真係買咗呢部車，後續維修費用可能要： • 電池更換或維修：HK$150,000+ • 煞車系統維修：HK$4,500+ • 冷氣系統維修：HK$2,000+ • 輪胎更換：HK$8,000+（估算） ➡️ 總計潛在維修費用超過 HK$160,000。 結果：避免中伏 客人聽完檢測報告，即刻打消購買念頭。佢仲同我哋講：「幸好搵咗你哋驗車，否則真係會中伏！」 呢次驗車唔單止幫佢慳返一大筆錢，仲揭示咗上手車主嘅駕駛習慣，令客人更清楚二手電動車背後嘅風險。 | D27: 2026/03/25 | G27: 中性 | H27: 陳述 | I27: 資訊分享 | J27: 廣告 | K27: 直接相關 | L27: null | M27: Tesla Model Y | N27: null | O27: 快充 | P27: 23 | Q27: 22 | R27: 0
A28: https://www.facebook.com/groups/hkevdiary/permalink/1705717037507955/ | B28: Anonymous participant | C28: 大貨 | D28: 2026/03/24 | F28: https://scontent-dfw5-2.xx.fbcdn.net/v/t39.30808-6/656205067_1915168912451522_1005801767426755260_n.webp?stp=cp6_dst-webp_p526x296&_nc_cat=108&ccb=1-7&_nc_sid=aa7b47&_nc_ohc=mDgJz0CXGqgQ7kNvwHWPsFm&_nc_oc=Ado_qxGCigImHSvj1Dv4dt_-qCS5hNPKRWEcApnb90iUbL6-PyYOMgYXYehxdhGrcWc&_nc_zt=23&_nc_ht=scontent-dfw5-2.xx&_nc_gid=wRmElNe7jwZrNdJhyArfqg&_nc_ss=7c289&oh=00_Af5h1Ze4qjlEY0zFeZ-kK_SYB5-Q2uNe-TVJgC7lTwZS4A&oe=6A117AF2 | G28: 中性 | H28: 陳述 | I28: 其他 | J28: 純分享 | K28: 間接相關 | L28: null | M28: null | N28: null | O28: null | P28: 306 | Q28: 77 | R28: 5
A29: https://www.facebook.com/groups/hkevdiary/permalink/1705083357571323/ | B29: Anonymous participant | C29: 所以話錦X不了 | D29: 2026/03/23 | F29: https://scontent-atl3-3.xx.fbcdn.net/v/t39.30808-6/657441005_1235412488803941_4526531031703293568_n.jpg?_nc_cat=110&ccb=1-7&_nc_sid=aa7b47&_nc_ohc=ZMrGbkiPiNUQ7kNvwFwlTUf&_nc_oc=Adoi5QMGo5NwKptsh2f0_Fl3c_5WsC7GA0GajA-NMOxJN2GkMjVgTkVG780-sgXa5kI&_nc_zt=23&_nc_ht=scontent-atl3-3.xx&_nc_gid=yvTUPe6Dh202jN3GLh2M2w&_nc_ss=72289&oh=00_Af6-FxbBmdSXkkZt4YS6pPknzgO6bWyrVJSB_0I0bjEdTQ&oe=6A11ACFD | G29: 負面 | H29: 失望 | I29: 其他 | J29: 純分享 | K29: 直接相關 | L29: null | M29: null | N29: null | O29: null | P29: 84 | Q29: 37 | R29: 1
A30: https://www.facebook.com/groups/hkevdiary/permalink/1700405358039123/ | B30: Samantha Vlog | C30: i3復活了 續航有900公里 | D30: 2026/03/19 | G30: 正面 | H30: 期待 | I30: 資訊分享 | J30: 純分享 | K30: 直接相關 | L30: null | M30: BMW i3 | N30: null | O30: null | P30: 12 | Q30: 2 | R30: 0
A31: https://www.facebook.com/groups/hkevdiary/permalink/1698439864902339/ | B31: Vincent Chan | C31: 【港車北上 歐標充電站地圖 覆蓋全廣東省】 內地歐標充電站已推行一段時間，現時已覆蓋全廣東省，遠至湛江、韶關、潮州等等，站點數量超過2️⃣0️⃣0️⃣個 📌歐標地圖及詳細列表 (含高德地圖連結) https://carparkhero.com/northbound-ev-chargers 更多港車北上資訊👇🏻 1️⃣Tesla港車北上最新資訊 https://bit.ly/3umryI7 2️⃣實時口岸交通情況 https://carparkhero.com/northbound-travel-real-time-traffic 3️⃣港車北上免橋費日子2026 https://carparkhero.com/toll-free-days-2026/ | D31: 2026/03/16 | G31: 中性 | H31: 陳述 | I31: 充電站設施/位置 | J31: 純分享 | K31: 直接相關 | L31: 廣東省,湛江,韶關,潮州 | M31: null | N31: null | O31: 歐標 | P31: 1 | Q31: 0 | R31: 0
A32: https://www.facebook.com/groups/hkevdiary/permalink/1695887905157535/ | B32: Samantha Vlog | C32: 如果仲有一換一嘅話會係HK$327,478 | D32: 2026/03/13 | G32: 中性 | H32: 陳述 | I32: 收費/價錢 | J32: 純分享 | K32: 直接相關 | L32: null | M32: null | N32: null | O32: null | P32: 36 | Q32: 22 | R32: 0
A33: https://www.facebook.com/groups/hkevdiary/permalink/1690909235655402/ | B33: Anonymous participant | C33: 又話差電先要排長龍嘅 | D33: 2026/03/06 | F33: https://scontent-lga3-2.xx.fbcdn.net/v/t39.30808-6/649130633_1222327253445798_6213665013637408395_n.jpg?stp=dst-jpg_p526x296_tt6&_nc_cat=105&ccb=1-7&_nc_sid=aa7b47&_nc_ohc=GQXvCEyGHaMQ7kNvwF8B46T&_nc_oc=AdrZSZqh-eTKff0InfOAUSTkmax7t-xpIqLkIOH7jl6A_7RTtwKaB_-S-bBuNVjfpOY&_nc_zt=23&_nc_ht=scontent-lga3-2.xx&_nc_gid=C-OwyOkQo7UJ4x-TEbh7EQ&_nc_ss=7c289&oh=00_Af4Z3wulTaR0FaDm0Irgud0E-VeRTRTAQoBdlxpyEkvtNw&oe=6A11986B | G33: 負面 | H33: 疑問 | I33: 排隊/打尖/霸位 | J33: 純分享 | K33: 直接相關 | L33: null | M33: null | N33: null | O33: null | P33: 49 | Q33: 28 | R33: 0
A34: https://www.facebook.com/groups/hkevdiary/permalink/1689249342488058/ | B34: Hin Lo | C34: 【2026年2月份電動車首次登記】 2月份出車數字，Tesla憑1,001部首次登記車輛重回第一位，主力車型繼續是Model 3/Y RWD，BYD Hong Kong - Harmony Auto以722部排在第二，第三位是GAC Hong Kong - DangDang，有358部。 四月初再報導大家期待的3月出車數字📈 頭五位型號： 1️⃣TESLA MODEL Y RWD - 504部 2️⃣BYD SEALION 7 – 353部 3️⃣TESLA MODEL 3 RWD - 316部 4️⃣BYD ATTO 2 – 264部 5️⃣GAC AION UT PREMIUM – 228部 *以運輸署登記型號名稱計 | D34: 2026/03/04 | G34: 中性 | H34: 陳述 | I34: 資訊分享 | J34: 純分享 | K34: 間接相關 | L34: null | M34: BYD ATTO 2, Tesla Model Y RWD, Dongfeng Nammi Vigo Pro, Tesla Model 3 RWD, Zeekr 7X Platinum | N34: null | O34: null | P34: 3 | Q34: 0 | R34: 0
A35: https://www.facebook.com/groups/hkevdiary/permalink/1688627129216946/ | B35: Anonymous participant | C35: 30蚊了，實際有幾多折扣? 埋單係咪都係廿蚊一L | D35: 2026/03/03 | F35: https://scontent-lga3-2.xx.fbcdn.net/v/t39.30808-6/645689918_679039758600837_2949160462928120842_n.png?stp=dst-png_p180x540&_nc_cat=101&ccb=1-7&_nc_sid=aa7b47&_nc_ohc=mPK9OQwp7a8Q7kNvwEYtDQ4&_nc_oc=AdolBPXN6DktffJGAB5YDoAgyPsKXAvbOTGNq6pEUaTtJO4hf-J1dS0N_3B9kxN6KKA&_nc_zt=23&_nc_ht=scontent-lga3-2.xx&_nc_gid=LBhGUaI7-OEdi07JpO-gQQ&_nc_ss=72289&oh=00_Af73SkG0u1bn1_yh716rmYPC___rHRC0fNqGFgJS1ypv9g&oe=6A118E1B | G35: 中性 | H35: 疑問 | I35: 疑問/求助 | J35: 求助 | K35: 無關 | L35: null | M35: null | N35: null | O35: null | P35: 12 | Q35: 4 | R35: 0
A36: https://www.facebook.com/groups/hkevdiary/permalink/1686328016113524/ | B36: Samuel Ho | C36: 第一次見，1003km／hr，勁喎！ | D36: 2026/03/01 | F36: https://scontent-lga3-2.xx.fbcdn.net/v/t39.30808-6/645130537_10162703659581482_9185019384392126727_n.jpg?stp=dst-jpg_p526x296_tt6&_nc_cat=107&ccb=1-7&_nc_sid=aa7b47&_nc_ohc=m0R8mt36gDsQ7kNvwEbQ0IE&_nc_oc=Ado_t5QIPU4ZWZFPEx7mJV_B6RDixHmlKmRdzQA1Ukn_oVBvuihKszQ3T0Tezy-PSEM&_nc_zt=23&_nc_ht=scontent-lga3-2.xx&_nc_gid=LBhGUaI7-OEdi07JpO-gQQ&_nc_ss=72289&oh=00_Af6p4bWbs5Peyj8ZKqocbz1hJFqbKzlMwkE6_m5jF_AeOA&oe=6A11AF71 | G36: 正面 | H36: 開心 | I36: 充電速度 | J36: 純分享 | K36: 直接相關 | L36: null | M36: null | N36: null | O36: null | P36: 41 | Q36: 11 | R36: 1
A37: https://www.facebook.com/groups/hkevdiary/permalink/1683411489738510/ | B37: carparkhero 全方位停車場及電動車充電站資訊 | C37: ➡️Tesla Model 3 RWD 稅前價 HK$249,000 一換一 HK$249,000 冇優惠 HK$403,140‼️ ➡️Tesla Model Y RWD 稅前價 HK$282,800 一換一 HK$293,508 冇優惠 HK$466,008‼️ ➡️BYD Sealion 7 Dynamic 稅前價 HK$218,000 一換一 HK$218,000 冇優惠 HK$345,480‼️ ➡️GAC AION ES 稅前價 HK$130,000 一換一 HK$130,000 冇優惠 HK$189,800‼️ | D37: 2026/02/25 | G37: 中性 | H37: 陳述 | I37: 其他 | J37: 純分享 | K37: 間接相關 | L37: null | M37: Tesla Model 3 RWD, Tesla Model Y RWD, BYD Sealion 7 Dynamic, GAC AION ES | N37: null | O37: null | P37: 1 | Q37: 4 | R37: 1
A38: https://www.facebook.com/groups/hkevdiary/permalink/1683313466414979/ | B38: Samantha Vlog | C38: 今日會有好多人訂購電動車？ | D38: 2026/02/25 | G38: 中性 | H38: 疑問 | I38: 疑問/求助 | J38: 求助 | K38: 間接相關 | L38: null | M38: null | N38: null | O38: null | P38: 7 | Q38: 13 | R38: 0
A39: https://www.facebook.com/groups/hkevdiary/permalink/1683279969751662/ | B39: Samantha Vlog | C39: 財政預算案：電動私家車首次登記稅的寬減安排不會繼續，包括一換一 | D39: 2026/02/25 | G39: 中性 | H39: 陳述 | I39: 其他 | J39: null | K39: 無關 | L39: null | M39: null | N39: null | O39: null | P39: 25 | Q39: 4 | R39: 0
A40: https://www.facebook.com/groups/hkevdiary/permalink/1681691876577138/ | B40: Anonymous participant | C40: 繼續為電動車提供優惠，有利於對接國家規劃，及助中國發展電動車行業 | D40: 2026/02/23 | G40: 正面 | H40: 滿意 | I40: 其他 | J40: 純分享 | K40: 直接相關 | L40: null | M40: null | N40: null | O40: null | P40: 2 | Q40: 0 | R40: 0
A41: https://www.facebook.com/groups/hkevdiary/permalink/1681625696583756/ | B41: Andrew Lin | C41: Tesla Model Y L（6人座）已在澳洲獲准銷售！！即是右軚Model Y L 應該會開始大量生產. ROVER 網站現已將變體型號 YL5NDB 列入核准車款類型。希望香港很快也能獲准銷售！ | D41: 2026/02/23 | F41: https://scontent-lga3-2.xx.fbcdn.net/v/t39.30808-6/638436247_10117762763865728_293750861674675188_n.jpg?stp=dst-jpg_p526x296_tt6&_nc_cat=109&ccb=1-7&_nc_sid=aa7b47&_nc_ohc=55_pytJIf-8Q7kNvwEARXB3&_nc_oc=AdqLM40vTKAyfnWGuIjpJmJkxVazDONneqEZFTarAejPkVxq8UxmpLd4OmiFLufC6M8&_nc_zt=23&_nc_ht=scontent-lga3-2.xx&_nc_gid=czEyMNTl4KWxVh8CYQoUXg&_nc_ss=72289&oh=00_Af625vI2ZBlqsivwp6uzxUxXpzSR_xUZU37pFi8J6cwn6w&oe=6A11869F | G41: 正面 | H41: 期待 | I41: 資訊分享 | J41: 純分享 | K41: 間接相關 | L41: null | M41: Tesla Model Y | N41: null | O41: null | P41: 101 | Q41: 35 | R41: 0
A42: https://www.facebook.com/groups/hkevdiary/permalink/1681084346637891/ | B42: Samantha Vlog | C42: Model 3 LR 續航又升級 Model 3 LR 629➡️660➡️**715km** 其他型號之前都提升過續航 Model 3 RWD 513➡️520➡️**534km** Model 3 Performance 528➡️**571km** Model Y RWD 466➡️**488km** Model Y LR 551➡️**629km** | D42: 2026/02/22 | F42: https://scontent-lga3-3.xx.fbcdn.net/v/t39.30808-6/637083629_1506210444838686_2828846513470509742_n.jpg?_nc_cat=101&ccb=1-7&_nc_sid=aa7b47&_nc_ohc=S513io6obdcQ7kNvwEBvEdL&_nc_oc=Adrx6tT1_062IUhly5TY4jIIYLsfsKCGvqsaMxFvGZ_IaaMQBhLF-gKXDhJlPEOkcW8&_nc_zt=23&_nc_ht=scontent-lga3-3.xx&_nc_gid=czEyMNTl4KWxVh8CYQoUXg&_nc_ss=72289&oh=00_Af5XyzTNfYC4vvm1wKnown8QxhTbguY7A2LD4ZBebX4KMg&oe=6A1179E3 | G42: 中性 | H42: 陳述 | I42: 資訊分享 | J42: 純分享 | K42: 直接相關 | L42: null | M42: Tesla Model 3, Tesla Model Y | N42: null | O42: null | P42: 66 | Q42: 32 | R42: 0
A43: https://www.facebook.com/groups/hkevdiary/permalink/1679949500084709/ | B43: Vincent Chan | C43: https://www.carparkhero.com/label/no-parking-fee-ev-charging-station/?fbclid=IwY2xjawR6DKlleHRuA2FlbQIxMABicmlkETE2ZHBFamR6bUhmalU0STZ6c3J0YwZhcHBfaWQQMjIyMDM5MTc4ODIwMDg5MgABHvuUAUTE5xIHmmF5-ns6-Eqf-Hyl0HSHU7MKY0R-iMbagorG__-mmqQCo4HJ_aem_VMPbNcyP3HXjozYBLzuO-w#google_vignette | D43: 2026/02/21 | G43: 中性 | H43: 陳述 | I43: 充電站設施/位置 | J43: 純分享 | K43: 直接相關 | L43: 香港 | M43: null | N43: null | O43: null | P43: 2 | Q43: 3 | R43: 0
A44: https://www.facebook.com/groups/hkevdiary/permalink/1679798096766516/ | B44: Anonymous participant | C44: 仲有冇一換一，下星期三就知 | D44: 2026/02/21 | G44: 中性 | H44: 疑問 | I44: 疑問/求助 | J44: 求助 | K44: 間接相關 | L44: null | M44: null | N44: null | O44: null | P44: 3 | Q44: 0 | R44: 0
A45: https://www.facebook.com/groups/hkevdiary/permalink/1679290770150582/ | B45: APEX Mobile | C45: 王者歸來，Mercedes Benz 今次純電車，應該可以佔香港銷量一席位。 https://www.facebook.com/share/v/1ZvDbAwQvo/ | D45: 2026/02/20 | G45: 正面 | H45: 期待 | I45: 資訊分享 | J45: 純分享 | K45: 直接相關 | L45: null | M45: null | N45: null | O45: null | P45: 5 | Q45: 1 | R45: 0
A46: https://www.facebook.com/groups/hkevdiary/permalink/1678885793524413/ | B46: Vincent Chan | C46: 由今日2月20日起，香園圍邊境管制站公眾停車場電動車充電需繳付每度電kWh➡️$2.5 | D46: 2026/02/19 | G46: 中性 | H46: 陳述 | I46: 充電站設施/位置 | J46: 純分享 | K46: 無關 | L46: 香園圍邊境管制站 | M46: null | N46: null | O46: null | P46: 5 | Q46: 0 | R46: 0
A47: https://www.facebook.com/groups/hkevdiary/permalink/1676595320420127/ | B47: MemorableFalcon5501 | C47: ￼ 政府資助屋苑安充電樁￼而家大約￼幾多錢？￼見到好多￼充電樁￼牌子都聽都未聽過￼￼，￼有冇咩鑊氣？ | D47: 2026/02/17 | G47: 中性 | H47: 疑問 | I47: 疑問/求助 | J47: 求助 | K47: 直接相關 | L47: null | M47: null | N47: null | O47: null | P47: 1 | Q47: 1 | R47: 0
A48: https://www.facebook.com/groups/hkevdiary/permalink/1675535290526130/ | B48: Sandra Yuen | C48: 而家超充見好多新都有優惠價。 平均係咪都2.2- 2.6/ kWh ? 我喺觀塘見好多洗車屋改裝後價錢都平。 不過呢啲舖頭喺地圖好似都好似仲未見到有。 | D48: 2026/02/16 | G48: 中性 | H48: 疑問 | I48: 收費/價錢 | J48: 求助 | K48: 直接相關 | L48: 觀塘 | M48: null | N48: null | O48: 超充 | P48: 18 | Q48: 11 | R48: 0
A49: https://www.facebook.com/groups/hkevdiary/permalink/1672247764188216/ | B49: Serena Cheung | C49: 請問Tesla所有充電站係咪都已經開放俾其他車充電？ | D49: 2026/02/12 | G49: 中性 | H49: 疑問 | I49: 疑問/求助 | J49: 求助 | K49: 直接相關 | L49: null | M49: null | N49: Tesla | O49: null | P49: 10 | Q49: 11 | R49: 0
A50: https://www.facebook.com/groups/hkevdiary/permalink/1668291631250496/ | B50: Hin Lo | D50: 2026/02/07 | G50: 中性 | H50: 陳述 | I50: 資訊分享 | J50: 純分享 | K50: 間接相關 | L50: null | M50: BYD ATTO 2, Tesla Model Y RWD, Dongfeng Nammi Vigo Pro, Tesla Model 3 RWD, Zeekr 7X Platinum | N50: null | O50: null | P50: 16 | Q50: 8 | R50: 0
A51: https://www.facebook.com/groups/hkevdiary/permalink/1663011711778488/ | B51: Kin Lam Ma | C51: 幾耐先至換摩打油 | D51: 2026/02/01 | G51: 中性 | H51: 疑問 | I51: 疑問/求助 | J51: 求助 | K51: 無關 | L51: null | M51: null | N51: null | O51: null | P51: 3 | Q51: 8 | R51: 0
A52: https://www.facebook.com/groups/hkevdiary/permalink/1658894968856829/ | B52: Anonymous participant | C52: 請教ching 入左100蚊充電費，充左51蚊後停止充電，開始收取我逾時收費 請問係唔係合理嗎？ | D52: 2026/01/27 | F52: https://scontent-bos5-1.xx.fbcdn.net/v/t39.30808-6/621997927_1183450587208314_3314015166691273803_n.jpg?stp=cp6_dst-jpg_s565x565_tt6&_nc_cat=107&ccb=1-7&_nc_sid=aa7b47&_nc_ohc=hO6RaceRMjwQ7kNvwH7cfj7&_nc_oc=Adosgsu-FU6kJRhPc-EBzmV-tUE3JsoUATVMTb0tApYClE3rq-VpYRFyjeDvvt62pWw&_nc_zt=23&_nc_ht=scontent-bos5-1.xx&_nc_gid=MwFVTEznOXKQmDcppOXODg&_nc_ss=7c289&oh=00_Af4OQl2_osjRzo3hjeJl05lXMCYl3zxhFBg_yI5BEJ-JGA&oe=6A11A85F | G52: 負面 | H52: 疑問 | I52: 收費/價錢 | J52: 求助 | K52: 直接相關 | L52: null | M52: null | N52: null | O52: null | P52: 12 | Q52: 31 | R52: 0
A53: https://www.facebook.com/groups/hkevdiary/permalink/1656821772397482/ | B53: WhitePapaya7967 | C53: The Point 充電，愈嚟愈運吉，一開始話 1500一節，一加加到 2500，原本有『60KWH』，依家校少三分一，出到40 KWH，已求神拜佛… | D53: 2026/01/27 | G53: 負面 | H53: 生氣 | I53: 收費/價錢 | J53: 純分享 | K53: 直接相關 | L53: null | M53: null | N53: ThePoint | O53: null | P53: 39 | Q53: 55 | R53: 0
A54: https://www.facebook.com/groups/hkevdiary/permalink/1656035302476129/ | B54: Mike Yeung | C54: 請問各C兄, 充完電後, 可否睇到車內屏幕已充了多小Kwh！？ 好多充電站只睇到Apps 顯示,實質不是充了該算字的電！ | D54: 2026/01/24 | G54: 中性 | H54: 疑問 | I54: 疑問/求助 | J54: 求助 | K54: 直接相關 | L54: null | M54: null | N54: null | O54: null | P54: 1 | Q54: 7 | R54: 0
A55: https://www.facebook.com/groups/hkevdiary/permalink/1649798796433113/ | B55: Samantha Vlog | C55: Model Y新配置 - 16寸2K Mon - 黑色布料頂篷 (not麂皮) | D55: 2026/01/16 | G55: 中性 | H55: 陳述 | I55: 其他 | J55: 純分享 | K55: 間接相關 | L55: null | M55: Tesla Model Y | N55: null | O55: null | P55: 70 | Q55: 11 | R55: 0
A56: https://www.facebook.com/groups/hkevdiary/permalink/1648634783216181/ | B56: Dicky Irq | C56: 唔知有冇師兄/姊用緊、剛剛收到（2025 Model 3 Highland 神秘灰） | D56: 2026/01/15 | F56: https://scontent-ord5-2.xx.fbcdn.net/v/t39.30808-6/615197148_10230626563983048_1743199582077078760_n.jpg?stp=dst-jpg_p526x296_tt6&_nc_cat=104&ccb=1-7&_nc_sid=aa7b47&_nc_ohc=Gr8nDufbdqUQ7kNvwH7RNYe&_nc_oc=AdpW4oAqxSUHZqE3alUmV7OsGO9_3zmR-CTXJa3L2rf26JB_ksvRSZBUsFQOY0B6VBA&_nc_zt=23&_nc_ht=scontent-ord5-2.xx&_nc_gid=40fzrQC5Xa9Lmrh7s13wWA&_nc_ss=72289&oh=00_Af7LL-JEDKniNYQjTnMwPBufq5lfmewl-ZtUAIqMX673Sw&oe=6A11A677 | G56: 中性 | H56: 疑問 | I56: 疑問/求助 | J56: 求助 | K56: 直接相關 | L56: null | M56: 2025 Model 3 Highland | N56: null | O56: null | P56: 3 | Q56: 0 | R56: 0
A57: https://www.facebook.com/groups/hkevdiary/permalink/1646907713388888/ | B57: Mike Yeung | C57: 請問Mifa9除了返英之傑, 仲可係邊度換迫力油！？ | D57: 2026/01/12 | G57: 中性 | H57: 疑問 | I57: 疑問/求助 | J57: 求助 | K57: 間接相關 | L57: null | M57: Mifa9 | N57: null | O57: null | P57: 0 | Q57: 9 | R57: 0
A58: https://www.facebook.com/groups/hkevdiary/permalink/1644875343592125/ | B58: Chloe Fa | C58: 請問2024 Mercedes EQS 500同2025 Maxus Mifa 9，大家會點揀？（一家三口有小朋友坐，本來想買Mifa9，但突然見到平治清貨做緊大減價，兩架車價錢差距小咗。）唔該先 | D58: 2026/01/09 | G58: 中性 | H58: 疑問 | I58: 疑問/求助 | J58: 求助 | K58: 直接相關 | L58: null | M58: Mercedes EQS 500, Maxus Mifa 9 | N58: null | O58: null | P58: 5 | Q58: 24 | R58: 0
A59: https://www.facebook.com/groups/hkevdiary/permalink/1644007120345614/ | B59: Hin Lo | D59: 2026/01/08 | G59: 中性 | H59: 陳述 | I59: 資訊分享 | J59: 純分享 | K59: 間接相關 | L59: null | M59: BYD ATTO 2, Tesla Model Y RWD, Dongfeng Nammi Vigo Pro, Tesla Model 3 RWD, Zeekr 7X Platinum | N59: null | O59: null | P59: 4 | Q59: 7 | R59: 0
A60: https://www.facebook.com/groups/hkevdiary/permalink/1638909477522045/ | B60: 陳傲輝 | C60: 咁大架車，1度行6公里，為起3毫，堅唔堅呀？ | D60: 2026/01/01 | G60: 中性 | H60: 疑問 | I60: 收費/價錢 | J60: 求助 | K60: 直接相關 | L60: null | M60: null | N60: null | O60: null | P60: 3 | Q60: 4 | R60: 0
A61: https://www.facebook.com/groups/hkevdiary/permalink/1634540501292276/ | B61: 昱希電車空間 珠海店 專業電改貼膜中心 | C61: Tesla港車北上 歐標CCS2超充Supercharger | D61: 2025/12/26 | G61: 中性 | H61: 陳述 | I61: 資訊分享 | J61: 純分享 | K61: 直接相關 | L61: null | M61: null | N61: Tesla Supercharger | O61: 超充, CCS2 | P61: 3 | Q61: 0 | R61: 1
A62: https://www.facebook.com/groups/hkevdiary/permalink/1633886988024294/ | B62: Chan Fai | C62: 各位师兄聖誕快樂啊， 想問下：有冇人聽講過外置副電池？ 最近見到有啲续航问题電車可以额外加裝副電池，同原廠電池並聯用嚟增程，就唔洗郁原電池 想問下大家有冇了解過？ 安全性、效果、對保養影響等等，大家點睇？ 純討論，想聽下大家嘅意見～ | D62: 2025/12/25 | G62: 中性 | H62: 疑問 | I62: 安裝/硬件/技術 | J62: 求助 | K62: 直接相關 | L62: null | M62: null | N62: null | O62: null | P62: 0 | Q62: 2 | R62: 0
A63: https://www.facebook.com/groups/hkevdiary/permalink/1633156474764012/ | B63: Billy Cheng | C63: 我準備買電車、請問有什麼要留意的地方？ 還有、電車第一年保險、是否車行包？ | D63: 2025/12/24 | G63: 中性 | H63: 疑問 | I63: 疑問/求助 | J63: 求助 | K63: 直接相關 | L63: null | M63: null | N63: null | O63: null | P63: 0 | Q63: 6 | R63: 0
A64: https://www.facebook.com/groups/hkevdiary/permalink/1632180268194966/ | B64: Fai Ng | C64: 請教各位用家, 新界及港島區, 有無類似九龍區大昌行咁嘅規模的充電設施？ 謝 | D64: 2025/12/23 | G64: 中性 | H64: 疑問 | I64: 充電站設施/位置 | J64: 求助 | K64: 直接相關 | L64: 新界, 港島區, 九龍區, 大昌行 | M64: null | N64: null | O64: null | P64: 0 | Q64: 3 | R64: 0
A65: https://www.facebook.com/groups/hkevdiary/permalink/1629536375126022/ | B65: Samantha Vlog | C65: 香港廠終於有空調薰蒸同清洗散熱器 | D65: 2025/12/19 | G65: 正面 | H65: 開心 | I65: 其他 | J65: 純分享 | K65: 無關 | L65: null | M65: null | N65: null | O65: null | P65: 64 | Q65: 9 | R65: 1
A66: https://www.facebook.com/groups/hkevdiary/permalink/1627862918626701/ | B66: Ricky Chen | C66: 又黎計下收到Wall Connector最新充電費用 上次3304公里到而家行左4640公里 今次電費$302 / 充左258度電 = 1度電$1.171 今次行左1336公里 / 258度電 = 1度電5.2公里 $302 / 1336公里 = 1公里$0.226 | D66: 2025/12/18 | F66: https://scontent.fluk1-1.fna.fbcdn.net/v/t39.30808-6/599640550_10162476995733741_8368700632565195183_n.jpg?_nc_cat=103&ccb=1-7&_nc_sid=aa7b47&_nc_ohc=4F3lecbC8usQ7kNvwEEfUxs&_nc_oc=AdrcjoUEZlkhl8i_VL-qmCYQ5cdVLIgILtMjaJPu5BPLUo562Ws8YExc38LQwMrYJWE&_nc_zt=23&_nc_ht=scontent.fluk1-1.fna&_nc_gid=ayvO0ksI-xzPlkHHNQuQ3g&_nc_ss=72289&oh=00_Af7MDGOgxERIIYxL9o0umf5WN_Ax8qj8YLPXHnWSYyiiIQ&oe=6A1196AA | G66: 中性 | H66: 陳述 | I66: 收費/價錢 | J66: 純分享 | K66: 直接相關 | L66: null | M66: null | N66: null | O66: null | P66: 11 | Q66: 0 | R66: 0
A67: https://www.facebook.com/groups/hkevdiary/permalink/1627232342023092/ | B67: Edwin Chi Ngai Chan | C67: 今日update 完之後 Jump start開到門，但着不到 落地一個月返廠 ￼翌日更新： 師傅8:18am 已經叫醒部車返去上一個version software，之後幫我update software ，結論是，update 途中hang 機。￼￼￼ | D67: 2025/12/16 | F67: https://scontent-sjc3-1.xx.fbcdn.net/v/t39.30808-6/600236641_10163551997267173_2184817830389719672_n.jpg?stp=cp6_dst-jpg_s720x720_tt6&_nc_cat=106&ccb=1-7&_nc_sid=aa7b47&_nc_ohc=SM7zBtMarYoQ7kNvwGGyDc6&_nc_oc=AdpIxTeC4eQhqjXg6Z96rhc3z0C1YT6rqRsOvw0jwO0xCA9CpTYuvtYgpL7m5ahfcRM&_nc_zt=23&_nc_ht=scontent-sjc3-1.xx&_nc_gid=pHPVb63jlT-JyrXkHjfsTw&_nc_ss=72289&oh=00_Af7UOSG46_YtsbwD2gr9MILp_iCbuDoFES0Pnxuqm-KNng&oe=6A11A2F7 | G67: 負面 | H67: 失望 | I67: 安裝/硬件/技術 | J67: 純分享 | K67: 間接相關 | L67: null | M67: null | N67: null | O67: null | P67: 111 | Q67: 34 | R67: 0
A68: https://www.facebook.com/groups/hkevdiary/permalink/1626527372093589/ | B68: Samantha Vlog | C68: 特斯拉塗裝下載區 https://drive.google.com/drive/folders/18R9O-mVUnSG9_hS5rVi6bjore_RU1Ahy | D68: 2025/12/15 | G68: 中性 | H68: 陳述 | I68: 其他 | J68: 純分享 | K68: 間接相關 | L68: null | M68: null | N68: null | O68: null | P68: 17 | Q68: 1 | R68: 2
A69: https://www.facebook.com/groups/hkevdiary/permalink/1625916815487978/ | B69: Anonymous participant | C69: 而家原廠都興用卡鉗罩？Mazda 6e，東風eπ007 | D69: 2025/12/14 | G69: 中性 | H69: 疑問 | I69: 其他 | J69: 求助 | K69: 間接相關 | L69: null | M69: Mazda 6e, 東風eπ007 | N69: null | O69: null | P69: 6 | Q69: 4 | R69: 0
A70: https://www.facebook.com/groups/hkevdiary/permalink/1625243032222023/ | B70: Samantha Vlog | C70: Model Y L將於歐洲開售？ | D70: 2025/12/13 | F70: https://scontent-atl3-1.xx.fbcdn.net/v/t39.30808-6/600287469_1443250454468019_7947907633003235315_n.jpg?stp=cp6_dst-jpg_p526x296_tt6&_nc_cat=105&ccb=1-7&_nc_sid=aa7b47&_nc_ohc=khZQxySlxK4Q7kNvwGNOz1c&_nc_oc=AdrOx0vp3IRh4KB-5cE5t27-aFtKQ7Nz-8RrvQ4SaQfYt2nmCNNXuXGrmhuveDxw-Ew&_nc_zt=23&_nc_ht=scontent-atl3-1.xx&_nc_gid=T2fLI8CTSqAb5JsR26VraQ&_nc_ss=72289&oh=00_Af58sHz3vFr0_fBQmQlxcXWGqDB-X8oJUqJZd9uDPiQkJg&oe=6A117ACE | G70: 中性 | H70: 疑問 | I70: 其他 | J70: 求助 | K70: 間接相關 | L70: null | M70: Model Y L | N70: null | O70: null | P70: 29 | Q70: 4 | R70: 0
A71: https://www.facebook.com/groups/hkevdiary/permalink/1624843035595356/ | B71: Vincent Chan | C71: 免費嘅中電充電站已經所剩無幾 | D71: 2025/12/13 | G71: 負面 | H71: 失望 | I71: 充電站設施/位置 | J71: 純分享 | K71: 直接相關 | L71: null | M71: null | N71: 中電 | O71: null | P71: 4 | Q71: 1 | R71: 0
A72: https://www.facebook.com/groups/hkevdiary/permalink/1624236598989333/ | B72: Anonymous participant | C72: 又打飛機 | D72: 2025/12/12 | F72: https://scontent-atl3-2.xx.fbcdn.net/v/t39.30808-6/597554096_825981936948281_8827068067625018338_n.jpg?stp=cp6_dst-jpg_s720x720_tt6&_nc_cat=104&ccb=1-7&_nc_sid=aa7b47&_nc_ohc=uC2tNHS6Qk4Q7kNvwFWL-iX&_nc_oc=AdrRzw8wRofMhheiYbGJQA5qEBEJwNoQTY__e7R7F7QeqVRdqgnXFDynLR0enIoNWnI&_nc_zt=23&_nc_ht=scontent-atl3-2.xx&_nc_gid=T2fLI8CTSqAb5JsR26VraQ&_nc_ss=72289&oh=00_Af4-oZqU1RPGrkRo5C0zMe7PvZhKcuLlJaD9hHD9S3It3g&oe=6A117F2C | G72: 負面 | H72: 失望 | I72: 其他 | J72: 純分享 | K72: 無關 | L72: null | M72: null | N72: null | O72: null | P72: 2 | Q72: 1 | R72: 0
A73: https://www.facebook.com/groups/hkevdiary/permalink/1621355325944127/ | B73: Anonymous participant | C73: 討論一下，尋找意見 預算15-22萬 想本身架舊車換電車 新車 或 二手 不限 Tesla / 大陸車不限 SUV / 房車 不限 7人車不考慮 無固定充電位 70% 時間一個人用 30% 時間四人（其中兩張car seat) 虛心請教，大家會選擇咩車？ | D73: 2025/12/08 | G73: 中性 | H73: 疑問 | I73: 疑問/求助 | J73: 求助 | K73: 直接相關 | L73: null | M73: null | N73: null | O73: null | P73: 2 | Q73: 49 | R73: 0
A74: https://www.facebook.com/groups/hkevdiary/permalink/1621310709281922/ | B74: Samantha Vlog | C74: 港版Mazda 6e純電房車規格 一換一意向價26萬？ | D74: 2025/12/08 | G74: 中性 | H74: 疑問 | I74: 資訊分享 | J74: 純分享 | K74: 直接相關 | L74: null | M74: Mazda 6e | N74: null | O74: null | P74: 49 | Q74: 16 | R74: 0
A75: https://www.facebook.com/groups/hkevdiary/permalink/1620793576000302/ | B75: Anonymous participant | C75: 想問吓揸電動車有啲咩app係必須？ | D75: 2025/12/07 | G75: 中性 | H75: 疑問 | I75: 疑問/求助 | J75: 求助 | K75: 直接相關 | L75: null | M75: null | N75: null | O75: null | P75: 4 | Q75: 8 | R75: 0
A76: https://www.facebook.com/groups/hkevdiary/permalink/1619726322773694/ | B76: Anonymous participant | C76: # 終於換了心目中最想要嘅Yoke軚 | D76: 2025/12/06 | F76: https://scontent-ord5-3.xx.fbcdn.net/v/t39.30808-6/591844401_1188112649409019_8925806442301649252_n.png?_nc_cat=109&ccb=1-7&_nc_sid=aa7b47&_nc_ohc=BWiTSvHZkowQ7kNvwEHbRMs&_nc_oc=AdoZQLW6ffYabmAGRa5-SyrsoG61DgWJcUNVrjSkw9DkUbYGzBl4r1tl45hfn3acYEU&_nc_zt=23&_nc_ht=scontent-ord5-3.xx&_nc_gid=MrV0c0krOSr7PRsEdjVXTw&_nc_ss=72289&oh=00_Af64ktdsvaw45BlU5GkqNOrDaGN9aOvRI9els5tBGdvlHg&oe=6A11A547 | G76: 正面 | H76: 開心 | I76: 安裝/硬件/技術 | J76: 純分享 | K76: 間接相關 | L76: null | M76: null | N76: null | O76: null | P76: 35 | Q76: 19 | R76: 0
A77: https://www.facebook.com/groups/hkevdiary/permalink/1619512716128388/ | B77: Wasabi_Mouse | C77: 新手一問： 貼轉色膜後需要通知利寶更新資料嗎? | D77: 2025/12/06 | G77: 中性 | H77: 疑問 | I77: 疑問/求助 | J77: 求助 | K77: 無關 | L77: null | M77: null | N77: null | O77: null | P77: 1 | Q77: 1 | R77: 0
A78: https://www.facebook.com/groups/hkevdiary/permalink/1618480862898240/ | B78: Hin Lo | D78: 2025/12/04 | G78: 中性 | H78: 陳述 | I78: 資訊分享 | J78: 純分享 | K78: 間接相關 | L78: null | M78: BYD ATTO 2, Tesla Model Y RWD, Dongfeng Nammi Vigo Pro, Tesla Model 3 RWD, Zeekr 7X Platinum | N78: null | O78: null | P78: 15 | Q78: 6 | R78: 1
A79: https://www.facebook.com/groups/hkevdiary/permalink/1617951862951140/ | B79: Jackson Lai | C79: 今日响tesla珠海板噴中心有官方貼膜。由4xxx-8xxx睇符品牌。 另外，可以改指揮燈，3500人仔 | D79: 2025/12/03 | F79: https://scontent-lga3-3.xx.fbcdn.net/v/t39.30808-6/594962338_10162553605374563_2182084687929569982_n.jpg?stp=dst-jpg_p526x296_tt6&_nc_cat=106&ccb=1-7&_nc_sid=aa7b47&_nc_ohc=4nPu9mGIgogQ7kNvwE-w8J4&_nc_oc=AdqrvLzcJUfB3SVB_-AkG1NGC4gv8C2NLIPnA4D9cwg7Uf2OexrmXYZorMW4NGVk1ic&_nc_zt=23&_nc_ht=scontent-lga3-3.xx&_nc_gid=lteR017OtabmMR0PdEvK8Q&_nc_ss=72289&oh=00_Af4PBx_B8l9mPoWStUli5vuu_fp3pI-pl9POuNEBy45c2Q&oe=6A11A95D | G79: 中性 | H79: 陳述 | I79: 其他 | J79: 純分享 | K79: 間接相關 | L79: 珠海板噴中心 | M79: Tesla | N79: null | O79: null | P79: 87 | Q79: 43 | R79: 6
A80: https://www.facebook.com/groups/hkevdiary/permalink/1617568272989499/ | B80: Edwin Chi Ngai Chan | C80: 最近這幾個月出Tesla gen 3 charger 部份同一個問題，New Gen 3 對應所有old model 3/S/X/Y 其他品牌都冇問題，唯一就是對 new Y new 3 鎖唔實，解決方法就係將左邊個窿開大。 另外所有新裝的充電器已經全面開放WiFi password，一經發現你改setting ，void warranty | D80: 2025/12/03 | F80: https://scontent-lga3-2.xx.fbcdn.net/v/t39.30808-6/592272927_10163494964347173_3892714623316118053_n.jpg?stp=dst-jpg_p526x296_tt6&_nc_cat=100&ccb=1-7&_nc_sid=aa7b47&_nc_ohc=E1VFXm4N5msQ7kNvwFIKA4g&_nc_oc=AdoiCSlFtOcTPtakPQqBuN5QrGdUM8vh-jbpkJ6Hr1DFD2yx5xPI3xHPy9xbZHBg_Ws&_nc_zt=23&_nc_ht=scontent-lga3-2.xx&_nc_gid=lteR017OtabmMR0PdEvK8Q&_nc_ss=72289&oh=00_Af7oivn_pzupaqN3VObBTxxqO01yXc-JlU-Eji-89vHwxg&oe=6A1193C1 | G80: 中性 | H80: 陳述 | I80: 安裝/硬件/技術 | J80: 純分享 | K80: 直接相關 | L80: null | M80: Tesla Model 3, Tesla Model Y, Tesla Model S, Tesla Model X | N80: null | O80: null | P80: 14 | Q80: 8 | R80: 0
A81: https://www.facebook.com/groups/hkevdiary/permalink/1617083653037961/ | B81: Samantha Vlog | C81: 經常有人問點解Model 3/Y車機顯示嘅100%公里數唔係官網個WLTP數字，車機嗰個數喺EPA標準，標準唔同，數字當然唔會一樣 就算俾你顯示返WLTP個數字大啲開心啲，實際行車個數字咪又係跌得快啲，反而EPA個數細啲，跌得仲冇咁快，仲貼近實際 都係建議大家用%，或者唔駛太在意點解唔係顯示WLTP條數 | D81: 2025/12/02 | G81: 中性 | H81: 陳述 | I81: 資訊分享 | J81: 純分享 | K81: 直接相關 | L81: null | M81: Tesla Model 3/Y | N81: null | O81: null | P81: 49 | Q81: 5 | R81: 2
A82: https://www.facebook.com/groups/hkevdiary/permalink/1616549123091414/ | B82: Samantha Vlog | C82: # Tesla 港車北上「斷網」風波現曙光 早前鬧得熱烘烘的 Tesla Model 3/Y 「港車北上」斷網風波，終於迎來突破性轉機！一眾苦主經歷近半個月無法遙控開冷氣、解鎖的「單機」日子後，資深科技界人士、Z CAM 首席執行官盧健生（Kinson Loo）帶來好消息，確認相關服務正逐步恢復，令一眾車主放下心頭大石。 Kinson 透露，收到 Tesla 客服主動致電通知，確認廠方正積極處理跨境數據連接失效的問題。據客服解釋，修復工作目前正分批進行中。Kinson 表示：「有啲已經正常返（我架得），有啲仲未。」他親身測試後，確認其座駕的網絡連接已回復正常，意味著早前因韌體更新或合規調整而導致的功能癱瘓，並非永久性的「閹割」，各項智能功能終於「復活」。 相比起早前被客服一句「有訊號係你好彩」激到一肚氣，Kinson 今次對 Tesla 的處理態度給予高度評價。他直言：「Tesla 肯聽客戶意見，肯改，大讚。」 | D82: 2025/12/01 | F82: https://scontent-phl2-1.xx.fbcdn.net/v/t39.30808-6/591955303_1432919915501073_2143096520252175279_n.jpg?stp=dst-jpg_s640x640_tt6&_nc_cat=111&ccb=1-7&_nc_sid=aa7b47&_nc_ohc=1HAbpXHKCE0Q7kNvwEs5vQf&_nc_oc=Adr3MfNnt-0df6wmVdyHXZqcIn-73XPAWF00Kmpn3Hm2WFEgw3qzdZhDbA-aMQH5NcM&_nc_zt=23&_nc_ht=scontent-phl2-1.xx&_nc_gid=BZu96PLbiXik_HFoeqY6Yw&_nc_ss=72289&oh=00_Af540l338xLoNBrNL7R3aJFqoua2TUbT8el_ArlI45Lhhg&oe=6A1196A5 | G82: 正面 | H82: 滿意 | I82: 資訊分享 | J82: 純分享 | K82: 直接相關 | L82: null | M82: Tesla Model 3, Tesla Model Y | N82: null | O82: null | P82: 80 | Q82: 21 | R82: 1
A83: https://www.facebook.com/groups/hkevdiary/permalink/1611909810222012/ | B83: Babamui Wong | C83: 單幢樓樓下車場無得叉 想問下元朗區ching 近雞地邊度叉電最抵又唔使排？ | D83: 2025/11/25 | G83: 中性 | H83: 疑問 | I83: 疑問/求助 | J83: 求助 | K83: 直接相關 | L83: 元朗雞地 | M83: null | N83: null | O83: null | P83: 10 | Q83: 11 | R83: 0
A84: https://www.facebook.com/groups/hkevdiary/permalink/1610321927047467/ | B84: SuperMe Lim | C84: 請問有冇人知，九龍灣大昌充電站，如果過咗90分鐘要唔要罰錢？ 謝謝 | D84: 2025/11/23 | G84: 中性 | H84: 疑問 | I84: 疑問/求助 | J84: 求助 | K84: 直接相關 | L84: 九龍灣大昌 | M84: null | N84: null | O84: null | P84: 6 | Q84: 4 | R84: 1
A85: https://www.facebook.com/groups/hkevdiary/permalink/1607474347332225/ | B85: Samantha Vlog | C85: 新款電動Cayenne發佈 option有得揀無線充電最高11kW | D85: 2025/11/19 | G85: 中性 | H85: 陳述 | I85: 資訊分享 | J85: 純分享 | K85: 直接相關 | L85: null | M85: Porsche Cayenne | N85: null | O85: 無線充電 11kW | P85: 41 | Q85: 1 | R85: 0
A86: https://www.facebook.com/groups/hkevdiary/permalink/1606542704092056/ | B86: Anonymous participant | C86: 強烈譴責特斯拉香港停止內地使用車內網絡功能，之前宣傳單張就寫仍可繼續使用，原來係欺騙消費者，而家就扮傻，手法極其惡劣，呼籲大家抵制佢 | D86: 2025/11/18 | G86: 負面 | H86: 生氣 | I86: 顧客服務/投訴 | J86: 有行動意向 | K86: 間接相關 | L86: null | M86: null | N86: null | O86: null | P86: 77 | Q86: 41 | R86: 0
A87: https://www.facebook.com/groups/hkevdiary/permalink/1606228694123457/ | B87: Just Be You | C87: 依家北上，架車已經用唔到數據，突然cut晒，遙控車嘅功能無晒，北上留意。 | D87: 2025/11/18 | F87: https://scontent-atl3-3.xx.fbcdn.net/v/t39.30808-6/583336755_122416726862205027_6115892718655432675_n.jpg?stp=dst-jpg_s720x720_tt6&_nc_cat=109&ccb=1-7&_nc_sid=aa7b47&_nc_ohc=A6tVPnnE6dIQ7kNvwE3U2He&_nc_oc=AdrJIZjDK_Jg-cKmQ03meQf8pVkBStwL8ZfAEU3ACMW2L_ghLEYRmAxm2jWL6MS0nlM&_nc_zt=23&_nc_ht=scontent-atl3-3.xx&_nc_gid=69e9Gf_JHY-jLh27f8HDjA&_nc_ss=72289&oh=00_Af7NZfXz9v4ojaKORnzFaZdU_jpq7V6GEt9mrpWC31pPdw&oe=6A119DDC | G87: 中性 | H87: 陳述 | I87: 其他 | J87: 純分享 | K87: 直接相關 | L87: null | M87: null | N87: null | O87: null | P87: 129 | Q87: 93 | R87: 4
A88: https://www.facebook.com/groups/hkevdiary/permalink/1605753907504269/ | B88: Ricky Chen | C88: 又更新今個月收到Wall Connector充電費用資料 上次2189公里到而家行左3304公里 今次電費$216 / 充左185度電 = 1度電$1.167 今次行左1115公里 / 185度電 = 1度電6公里 $216 / 1115公里 = 1公里$0.193 | D88: 2025/11/17 | F88: https://scontent-sea5-1.xx.fbcdn.net/v/t39.30808-6/582329679_10162356528078741_4889534859537922655_n.jpg?stp=cp6_dst-jpg_p843x403_tt6&_nc_cat=107&ccb=1-7&_nc_sid=aa7b47&_nc_ohc=j5sFMMNlH9sQ7kNvwG_TlQi&_nc_oc=Adqy63wMCiuGsTDumvb0Aeg3ngWBVd-cFXK5Xz3OKhQKEFtOmB_8X2Y-nTScPpO52yU&_nc_zt=23&_nc_ht=scontent-sea5-1.xx&_nc_gid=eDO5GoebYH04PbJllyXhCg&_nc_ss=72289&oh=00_Af66mx_CFFQQp19hd_w7gxRXLbLWN5z3m0JO30A4P664xw&oe=6A117C96 | G88: 中性 | H88: 陳述 | I88: 收費/價錢 | J88: 純分享 | K88: 直接相關 | L88: null | M88: null | N88: null | O88: null | P88: 34 | Q88: 7 | R88: 0
A89: https://www.facebook.com/groups/hkevdiary/permalink/1604752654271061/ | B89: Samantha Vlog | C89: 大家覺得會唔會續 A. 續，首次登記稅寬減維持一樣 B. 續，首次登記稅寬減再度調低 C. 唔續 | D89: 2025/11/16 | G89: 中性 | H89: 疑問 | I89: 疑問/求助 | J89: 求助 | K89: 直接相關 | L89: null | M89: null | N89: null | O89: null | P89: 20 | Q89: 34 | R89: 1
A90: https://www.facebook.com/groups/hkevdiary/permalink/1603991624347164/ | B90: Samantha Vlog | C90: S3XY Buttons 新產品➡️《Dash 多功能觸控自訂錶板》 ✅支援 Apple CarPlay & Android Auto ✅實時監測車輛數據 (電池損耗、溫度、摩打輸出等等) ✅盲點提示、剎車燈、AP燈效 ✅提供部分 S3XY Buttons 功能 (調較Regen級數、電池預熱等等) ✅8頁版面自由組合 (包括個別 Widget 大小、擺位) ✅磁吸安裝背架，自選擺位 無損簡易安裝 (Model 3/Y 全系列 可以安裝✅) # 優惠碼"SAMANTHA" 減10% 1️⃣如果本身冇 S3XY Buttons / Knob，可以 Dash (w/ Gen 2 Commander) + 兩粒 Buttons 咁組合，Buttons 幾年前一出已經開始用，真心推薦 [https://www.enhauto.com/products/dash](https://www.enhauto.com/products/dash) 2️⃣本身有 Gen 2 Commander 嘅只需要加一個 Dash [https://www.enhauto.com/products/dash-standalone](https://www.enhauto.com/products/dash-standalone) | D90: 2025/11/15 | G90: 正面 | H90: 期待 | I90: 廣告/促銷 | J90: 廣告 | K90: 間接相關 | L90: null | M90: Tesla Model 3, Tesla Model Y | N90: null | O90: null | P90: 47 | Q90: 36 | R90: 1
A91: https://www.facebook.com/groups/hkevdiary/permalink/1603577031055290/ | B91: Anonymous participant | C91: 話說今日去大搶幫部LEAF做保養 佢話我成日用快充 日後粒電有事會吾保 佢話車主手册有寫㗎 | D91: 2025/11/14 | G91: 中性 | H91: 陳述 | I91: 充電速度 | J91: 純分享 | K91: 直接相關 | L91: null | M91: Nissan LEAF | N91: null | O91: 快充 | P91: 12 | Q91: 22 | R91: 0
A92: https://www.facebook.com/groups/hkevdiary/permalink/1603323471080646/ | B92: Samantha Vlog | C92: iPhone & Tesla 用家福音 原生喺大Mon用到高德地圖應該係好多車主想要嘅功能 | D92: 2025/11/14 | G92: 正面 | H92: 期待 | I92: 資訊分享 | J92: 純分享 | K92: 間接相關 | L92: null | M92: Tesla | N92: null | O92: null | P92: 54 | Q92: 12 | R92: 1
A93: https://www.facebook.com/groups/hkevdiary/permalink/1602153694530957/ | B93: Anonymous participant | C93: 想买电动车，有边噶冇限住定期返厂都有保养 | D93: 2025/11/12 | F93: https://scontent-hou1-1.xx.fbcdn.net/v/t39.30808-6/580704201_804270072452801_5411695677419719263_n.jpg?stp=cp6_dst-jpg_p843x403_tt6&_nc_cat=110&ccb=1-7&_nc_sid=aa7b47&_nc_ohc=2X6aaFx3PQQQ7kNvwGJ-Fhq&_nc_oc=AdrxdHQCzGd69qjdP6caDw2hVfBF9FI78lXb5TPLv_3-4ztebmNhSJQBLlUadKZNlhs&_nc_zt=23&_nc_ht=scontent-hou1-1.xx&_nc_gid=SjWk3H8ZmjzM0oI0C2NB6Q&_nc_ss=72289&oh=00_Af40e9h-sp1WlhpFIjgDXFTIcziJdNUWGOqFLyPKxPKB0Q&oe=6A118393 | G93: 中性 | H93: 疑問 | I93: 疑問/求助 | J93: 求助 | K93: 直接相關 | L93: null | M93: null | N93: null | O93: null | P93: 20 | Q93: 29 | R93: 0
A94: https://www.facebook.com/groups/hkevdiary/permalink/1601462771266716/ | B94: Samantha Vlog | C94: 有冇用呢？ 不過都叫多個途徑睇到囉 | D94: 2025/11/12 | G94: 中性 | H94: 疑問 | I94: 疑問/求助 | J94: 求助 | K94: 直接相關 | L94: null | M94: null | N94: null | O94: null | P94: 14 | Q94: 0 | R94: 0
A95: https://www.facebook.com/groups/hkevdiary/permalink/1600511671361826/ | B95: Samantha Vlog | C95: 內地Model Y L限定 V2L Adapter | D95: 2025/11/11 | G95: 中性 | H95: 陳述 | I95: 安裝/硬件/技術 | J95: 純分享 | K95: 直接相關 | L95: null | M95: Tesla Model Y | N95: null | O95: V2L | P95: 18 | Q95: 1 | R95: 0
A96: https://www.facebook.com/groups/hkevdiary/permalink/1597831854963141/ | B96: Anonymous participant | C96: 考慮緊買電車，成日都講話大灣區聯保，但又聽人講電車邊有咁多嘢要整 想問揸過電車嘅朋友，其實個聯保係咪真係咁有用？ | D96: 2025/11/08 | G96: 中性 | H96: 疑問 | I96: 疑問/求助 | J96: 求助 | K96: 直接相關 | L96: null | M96: null | N96: null | O96: null | P96: 1 | Q96: 8 | R96: 0
A97: https://www.facebook.com/groups/hkevdiary/permalink/1594749981937995/ | B97: Yat Sing Cheung | C97: 新手入坑，想請問各位，冇自己充電位既話，值唔值得買一條AC充電線用黎出去用中叉？因為見好多中叉站都要自備線 | D97: 2025/11/04 | G97: 中性 | H97: 疑問 | I97: 疑問/求助 | J97: 求助 | K97: 直接相關 | L97: null | M97: null | N97: null | O97: 中充, AC | P97: 3 | Q97: 22 | R97: 0
A98: https://www.facebook.com/groups/hkevdiary/permalink/1594765315269795/ | B98: Anonymous participant | C98: 有冇師兄部byd軚盤都甩皮 | D98: 2025/11/04 | F98: https://scontent-lga3-2.xx.fbcdn.net/v/t39.30808-6/574886957_1345686466932945_7544620143430161837_n.png?stp=dst-png_p526x296&_nc_cat=101&ccb=1-7&_nc_sid=aa7b47&_nc_ohc=g5ljdKwVA88Q7kNvwFDalED&_nc_oc=AdrFrWswI8ZM1juOXY_I6pPsCqvRhu9CpkGnJLZB8Ktci_uFuYHqIgKGPrIjQDZ4Z8s&_nc_zt=23&_nc_ht=scontent-lga3-2.xx&_nc_gid=ZgtxN2u20xDATpOjKvXtNg&_nc_ss=72289&oh=00_Af6_OzfDzyhZhYmRCtwYBPt3j44jFaA9QQOhhLrnjxs5qg&oe=6A1186E9 | G98: 中性 | H98: 疑問 | I98: 疑問/求助 | J98: 求助 | K98: 間接相關 | L98: null | M98: BYD | N98: null | O98: null | P98: 108 | Q98: 68 | R98: 2
A99: https://www.facebook.com/groups/hkevdiary/permalink/1594111115335215/ | B99: Anonymous participant | C99: 請問各位，想借p loan 出model y 或者smart #5，借5年邊間銀行息口抵？ thx | D99: 2025/11/04 | G99: 中性 | H99: 疑問 | I99: 疑問/求助 | J99: 求助 | K99: 間接相關 | L99: null | M99: Tesla Model Y, Smart #5 | N99: null | O99: null | P99: 5 | Q99: 11 | R99: 0
A100: https://www.facebook.com/groups/hkevdiary/permalink/1593575188722141/ | B100: Donlex Wong | C100: 唔好意思，想請問珠海環宇城特斯拉歐錶充電解地鎖密碼幾多號？麻煩晒咁多位師兄 | D100: 2025/11/03 | G100: 中性 | H100: 疑問 | I100: 疑問/求助 | J100: 求助 | K100: 直接相關 | L100: 珠海環宇城 | M100: Tesla | N100: null | O100: null | P100: 0 | Q100: 3 | R100: 0
...

Sheet 1 Full Data
